Workbook
Name Slicer_Brand: #N/A
Name Slicer_Category: #N/A

Sheet Customer_Dim
A1: Customer_ID | B1: Name | C1: Age | D1: Gender | E1: City | F1: State | G1: Country | H1: Loyalty_Level
A2: CUST1000 | B2: sheena bonilla | C2: 55 | D2: Male | E2: Donaldton | F2: North Carolina | G2: USA
A3: CUST1001 | B3: Eugene Nelson | C3: 26 | D3: Female | E3: Phillipsmouth | F3: North Dakota | G3: USA | H3: Platinum
A4: CUST1002 | B4: dr. Benjamin Price | C4: 29 | D4: Female | E4: Kylebury | F4: Alabama | G4: USA | H4: Platinum
A5: CUST1003 | B5: jeremy harris | C5: 59 | D5: Female | E5: Thomastown | F5: Ohio | G5: USA | H5: Bronze
A6: CUST1004 | B6: Caroline Collins | C6: 64 | D6: Female | E6: Nicholasshire | F6: California | G6: USA | H6: Silver
A7: CUST1005 | B7: Christine Vaughn | C7: 24 | D7: Male | E7: East Amandamouth | F7: Oregon | G7: USA | H7: Bronze
A8: CUST1006 | B8: Amber Jackson | C8: 29 | D8: Female | E8: Deborahborough | F8: South Dakota | G8: USA | H8: Platinum
A9: CUST1007 | B9: Daniel Boyd | C9: 29 | D9: Female | E9: West Pamelafurt | F9: West Virginia | G9: USA | H9: Bronze
A10: CUST1008 | B10: Melissa Howard | C10: 53 | D10: Female | E10: Maynardton | F10: New Hampshire | G10: USA | H10: Gold
A11: CUST1009 | B11: Ms. Maria Leach | C11: 64 | D11: Male | E11: Melissashire | F11: Pennsylvania | G11: USA | H11: Platinum
A12: CUST1010 | B12: Dominic Page | C12: 53 | D12: Male | E12: Port Michaelburgh | F12: Pennsylvania | G12: USA | H12: Bronze
A13: CUST1011 | B13: Brian Lopez | C13: 28 | D13: Female | E13: East Krista | F13: New York | G13: USA | H13: Gold
A14: CUST1012 | B14: Kenneth Lambert | C14: 55 | D14: Female | E14: North Kathryn | F14: Kansas | G14: USA | H14: Platinum
... A19: CUST1017 | B19: Adam Cruz | C19: 60 | D19: Female | E19: Brandonville | F19: Georgia | G19: USA | H19: Platinum
A20: CUST1018 | B20: Rhonda Moss | C20: 43 | D20: Male | E20: South William | F20: Kansas | G20: USA
A21: CUST1019 | B21: Michael Torres | C21: 46 | D21: Female | E21: Gonzalezfort | F21: New Jersey | G21: USA | H21: Platinum
A22: CUST1020 | B22: Bridget Allen | C22: 59 | D22: Male | E22: Lake Shaneburgh | F22: Delaware | G22: USA | H22: Silver
A23: CUST1021 | B23: Jeff Martinez | C23: 36 | D23: Female | E23: Smithburgh | F23: Oklahoma | G23: USA | H23: Gold
A24: CUST1022 | B24: paul fox | C24: 33 | D24: Female | E24: Michaelton | F24: Hawaii | G24: USA | H24: Silver
A25: CUST1023 | B25: Jonathan Steele | C25: 52 | D25: Female | E25: Molinabury | F25: Oregon | G25: USA | H25: Silver
A26: CUST1024 | B26: Heather Collins | C26: 40 | D26: Male | E26: Rogerschester | F26: Idaho | G26: USA | H26: Platinum
A27: CUST1025 | B27: Diana Taylor | C27: 59 | D27: Female | E27: Vasqueztown | F27: California | G27: USA | H27: Bronze
A28: CUST1026 | B28: Amber Carlson | C28: 18 | D28: Female | E28: East Michellemouth | F28: Missouri | G28: USA | H28: Gold
A29: CUST1027 | B29: Leslie Johnson | C29: 31 | D29: Male | E29: Mollyshire | F29: Utah | G29: USA
A30: CUST1028 | B30: Joshua Ryan | C30: 27 | D30: Female | E30: New David | F30: New Jersey | G30: USA | H30: Platinum
A31: CUST1029 | B31: David Arnold | C31: 54 | D31: Female | E31: East Jennifer | F31: California | G31: USA | H31: Silver
A32: CUST1030 | B32: Jessica Acevedo | C32: 64 | D32: Female | E32: Amybury | F32: Pennsylvania | G32: USA | H32: Bronze
A33: CUST1031 | B33: Sarah Vance | C33: 41 | D33: Male | E33: Johnsonville | F33: Oregon | G33: USA | H33: Silver
A34: CUST1032 | B34: Mike Jennings | C34: 48 | D34: Female | E34: Fostermouth | F34: Arizona | G34: USA | H34: Gold
A35: CUST1033 | B35: Robert Jones DDS | C35: 25 | D35: Male | E35: Tristanton | F35: Oklahoma | G35: USA | H35: Platinum
A36: CUST1034 | B36: Christopher Olson | C36: 27 | D36: Female | E36: West Richard | F36: Maryland | G36: USA | H36: Platinum
A37: CUST1035 | B37: Rachel Myers | C37: 52 | D37: Male | E37: Robertberg | F37: North Dakota | G37: USA | H37: Silver
A38: CUST1036 | B38: Thomas Phillips | C38: 20 | D38: Female | E38: Luisfurt | F38: Georgia | G38: USA | H38: Gold
A39: CUST1037 | B39: Christopher Carter | C39: 27 | D39: Female | E39: Brendastad | F39: South Dakota | G39: USA
A40: CUST1038 | B40: Deanna Simpson | C40: 35 | D40: Female | E40: Brownport | F40: North Dakota | G40: USA | H40: Bronze
A41: CUST1039 | B41: Tonya Reynolds | C41: 55 | D41: Female | E41: Darleneton | F41: Michigan | G41: USA | H41: Gold
A42: CUST1040 | B42: Eric Vega | C42: 50 | D42: Male | E42: Williamsonland | F42: Kansas | G42: USA | H42: Gold
A43: CUST1041 | B43: James Gibbs | C43: 21 | D43: Male | E43: Mooneyshire | F43: Alaska | G43: USA | H43: Platinum
A44: CUST1042 | B44: William Martin | C44: 19 | D44: Male | E44: Ryanburgh | F44: Connecticut | G44: USA | H44: Platinum
A45: CUST1043 | B45: Joseph Snow | C45: 45 | D45: Male | E45: South Michaelfort | F45: Vermont | G45: USA | H45: Gold
A46: CUST1044 | B46: Denise Williams | C46: 34 | D46: Male | E46: Christianstad | F46: Hawaii | G46: USA | H46: Bronze
A47: CUST1045 | B47: Jordan Jackson DDS | C47: 54 | D47: Male | E47: North Johnview | F47: Arizona | G47: USA | H47: Gold
A48: CUST1046 | B48: Michelle Garcia DDS | C48: 55 | D48: Female | E48: Perezbury | F48: Ohio | G48: USA | H48: Platinum
A49: CUST1047 | B49: Gina Knight | C49: 54 | D49: Female | E49: Lake Roberthaven | F49: Nevada | G49: USA | H49: Silver
A50: CUST1048 | B50: April Mullins | C50: 54 | D50: Male | E50: Dawsonbury | F50: North Carolina | G50: USA | H50: Platinum
A51: CUST1049 | B51: Timothy Weaver | C51: 45 | D51: Female | E51: New Amy | F51: Ohio | G51: USA | H51: Gold
... A501: C-1499 | B501: Philip Pennington | C501: 27 | D501: Female | E501: East Valerieview | F501: Oregon | G501: USA | H501: Platinum

Sheet Product_Dim
A1: Product_ID | B1: Product_Name | C1: Category | D1: Sub_Category | E1: Brand | F1: Cost | G1: Stock
A2: PROD0 | B2: Brother Laser Printer | C2: Electronics | D2: Computer | E2: Hunt Inc | F2: 112.42 | G2: 416
A3: PROD1 | B3: Men's Graphic T-Shirt | C3: Clothing | D3: Tops | E3: Terry-Moore | F3: 342.56 | G3: 181
A4: PROD2 | B4: Women's Casual Hoodie | C4: Clothing | D4: Outerwear | E4: Sims Inc | G4: 352
A5: P-3 | B5: Men's Running Jacket | C5: Clothing | D5: Outerwear | E5: Pineda Ltd | F5: 364.67 | G5: 452
A6: PROD4 | B6: Women's Yoga Pants | C6: Clothing | D6: Bottoms | E6: Gonzales-Davis | F6: 306.46 | G6: 487
A7: PROD5 | B7: Men's Leather Belt | C7: Clothing | D7: Accessories | E7: Baldwin, Garza and Gonzalez | F7: 261 | G7: 59
A8: PROD6 | B8: Herbal Face Moisturizer | C8: Beauty | D8: Skincare | E8: Davidson PLC | F8: 312.8 | G8: 350
A9: PROD7 | B9: LED Table Lamp | C9: Home | D9: Lighting | E9: Harrell LLC | F9: 218.86 | G9: 170
A10: PROD8 | B10: Wireless Bluetooth Earbuds | C10: Electronics | D10: Audio | E10: Perez-Johnston | F10: 439.07 | G10: 142
A11: PROD9 | B11: Adjustable Dumbbell Set | C11: Sports | D11: Fitness | E11: Hill PLC | F11: 495.72 | G11: 323
A12: PROD10 | B12: Ceramic Kitchen Bowl Set | C12: Home | D12: Kitchen | E12: Hamilton Group | F12: 298.86 | G12: 308
A13: PROD11 | B13: HD Smart TV Stick | C13: Electronics | D13: Accessories | E13: Gibson, Hobbs and Weaver | F13: 449.4
A14: PROD12 | B14: Hair Strengthening Shampoo | C14: Beauty | D14: Haircare | E14: Rice LLC | F14: 115.82 | G14: 460
A15: PROD13 | B15: USB-C Fast Charger | C15: Electronics | D15: Accessories | E15: Dawson-Perkins | F15: 242.23 | G15: 453
A16: PROD14 | B16: Decorative Wall Mirror | C16: Home | D16: Decor | E16: Luna, Anderson and Bowman | F16: 48.01 | G16: 439
A17: PROD15 | B17: 4K Home Projector | C17: Electronics | D17: Appliances | E17: Thomas LLC | F17: 465.34 | G17: 301
A18: P-16 | B18: Beard Grooming Kit | C18: Beauty | D18: Grooming | E18: Erickson-Green | F18: 337.42 | G18: 256
A19: PROD17 | B19: Soccer Training Cone Set | C19: Sports | D19: Accessories | E19: Ford, Murphy and Wilson | F19: 144.53 | G19: 367
A20: PROD18 | B20: Women's Denim Jeans | C20: Clothing | D20: Bottoms | E20: Guerra-Hendrix | G20: 343
A21: PROD19 | B21: Knee Support Brace | C21: Sports | D21: Equipment | E21: May-Reese | F21: 21.34 | G21: 65
A22: PROD20 | B22: Outdoor Sports Water Bottle | C22: Sports | D22: Accessories | E22: Soto-Ellis | F22: 131.51
A23: PROD21 | B23: Multi-Purpose Storage Box | C23: Home | D23: Storage | E23: Gardner-Montes | F23: 123.46 | G23: 76
A24: PROD22 | B24: Carbon Fiber Tennis Racket | C24: Sports | D24: Equipment | E24: Flores, Pineda and Rodriguez | F24: 484.62 | G24: 432
A25: PROD23 | B25: Men's Formal Shirt | C25: Clothing | D25: Tops | E25: Moon, Mora and Santos | G25: 360
A26: PROD24 | B26: Foldable Camping Chair | C26: Sports | D26: Outdoor | E26: Cook Ltd | F26: 166.06 | G26: 340
A27: PROD25 | B27: Women's Scarf Set | C27: Clothing | D27: Accessories | E27: Brown and Sons | F27: 174.02 | G27: 268
A28: PROD26 | B28: Wireless Bluetooth Speaker | C28: Electronics | D28: Audio | E28: Reed-Schmidt | F28: 322.41 | G28: 213
A29: PROD27 | B29: Decorative Floor Vase | C29: Home | D29: Decor | E29: Khan, Jones and Paul | G29: 378
A30: PROD28 | B30: Sports Stopwatch Timer | C30: Sports | D30: Accessories | E30: Burns-Hansen | F30: 38.76 | G30: 137
A31: PROD29 | B31: Fabric Sofa Throw Blanket | C31: Home | D31: Decor | E31: Hoffman Group | F31: 218.48 | G31: 276
A32: PROD30 | B32: Stainless Steel Cutlery Set | C32: Home | D32: Kitchen | E32: Stevens, Fernandez and Martin | F32: 19.52 | G32: 57
A33: PROD31 | B33: Basketball | C33: Sports | D33: Team Sports | E33: Nolan-Snow | F33: 204.39 | G33: 281
A34: PROD32 | B34: Vitamin C Face Serum | C34: Beauty | D34: Skincare | E34: Griffin Ltd | F34: 283.83 | G34: 244
A35: PROD33 | B35: Modern Wall Clock | C35: Home | D35: Decor | E35: Weiss-Watson | F35: 179.77 | G35: 305
A36: PROD34 | B36: Gaming Mechanical Keyboard | C36: Electronics | D36: Computer | E36: Lucero LLC | F36: 419.28 | G36: 86
A37: PROD35 | B37: Bedroom Table Lamp | C37: Home | D37: Lighting | E37: Jones LLC | F37: 382.22 | G37: 329
A38: PROD36 | B38: Women's Summer Dress | C38: Clothing | D38: Tops | E38: Smith-Mills | F38: 223.43 | G38: 154
A39: PROD37 | B39: Men's Casual Sneakers | C39: Clothing | D39: Footwear | E39: Hogan-Lee | F39: 353.47 | G39: 214
A40: PROD38 | B40: Sports Water Hydration Pack | C40: Sports | D40: Outdoor | E40: Sims-Smith | F40: 135.61 | G40: 394
A41: PROD39 | B41: Portable Power Bank | C41: Electronics | D41: Mobile | E41: Cummings and Sons | F41: 326.06 | G41: 301
... A48: PROD46 | B48: Men's Winter Jacket | C48: Clothing | D48: Outerwear | E48: Kelly, Smith and Perez | F48: 167.34 | G48: 296
A49: PROD47 | B49: Makeup Brush Set | C49: Beauty | D49: Makeup | E49: Cook Inc | G49: 431
A50: PROD48 | B50: Car Dashboard Phone Holder | C50: Electronics | D50: Accessories | E50: Byrd, Stewart and Valdez | F50: 177.98 | G50: 103
A51: PROD49 | B51: Men's Roll-On Perfume | C51: Beauty | D51: Fragrance | E51: Sullivan and Sons | F51: 43.29 | G51: 267
A52: PROD50 | B52: Boxing Hand Wraps | C52: Sports | D52: Fitness | E52: Smith-King | F52: 190.29 | G52: 260
A53: PROD51 | B53: HDMI Cable – 2m | C53: Electronics | D53: Accessories | E53: Bautista, Green and Hale | F53: 88.49 | G53: 246
A54: PROD52 | B54: Rugby Ball | C54: Sports | D54: Team Sports | E54: Harris Inc | F54: 212.26 | G54: 82
A55: PROD53 | B55: Men's Track Pants | C55: Clothing | D55: Bottoms | E55: Hamilton, Woods and Walker | F55: 386.56 | G55: 125
A56: PROD54 | B56: Sports Stopwatch Pro | C56: Sports | D56: Accessories | E56: Thompson-French | F56: 434.84 | G56: 185
A57: PROD55 | B57: Ceramic Plant Pot | C57: Home | D57: Decor | E57: Hatfield, Baird and Torres | F57: 81.75
A58: PROD56 | B58: Premium Blanket Throw | C58: Home | D58: Decor | E58: Hernandez, Kennedy and Porter | F58: 461.47 | G58: 190
A59: PROD57 | B59: Foam Roller | C59: Sports | D59: Fitness | E59: Atkinson, Camacho and Oliver | F59: 30.62 | G59: 138
A60: PROD58 | B60: Womens Cotton Scarf | C60: Clothing | D60: Accessories | E60: Shepherd-Gould | F60: 113.83 | G60: 485
A61: PROD59 | B61: Men's Hair Styling Gel | C61: Beauty | D61: Haircare | E61: Cline-Mccarthy | F61: 17.31 | G61: 399
A62: PROD60 | B62: Luxury Perfume Spray | C62: Beauty | D62: Fragrance | E62: Gibson, Green and Lopez | F62: 482.75 | G62: 444
A63: PROD61 | B63: Tennis Ball 3-Pack | C63: Sports | D63: Equipment | E63: Lopez LLC | F63: 103.45 | G63: 465
A64: PROD62 | B64: Laptop Cooling Pad | C64: Electronics | D64: Computer | E64: Murray, Gould and Ware | F64: 86.42 | G64: 222
A65: PROD63 | B65: Organic Sunscreen Lotion | C65: Beauty | D65: Skincare | E65: Anderson-Riley | F65: 266.86 | G65: 458
A66: PROD64 | B66: Matte Lipstick Set | C66: Beauty | D66: Makeup | E66: Zhang Inc | F66: 299.11 | G66: 118
A67: PROD65 | B67: Adjustable Dumbbells 20kg | C67: Sports | D67: Fitness | E67: Montgomery, Benton and Miller | F67: 240.63 | G67: 423
A68: PROD66 | B68: Women's Hair Dryer Brush | C68: Beauty | D68: Haircare | E68: Torres, Spencer and Potter | F68: 340.39 | G68: 177
A69: PROD67 | B69: Smart LED Light Strip | C69: Electronics | D69: Accessories | E69: Flores-Davis | F69: 349.17 | G69: 476
... A84: PROD82 | B84: Fitness Resistance Bands | C84: Sports | D84: Fitness | E84: Reese-Watson | F84: 152.92 | G84: 281
A85: PROD83 | B85: Hydrating Face Cleanser | C85: Beauty | D85: Skincare | E85: Butler Group | G85: 159
A86: PROD84 | B86: Wooden Bookshelf | C86: Home | D86: Furniture | E86: Collins-Stephenson | F86: 388.46 | G86: 208
A87: PROD85 | B87: Women's Beanie Hat | C87: Clothing | D87: Accessories | E87: Richardson-Carrillo | F87: 119.57 | G87: 210
A88: PROD86 | B88: Kitchen Cutting Board | C88: Home | D88: Kitchen | E88: Taylor, Dodson and Johnston | F88: 176.07 | G88: 82
A89: PROD87 | B89: LED Bedside Lamp | C89: Home | D89: Lighting | E89: Aguilar, Horton and Lewis | F89: 371.38 | G89: 220
A90: PROD88 | B90: Sports Wrist Sweatbands | C90: Sports | D90: Accessories | E90: Olsen-Daniels | F90: 131.24 | G90: 232
A91: PROD89 | B91: Face Foundation Kit | C91: Beauty | D91: Makeup | E91: Taylor-Elliott | F91: 183.04 | G91: 457
A92: PROD90 | B92: Gaming Mouse Pad XL | C92: Electronics | D92: Accessories | E92: Sharp, Taylor and Rodriguez | F92: 340.14 | G92: 361
A93: PROD91 | B93: Women's High Heels | C93: Clothing | D93: Footwear | E93: Smith-Charles | F93: 438.25 | G93: 496
A94: PROD92 | B94: Microwave Oven | C94: Home | D94: Appliances | E94: Green, Powell and Palmer | F94: 447.43 | G94: 191
A95: PROD93 | B95: USB-C Laptop Charger | C95: Electronics | D95: Computer | E95: Martin LLC | F95: 377.52 | G95: 485
A96: PROD94 | B96: Vitamin E Body Lotion | C96: Beauty | D96: Skincare | E96: Hoffman-Williams | F96: 358.47 | G96: 213
A97: PROD95 | B97: Sports Stopwatch Basic | C97: Sports | D97: Accessories | E97: Wilson Group | F97: 60.65 | G97: 75
... A101: PROD99 | B101: Stainless Steel Cookware Set | C101: Home | D101: Kitchen | E101: Campbell Ltd | F101: 201.41 | G101: 146

Sheet Store_Dim
A1: Store_ID | B1: Store_Name | C1: Region | D1: City | E1: Store_Type
A2: STORE0 | B2: Rivera-Warner | C2: East | D2: Washingtonfurt | E2: Flagship
A3: STORE1 | B3: Martinez, Adkins and Johnson | C3: North | D3: Danielmouth | E3: Flagship
A4: STORE2 | B4: Black-Horn | C4: South | D4: North Nancyview | E4: Outlet
A5: STORE3 | B5: Johnson-Wright | C5: North | D5: Hoodberg | E5: Outlet
A6: STORE4 | B6: Alexander Group | C6: South | D6: Port Sharon | E6: Online
A7: STORE5 | B7: Gray Ltd | C7: North | D7: New Michaelchester | E7: Outlet
A8: STORE6 | B8: Benson-Elliott | C8: East | D8: Port Josephberg | E8: Online
A9: STORE7 | B9: Martinez-Mullins | C9: South | D9: Williamsfurt | E9: Online
A10: STORE8 | B10: Bean, Jones and Park | C10: West | D10: Thompsonborough | E10: Online
A11: STORE9 | B11: Moore, Padilla and Butler | C11: South | D11: East Johnstad | E11: Flagship
A12: STORE10 | B12: Hill, Wagner and Ballard | C12: East | D12: East Davidville | E12: Online
... A21: STORE19 | B21: Mann-Austin | C21: East | D21: Vasquezborough | E21: Online

Sheet Sales_Fact
A1: Sales_ID | B1: Order_Date | C1: Customer_ID | D1: Product_ID | E1: Store_ID | F1: Quantity | G1: Unit_Price | H1: Discount | I1: Payment_Type | J1: Total_Amount
A2: SALE0 | B2: 45480 | C2: CUST1409 | D2: PROD97 | E2: STORE3 | F2: 1 | G2: 218.04 | H2: 0.09 | I2: Credit Card | J2: 198.4164
A3: SALE1 | B3: 45285 | C3: CUST1467 | D3: PROD74 | E3: STORE17 | F3: 3 | G3: 104.47 | H3: 0.27 | I3: PayPal | J3: 228.7893
A4: SALE2 | B4: 45446 | C4: CUST1056 | D4: PROD49 | E4: STORE8 | F4: 4 | G4: 914.05 | H4: 0.25 | I4: Credit Card | J4: 2742.15
A5: SALE3 | B5: 45259 | C5: CUST1346 | D5: PROD76 | E5: STORE8 | F5: 1 | G5: 921.51 | H5: 0.16 | I5: COD | J5: 774.0684
A6: SALE4 | B6: 45297 | C6: CUST1493 | D6: PROD59 | E6: STORE5 | F6: 3 | G6: 745.3 | H6: 0.18 | I6: Credit Card | J6: 1833.438
A7: SALE5 | B7: 45499 | C7: CUST1116 | D7: PROD15 | E7: STORE7 | F7: 3 | G7: 147.01 | H7: 0.19 | I7: COD | J7: 357.2343
A8: SALE6 | B8: 45850 | C8: CUST1016 | D8: PROD56 | E8: STORE4 | F8: 2 | G8: 785.31 | H8: 0.15 | I8: PayPal | J8: 1335.027
A9: SALE7 | B9: 45248 | C9: CUST1152 | D9: PROD70 | E9: STORE8 | F9: 4 | G9: 342.39 | H9: 0.23 | I9: PayPal | J9: 1054.5612
A10: SALE8 | B10: 45781 | C10: CUST1187 | D10: PROD99 | E10: STORE5 | G10: 448.25 | H10: 0.07 | I10: PayPal | J10: 1250.6175
A11: SALE9 | B11: 45869 | C11: CUST1464 | D11: PROD33 | E11: STORE0 | F11: 2 | G11: 873.17 | H11: 0.23 | I11: PayPal | J11: 1344.6818
A12: SALE10 | B12: 45335 | C12: CUST1065 | D12: PROD24 | E12: STORE14 | F12: 1 | G12: 278.63 | H12: 0.07 | I12: Credit Card | J12: 259.1259
A13: SALE11 | B13: 45801 | C13: CUST1320 | D13: PROD39 | E13: STORE1 | F13: 4 | G13: 286.92 | H13: 0.17 | I13: Credit Card | J13: 952.5744
A14: SALE12 | B14: 45528 | C14: CUST1237 | D14: PROD88 | E14: STORE4 | F14: 4 | G14: 644.58 | H14: 0.01 | I14: Credit Card | J14: 2552.5368
A15: SALE13 | B15: 45875 | C15: CUST1443 | D15: PROD34 | E15: STORE16 | F15: 2 | G15: 316.9 | H15: 0.3 | I15: PayPal | J15: 443.66
A16: SALE14 | B16: 45829 | C16: CUST1348 | D16: PROD24 | E16: STORE15 | F16: 4 | G16: 403.47 | H16: 0.29 | I16: PayPal | J16: 1145.8548
A17: SALE15 | B17: 45636 | C17: CUST1435 | D17: PROD36 | E17: STORE9 | G17: 871.34 | H17: 0.04 | I17: COD | J17: 2509.4592
A18: SALE16 | B18: 45913 | C18: CUST1276 | D18: PROD65 | E18: STORE19 | F18: 2 | G18: 451.98 | H18: 0.25 | I18: Credit Card | J18: 677.97
A19: SALE17 | B19: 45637 | C19: CUST1079 | D19: PROD27 | E19: STORE4 | F19: 2 | G19: 502.69 | H19: 0.23 | I19: Credit Card | J19: 774.1426
A20: SALE18 | B20: 45517 | C20: CUST1094 | D20: PROD39 | E20: STORE4 | F20: 2 | G20: 559.23 | H20: 0.25 | I20: COD | J20: 838.845
A21: SALE19 | B21: 45369 | C21: CUST1239 | D21: PROD60 | E21: STORE13 | F21: 4 | H21: 0.04 | I21: COD | J21: 1782.4512
A22: SALE20 | B22: 45843 | C22: CUST1144 | D22: PROD72 | E22: STORE17 | F22: 3 | G22: 986.04 | H22: 0.27 | I22: COD | J22: 2159.4276
A23: SALE21 | B23: 45447 | C23: CUST1396 | D23: PROD43 | E23: STORE18 | F23: 1 | G23: 589.56 | H23: 0.22 | I23: Credit Card | J23: 459.8568
A24: SALE22 | B24: 45394 | C24: CUST1476 | D24: PROD69 | E24: STORE10 | F24: 3 | G24: 979.42 | H24: 0.03 | I24: PayPal | J24: 2850.1122
A25: SALE23 | B25: 45466 | C25: CUST1368 | D25: PROD12 | E25: STORE8 | F25: 1 | G25: 719.28 | H25: 0.08 | I25: Credit Card | J25: 661.7376
A26: SALE24 | B26: 45908 | C26: CUST1186 | D26: PROD67 | E26: STORE6 | F26: 3 | G26: 77.6 | H26: 0.07 | I26: Credit Card | J26: 216.504
A27: SALE25 | B27: 45552 | C27: CUST1381 | D27: PROD5 | E27: STORE3 | F27: 4 | G27: 852.71 | H27: 0.14 | I27: PayPal | J27: 2933.3224
A28: SALE26 | B28: 45294 | C28: CUST1213 | D28: PROD98 | E28: STORE8 | F28: 4 | G28: 156.16 | I28: Credit Card | J28: 599.6544
A29: SALE27 | B29: 45710 | C29: CUST1200 | D29: PROD77 | E29: STORE8 | F29: 3 | G29: 815.49 | H29: 0.17 | I29: Credit Card | J29: 2030.5701
A30: SALE28 | B30: 45923 | C30: CUST1148 | D30: PROD13 | E30: STORE2 | F30: 2 | G30: 74.21 | H30: 0.11 | I30: PayPal | J30: 132.0938
A31: SALE29 | B31: 45302 | C31: CUST1348 | D31: PROD99 | E31: STORE3 | G31: 451.67 | H31: 0.15 | I31: Credit Card | J31: 1535.678
A32: SALE30 | B32: 45217 | C32: CUST1028 | D32: PROD5 | E32: STORE19 | F32: 1 | G32: 429.38 | H32: 0.13 | I32: PayPal | J32: 373.5606
A33: SALE31 | B33: 45593 | C33: CUST1412 | D33: PROD53 | E33: STORE12 | F33: 2 | G33: 148.96 | H33: 0.03 | I33: COD | J33: 288.9824
A34: SALE32 | B34: 45597 | C34: CUST1398 | D34: PROD75 | E34: STORE8 | F34: 4 | G34: 313.83 | H34: 0.08 | I34: Credit Card | J34: 1154.8944
A35: SALE33 | B35: 45620 | C35: CUST1453 | D35: PROD12 | E35: STORE6 | F35: 2 | G35: 717.31 | H35: 0.15 | I35: Credit Card | J35: 1219.427
A36: SALE34 | B36: 45215 | C36: CUST1344 | D36: PROD79 | E36: STORE1 | G36: 873.22 | H36: 0.18 | I36: Credit Card | J36: 2148.1212
A37: SALE35 | B37: 45878 | C37: CUST1218 | D37: PROD16 | E37: STORE3 | F37: 4 | G37: 109.36 | H37: 0.19 | I37: COD | J37: 354.3264
A38: SALE36 | B38: 45635 | C38: CUST1086 | D38: PROD5 | E38: STORE7 | F38: 3 | G38: 559.52 | H38: 0.16 | I38: PayPal | J38: 1409.9904
A39: SALE37 | B39: 45329 | C39: CUST1492 | D39: PROD10 | E39: STORE17 | F39: 3 | G39: 121.76 | H39: 0.27 | I39: PayPal | J39: 266.6544
A40: SALE38 | B40: 45378 | C40: CUST1189 | D40: PROD33 | E40: STORE13 | F40: 4 | G40: 735.32 | H40: 0.06 | I40: COD | J40: 2764.8032
A41: SALE39 | B41: 45264 | C41: CUST1431 | D41: PROD94 | E41: STORE3 | F41: 2 | G41: 600.73 | H41: 0.08 | I41: Credit Card | J41: 1105.3432
A42: SALE40 | B42: 45486 | C42: CUST1072 | D42: PROD26 | E42: STORE19 | F42: 2 | G42: 873.86 | H42: 0.07 | I42: COD | J42: 1625.3796
A43: SALE41 | B43: 45241 | C43: CUST1302 | D43: PROD23 | E43: STORE8 | F43: 3 | G43: 342.47 | H43: 0.08 | I43: PayPal | J43: 945.2172
A44: SALE42 | B44: 45649 | C44: CUST1335 | D44: PROD29 | E44: STORE9 | F44: 2 | G44: 915.15 | H44: 0.16 | I44: PayPal | J44: 1537.452
A45: SALE43 | B45: 45677 | C45: CUST1084 | D45: PROD33 | E45: STORE17 | G45: 863.11 | H45: 0.28 | I45: PayPal | J45: 1864.3176
A46: SALE44 | B46: 45538 | C46: CUST1203 | D46: PROD43 | E46: STORE12 | F46: 2 | G46: 209.32 | H46: 0.23 | I46: COD | J46: 322.3528
A47: SALE45 | B47: 45606 | C47: CUST1470 | D47: PROD59 | E47: STORE8 | F47: 4 | G47: 288.6 | H47: 0.09 | I47: PayPal | J47: 1050.504
A48: SALE46 | B48: 45570 | C48: CUST1070 | D48: PROD78 | E48: STORE16 | F48: 1 | G48: 418.69 | H48: 0.06 | I48: PayPal | J48: 393.5686
A49: SALE47 | B49: 45466 | C49: CUST1008 | D49: PROD30 | E49: STORE11 | F49: 1 | G49: 135.78 | H49: 0.14 | I49: PayPal | J49: 116.7708
A50: SALE48 | B50: 45218 | C50: CUST1203 | D50: PROD44 | E50: STORE17 | F50: 1 | G50: 517.13 | H50: 0.28 | I50: Credit Card | J50: 372.3336
A51: SALE49 | B51: 45607 | C51: CUST1420 | D51: PROD21 | E51: STORE16 | F51: 2 | G51: 384.66 | H51: 0.08 | I51: COD | J51: 707.7744
A52: SALE50 | B52: 45291 | C52: CUST1070 | D52: PROD52 | E52: STORE9 | F52: 3 | G52: 83.7 | H52: 0.24 | I52: PayPal | J52: 190.836
A53: SALE51 | B53: 45689 | C53: CUST1142 | D53: PROD69 | E53: STORE7 | F53: 3 | G53: 76.57 | H53: 0.26 | I53: Credit Card | J53: 169.9854
A54: SALE52 | B54: 45894 | C54: CUST1148 | D54: PROD89 | E54: STORE6 | F54: 3 | I54: Credit Card | J54: 486.0633
A55: SALE53 | B55: 45677 | C55: CUST1324 | D55: PROD20 | E55: STORE8 | F55: 1 | G55: 900.35 | H55: 0.13 | I55: COD | J55: 783.3045
A56: SALE54 | B56: 45706 | C56: CUST1095 | D56: PROD40 | E56: STORE10 | F56: 4 | G56: 428.09 | H56: 0.07 | I56: Credit Card | J56: 1592.4948
A57: SALE55 | B57: 45589 | C57: CUST1416 | D57: PROD49 | E57: STORE11 | F57: 2 | G57: 559.71 | H57: 0.3 | I57: COD | J57: 783.594
A58: SALE56 | B58: 45282 | C58: CUST1080 | D58: PROD34 | E58: STORE6 | F58: 2 | G58: 833.7 | H58: 0.06 | I58: PayPal | J58: 1567.356
A59: SALE57 | B59: 45462 | C59: CUST1467 | D59: PROD47 | E59: STORE14 | F59: 2 | G59: 680.16 | H59: 0.28 | I59: Credit Card | J59: 979.4304
A60: SALE58 | B60: 45633 | C60: CUST1404 | D60: PROD15 | E60: STORE7 | F60: 4 | G60: 733.42 | I60: PayPal | J60: 2552.3016
A61: SALE59 | B61: 45257 | C61: CUST1367 | D61: PROD89 | E61: STORE11 | F61: 1 | G61: 996.33 | H61: 0.23 | I61: PayPal | J61: 767.1741
A62: SALE60 | B62: 45854 | C62: CUST1408 | D62: PROD31 | E62: STORE10 | F62: 1 | G62: 198.83 | H62: 0.09 | I62: COD | J62: 180.9353
A63: SALE61 | B63: 45716 | C63: CUST1239 | D63: PROD19 | E63: STORE7 | F63: 1 | G63: 374.92 | H63: 0.18 | I63: PayPal | J63: 307.4344
A64: SALE62 | B64: 45515 | C64: CUST1464 | D64: PROD93 | E64: STORE16 | F64: 1 | G64: 468.94 | H64: 0.12 | I64: Credit Card | J64: 412.6672
A65: SALE63 | B65: 45927 | C65: CUST1126 | D65: PROD89 | E65: STORE12 | F65: 2 | G65: 121.37 | H65: 0.05 | I65: Credit Card | J65: 230.603
A66: SALE64 | B66: 45914 | C66: CUST1255 | D66: PROD53 | E66: STORE10 | F66: 3 | G66: 480.06 | H66: 0.01 | I66: Credit Card
A67: SALE65 | B67: 45290 | C67: CUST1162 | D67: PROD99 | E67: STORE17 | F67: 2 | G67: 856.57 | H67: 0.24 | I67: Credit Card | J67: 1301.9864
A68: SALE66 | B68: 45213 | C68: CUST1269 | D68: PROD77 | E68: STORE2 | F68: 4 | G68: 814.25 | H68: 0.18 | I68: Credit Card | J68: 2670.74
A69: SALE67 | B69: 45255 | C69: CUST1483 | D69: PROD12 | E69: STORE2 | F69: 1 | G69: 989.17 | H69: 0.2 | I69: PayPal | J69: 791.336
A70: SALE68 | B70: 45270 | C70: CUST1372 | D70: PROD72 | E70: STORE10 | F70: 4 | G70: 62.48 | H70: 0.18 | I70: Credit Card | J70: 204.9344
A71: SALE69 | B71: 45897 | C71: CUST1423 | D71: PROD13 | E71: STORE16 | F71: 4 | G71: 561.24 | H71: 0.24 | I71: Credit Card | J71: 1706.1696
A72: SALE70 | B72: 45849 | C72: CUST1058 | D72: PROD60 | E72: STORE5 | F72: 3 | G72: 92.24 | H72: 0.28 | I72: COD
A73: SALE71 | B73: 45889 | C73: CUST1168 | D73: PROD72 | E73: STORE1 | F73: 2 | G73: 668.3 | H73: 0.07 | I73: Credit Card | J73: 1243.038
A74: SALE72 | B74: 45533 | C74: CUST1409 | D74: PROD38 | E74: STORE5 | F74: 1 | G74: 553.82 | H74: 0.09 | I74: Credit Card | J74: 503.9762
A75: SALE73 | B75: 45626 | C75: CUST1037 | D75: PROD45 | E75: STORE11 | F75: 2 | G75: 556.43 | H75: 0.13 | I75: Credit Card | J75: 968.1882
A76: SALE74 | B76: 45942 | C76: CUST1273 | D76: PROD20 | E76: STORE8 | F76: 1 | G76: 184.98 | H76: 0.1 | I76: COD | J76: 166.482
A77: SALE75 | B77: 45500 | C77: CUST1035 | D77: PROD97 | E77: STORE12 | F77: 4 | G77: 700.18 | H77: 0.23 | I77: Credit Card | J77: 2156.5544
A78: SALE76 | B78: 45285 | C78: CUST1019 | D78: PROD76 | E78: STORE10 | F78: 2 | G78: 686.31 | H78: 0.25 | I78: Credit Card | J78: 1029.465
A79: SALE77 | B79: 45800 | C79: CUST1007 | D79: PROD67 | E79: STORE15 | F79: 1 | G79: 687.82 | H79: 0.27 | I79: COD | J79: 502.1086
A80: SALE78 | B80: 45609 | C80: CUST1221 | D80: PROD83 | E80: STORE8 | F80: 2 | G80: 900.55 | H80: 0.16 | I80: Credit Card | J80: 1512.924
A81: SALE79 | B81: 45268 | C81: CUST1115 | D81: PROD21 | E81: STORE2 | F81: 1 | G81: 341.17 | H81: 0.15 | I81: Credit Card | J81: 289.9945
A82: SALE80 | B82: 45885 | C82: CUST1176 | D82: PROD52 | E82: STORE8 | F82: 1 | G82: 442.27 | H82: 0.06 | I82: COD | J82: 415.7338
A83: SALE81 | B83: 45616 | C83: CUST1253 | D83: PROD71 | E83: STORE9 | F83: 1 | G83: 363.73 | H83: 0.25 | I83: PayPal | J83: 272.7975
A84: SALE82 | B84: 45518 | C84: CUST1378 | D84: PROD91 | E84: STORE17 | F84: 2 | G84: 601.33 | H84: 0.16 | I84: PayPal | J84: 1010.2344
A85: SALE83 | B85: 45427 | C85: CUST1403 | D85: PROD17 | E85: STORE18 | F85: 4 | G85: 34.39 | H85: 0.03 | I85: PayPal | J85: 133.4332
A86: SALE84 | B86: 45268 | C86: CUST1423 | D86: PROD46 | E86: STORE17 | F86: 1 | G86: 773.57 | H86: 0.05 | I86: COD
A87: SALE85 | B87: 45282 | C87: CUST1054 | D87: PROD88 | E87: STORE7 | F87: 4 | G87: 127.1 | H87: 0.24 | I87: COD | J87: 386.384
A88: SALE86 | B88: 45545 | C88: CUST1303 | D88: PROD20 | E88: STORE3 | F88: 3 | G88: 899.58 | H88: 0.28 | I88: PayPal | J88: 1943.0928
A89: SALE87 | B89: 45755 | C89: CUST1327 | D89: PROD1 | E89: STORE10 | F89: 3 | G89: 964.39 | H89: 0.04 | I89: Credit Card | J89: 2777.4432
A90: SALE88 | B90: 45588 | C90: CUST1183 | D90: PROD38 | E90: STORE0 | F90: 2 | G90: 217.83 | H90: 0.14 | I90: PayPal | J90: 374.6676
A91: SALE89 | B91: 45848 | C91: CUST1143 | D91: PROD17 | E91: STORE1 | F91: 4 | G91: 187.71 | H91: 0.06 | I91: COD | J91: 705.7896
A92: SALE90 | B92: 45577 | C92: CUST1010 | D92: PROD33 | E92: STORE18 | F92: 2 | G92: 350.12 | H92: 0.12 | I92: COD | J92: 616.2112
A93: SALE91 | B93: 45312 | C93: CUST1406 | D93: PROD16 | E93: STORE1 | F93: 4 | G93: 102.19 | H93: 0.17 | I93: PayPal | J93: 339.2708
A94: SALE92 | B94: 45350 | C94: CUST1007 | D94: PROD86 | E94: STORE4 | F94: 1 | G94: 696.53 | H94: 0.17 | I94: Credit Card | J94: 578.1199
A95: SALE93 | B95: 45657 | C95: CUST1065 | D95: PROD19 | E95: STORE4 | F95: 2 | G95: 327.52 | H95: 0.15 | I95: PayPal | J95: 556.784
A96: SALE94 | B96: 45530 | C96: CUST1298 | D96: PROD97 | E96: STORE19 | F96: 2 | G96: 569.36 | H96: 0.01 | I96: PayPal
A97: SALE95 | B97: 45556 | C97: CUST1321 | D97: PROD99 | E97: STORE6 | F97: 2 | G97: 68.29 | H97: 0.14 | I97: COD | J97: 117.4588
A98: SALE96 | B98: 45523 | C98: CUST1244 | D98: PROD50 | E98: STORE10 | F98: 1 | G98: 842.9 | H98: 0.06 | I98: COD | J98: 792.326
A99: SALE97 | B99: 45587 | C99: CUST1287 | D99: PROD3 | E99: STORE3 | F99: 3 | G99: 751.94 | H99: 0.26 | I99: PayPal | J99: 1669.3068
A100: SALE98 | B100: 45580 | C100: CUST1131 | D100: PROD56 | E100: STORE7 | F100: 4 | G100: 476.28 | H100: 0.17 | I100: Credit Card | J100: 1581.2496
...

Sheet Customer
A1: Customer_ID | B1: Name | C1: Age | D1: Gender | E1: City | F1: State | G1: Country | H1: Loyalty_Level | I1: Name Corrected | J1: Loyaly Level Corrected
A2: CUST1000 | B2: sheena bonilla | C2: 55 | D2: Male | E2: Donaldton | F2: North Carolina | G2: USA | I2: =TRIM(PROPER(B2)) -> Sheena Bonilla | J2: {=IF(H2<>"", H2, INDEX($H$2:$H$501, MODE(IF($H$2:$H$501<>"", MATCH($H$2:$H$501, $H$2:$H$501, 0)))))} -> Platinum
A3: CUST1001 | B3: Eugene Nelson | C3: 26 | D3: Female | E3: Phillipsmouth | F3: North Dakota | G3: USA | H3: Platinum | I3: =TRIM(PROPER(B3)) -> Eugene Nelson | J3: {=IF(H3<>"", H3, INDEX($H$2:$H$501, MODE(IF($H$2:$H$501<>"", MATCH($H$2:$H$501, $H$2:$H$501, 0)))))} -> Platinum
A4: CUST1002 | B4: dr. Benjamin Price | C4: 29 | D4: Female | E4: Kylebury | F4: Alabama | G4: USA | H4: Platinum | I4: =TRIM(PROPER(B4)) -> Dr. Benjamin Price | J4: {=IF(H4<>"", H4, INDEX($H$2:$H$501, MODE(IF($H$2:$H$501<>"", MATCH($H$2:$H$501, $H$2:$H$501, 0)))))} -> Platinum | L4: Summary
A5: CUST1003 | B5: jeremy harris | C5: 59 | D5: Female | E5: Thomastown | F5: Ohio | G5: USA | H5: Bronze | I5: =TRIM(PROPER(B5)) -> Jeremy Harris | J5: {=IF(H5<>"", H5, INDEX($H$2:$H$501, MODE(IF($H$2:$H$501<>"", MATCH($H$2:$H$501, $H$2:$H$501, 0)))))} -> Bronze | L5: 1)I use trim and proper formula to correct the name
A6: CUST1004 | B6: Caroline Collins | C6: 64 | D6: Female | E6: Nicholasshire | F6: California | G6: USA | H6: Silver | I6: =TRIM(PROPER(B6)) -> Caroline Collins | J6: {=IF(H6<>"", H6, INDEX($H$2:$H$501, MODE(IF($H$2:$H$501<>"", MATCH($H$2:$H$501, $H$2:$H$501, 0)))))} -> Silver | L6: 2)I use if, index, match formula to take mode for loyalty level
A7: CUST1005 | B7: Christine Vaughn | C7: 24 | D7: Male | E7: East Amandamouth | F7: Oregon | G7: USA | H7: Bronze | I7: =TRIM(PROPER(B7)) -> Christine Vaughn | J7: {=IF(H7<>"", H7, INDEX($H$2:$H$501, MODE(IF($H$2:$H$501<>"", MATCH($H$2:$H$501, $H$2:$H$501, 0)))))} -> Bronze | L7: 3) C-1486, C-1491, C-1496,… are corrected by using find and replace
A8: CUST1006 | B8: Amber Jackson | C8: 29 | D8: Female | E8: Deborahborough | F8: South Dakota | G8: USA | H8: Platinum | I8: =TRIM(PROPER(B8)) -> Amber Jackson | J8: {=IF(H8<>"", H8, INDEX($H$2:$H$501, MODE(IF($H$2:$H$501<>"", MATCH($H$2:$H$501, $H$2:$H$501, 0)))))} -> Platinum
A9: CUST1007 | B9: Daniel Boyd | C9: 29 | D9: Female | E9: West Pamelafurt | F9: West Virginia | G9: USA | H9: Bronze | I9: =TRIM(PROPER(B9)) -> Daniel Boyd | J9: {=IF(H9<>"", H9, INDEX($H$2:$H$501, MODE(IF($H$2:$H$501<>"", MATCH($H$2:$H$501, $H$2:$H$501, 0)))))} -> Bronze
A10: CUST1008 | B10: Melissa Howard | C10: 53 | D10: Female | E10: Maynardton | F10: New Hampshire | G10: USA | H10: Gold | I10: =TRIM(PROPER(B10)) -> Melissa Howard | J10: {=IF(H10<>"", H10, INDEX($H$2:$H$501, MODE(IF($H$2:$H$501<>"", MATCH($H$2:$H$501, $H$2:$H$501, 0)))))} -> Gold
A11: CUST1009 | B11: Ms. Maria Leach | C11: 64 | D11: Male | E11: Melissashire | F11: Pennsylvania | G11: USA | H11: Platinum | I11: =TRIM(PROPER(B11)) -> Ms. Maria Leach | J11: {=IF(H11<>"", H11, INDEX($H$2:$H$501, MODE(IF($H$2:$H$501<>"", MATCH($H$2:$H$501, $H$2:$H$501, 0)))))} -> Platinum
A12: CUST1010 | B12: Dominic Page | C12: 53 | D12: Male | E12: Port Michaelburgh | F12: Pennsylvania | G12: USA | H12: Bronze | I12: =TRIM(PROPER(B12)) -> Dominic Page | J12: {=IF(H12<>"", H12, INDEX($H$2:$H$501, MODE(IF($H$2:$H$501<>"", MATCH($H$2:$H$501, $H$2:$H$501, 0)))))} -> Bronze
A13: CUST1011 | B13: Brian Lopez | C13: 28 | D13: Female | E13: East Krista | F13: New York | G13: USA | H13: Gold | I13: =TRIM(PROPER(B13)) -> Brian Lopez | J13: {=IF(H13<>"", H13, INDEX($H$2:$H$501, MODE(IF($H$2:$H$501<>"", MATCH($H$2:$H$501, $H$2:$H$501, 0)))))} -> Gold
A14: CUST1012 | B14: Kenneth Lambert | C14: 55 | D14: Female | E14: North Kathryn | F14: Kansas | G14: USA | H14: Platinum | I14: =TRIM(PROPER(B14)) -> Kenneth Lambert | J14: {=IF(H14<>"", H14, INDEX($H$2:$H$501, MODE(IF($H$2:$H$501<>"", MATCH($H$2:$H$501, $H$2:$H$501, 0)))))} -> Platinum
A15: CUST1013 | B15: Nathan Hernandez | C15: 32 | D15: Female | E15: New Becky | F15: Montana | G15: USA | H15: Silver | I15: =TRIM(PROPER(B15)) -> Nathan Hernandez | J15: {=IF(H15<>"", H15, INDEX($H$2:$H$501, MODE(IF($H$2:$H$501<>"", MATCH($H$2:$H$501, $H$2:$H$501, 0)))))} -> Silver
A16: CUST1014 | B16: Ashley Cohen | C16: 53 | D16: Female | E16: Lake Kristamouth | F16: Nebraska | G16: USA | H16: Silver | I16: =TRIM(PROPER(B16)) -> Ashley Cohen | J16: {=IF(H16<>"", H16, INDEX($H$2:$H$501, MODE(IF($H$2:$H$501<>"", MATCH($H$2:$H$501, $H$2:$H$501, 0)))))} -> Silver
A17: CUST1015 | B17: Laura Alvarez | C17: 49 | D17: Female | E17: Lawsonhaven | F17: Washington | G17: USA | H17: Platinum | I17: =TRIM(PROPER(B17)) -> Laura Alvarez | J17: {=IF(H17<>"", H17, INDEX($H$2:$H$501, MODE(IF($H$2:$H$501<>"", MATCH($H$2:$H$501, $H$2:$H$501, 0)))))} -> Platinum
A18: CUST1016 | B18: John Scott | C18: 24 | D18: Female | E18: South Christopher | F18: Pennsylvania | G18: USA | H18: Bronze | I18: =TRIM(PROPER(B18)) -> John Scott | J18: {=IF(H18<>"", H18, INDEX($H$2:$H$501, MODE(IF($H$2:$H$501<>"", MATCH($H$2:$H$501, $H$2:$H$501, 0)))))} -> Bronze
A19: CUST1017 | B19: Adam Cruz | C19: 60 | D19: Female | E19: Brandonville | F19: Georgia | G19: USA | H19: Platinum | I19: =TRIM(PROPER(B19)) -> Adam Cruz | J19: {=IF(H19<>"", H19, INDEX($H$2:$H$501, MODE(IF($H$2:$H$501<>"", MATCH($H$2:$H$501, $H$2:$H$501, 0)))))} -> Platinum
A20: CUST1018 | B20: Rhonda Moss | C20: 43 | D20: Male | E20: South William | F20: Kansas | G20: USA | I20: =TRIM(PROPER(B20)) -> Rhonda Moss | J20: {=IF(H20<>"", H20, INDEX($H$2:$H$501, MODE(IF($H$2:$H$501<>"", MATCH($H$2:$H$501, $H$2:$H$501, 0)))))} -> Platinum
A21: CUST1019 | B21: Michael Torres | C21: 46 | D21: Female | E21: Gonzalezfort | F21: New Jersey | G21: USA | H21: Platinum | I21: =TRIM(PROPER(B21)) -> Michael Torres | J21: {=IF(H21<>"", H21, INDEX($H$2:$H$501, MODE(IF($H$2:$H$501<>"", MATCH($H$2:$H$501, $H$2:$H$501, 0)))))} -> Platinum
A22: CUST1020 | B22: Bridget Allen | C22: 59 | D22: Male | E22: Lake Shaneburgh | F22: Delaware | G22: USA | H22: Silver | I22: =TRIM(PROPER(B22)) -> Bridget Allen | J22: {=IF(H22<>"", H22, INDEX($H$2:$H$501, MODE(IF($H$2:$H$501<>"", MATCH($H$2:$H$501, $H$2:$H$501, 0)))))} -> Silver
A23: CUST1021 | B23: Jeff Martinez | C23: 36 | D23: Female | E23: Smithburgh | F23: Oklahoma | G23: USA | H23: Gold | I23: =TRIM(PROPER(B23)) -> Jeff Martinez | J23: {=IF(H23<>"", H23, INDEX($H$2:$H$501, MODE(IF($H$2:$H$501<>"", MATCH($H$2:$H$501, $H$2:$H$501, 0)))))} -> Gold
A24: CUST1022 | B24: paul fox | C24: 33 | D24: Female | E24: Michaelton | F24: Hawaii | G24: USA | H24: Silver | I24: =TRIM(PROPER(B24)) -> Paul Fox | J24: {=IF(H24<>"", H24, INDEX($H$2:$H$501, MODE(IF($H$2:$H$501<>"", MATCH($H$2:$H$501, $H$2:$H$501, 0)))))} -> Silver
A25: CUST1023 | B25: Jonathan Steele | C25: 52 | D25: Female | E25: Molinabury | F25: Oregon | G25: USA | H25: Silver | I25: =TRIM(PROPER(B25)) -> Jonathan Steele | J25: {=IF(H25<>"", H25, INDEX($H$2:$H$501, MODE(IF($H$2:$H$501<>"", MATCH($H$2:$H$501, $H$2:$H$501, 0)))))} -> Silver
A26: CUST1024 | B26: Heather Collins | C26: 40 | D26: Male | E26: Rogerschester | F26: Idaho | G26: USA | H26: Platinum | I26: =TRIM(PROPER(B26)) -> Heather Collins | J26: {=IF(H26<>"", H26, INDEX($H$2:$H$501, MODE(IF($H$2:$H$501<>"", MATCH($H$2:$H$501, $H$2:$H$501, 0)))))} -> Platinum
A27: CUST1025 | B27: Diana Taylor | C27: 59 | D27: Female | E27: Vasqueztown | F27: California | G27: USA | H27: Bronze | I27: =TRIM(PROPER(B27)) -> Diana Taylor | J27: {=IF(H27<>"", H27, INDEX($H$2:$H$501, MODE(IF($H$2:$H$501<>"", MATCH($H$2:$H$501, $H$2:$H$501, 0)))))} -> Bronze
A28: CUST1026 | B28: Amber Carlson | C28: 18 | D28: Female | E28: East Michellemouth | F28: Missouri | G28: USA | H28: Gold | I28: =TRIM(PROPER(B28)) -> Amber Carlson | J28: {=IF(H28<>"", H28, INDEX($H$2:$H$501, MODE(IF($H$2:$H$501<>"", MATCH($H$2:$H$501, $H$2:$H$501, 0)))))} -> Gold
A29: CUST1027 | B29: Leslie Johnson | C29: 31 | D29: Male | E29: Mollyshire | F29: Utah | G29: USA | I29: =TRIM(PROPER(B29)) -> Leslie Johnson | J29: {=IF(H29<>"", H29, INDEX($H$2:$H$501, MODE(IF($H$2:$H$501<>"", MATCH($H$2:$H$501, $H$2:$H$501, 0)))))} -> Platinum
A30: CUST1028 | B30: Joshua Ryan | C30: 27 | D30: Female | E30: New David | F30: New Jersey | G30: USA | H30: Platinum | I30: =TRIM(PROPER(B30)) -> Joshua Ryan | J30: {=IF(H30<>"", H30, INDEX($H$2:$H$501, MODE(IF($H$2:$H$501<>"", MATCH($H$2:$H$501, $H$2:$H$501, 0)))))} -> Platinum
A31: CUST1029 | B31: David Arnold | C31: 54 | D31: Female | E31: East Jennifer | F31: California | G31: USA | H31: Silver | I31: =TRIM(PROPER(B31)) -> David Arnold | J31: {=IF(H31<>"", H31, INDEX($H$2:$H$501, MODE(IF($H$2:$H$501<>"", MATCH($H$2:$H$501, $H$2:$H$501, 0)))))} -> Silver
A32: CUST1030 | B32: Jessica Acevedo | C32: 64 | D32: Female | E32: Amybury | F32: Pennsylvania | G32: USA | H32: Bronze | I32: =TRIM(PROPER(B32)) -> Jessica Acevedo | J32: {=IF(H32<>"", H32, INDEX($H$2:$H$501, MODE(IF($H$2:$H$501<>"", MATCH($H$2:$H$501, $H$2:$H$501, 0)))))} -> Bronze
A33: CUST1031 | B33: Sarah Vance | C33: 41 | D33: Male | E33: Johnsonville | F33: Oregon | G33: USA | H33: Silver | I33: =TRIM(PROPER(B33)) -> Sarah Vance | J33: {=IF(H33<>"", H33, INDEX($H$2:$H$501, MODE(IF($H$2:$H$501<>"", MATCH($H$2:$H$501, $H$2:$H$501, 0)))))} -> Silver
A34: CUST1032 | B34: Mike Jennings | C34: 48 | D34: Female | E34: Fostermouth | F34: Arizona | G34: USA | H34: Gold | I34: =TRIM(PROPER(B34)) -> Mike Jennings | J34: {=IF(H34<>"", H34, INDEX($H$2:$H$501, MODE(IF($H$2:$H$501<>"", MATCH($H$2:$H$501, $H$2:$H$501, 0)))))} -> Gold
A35: CUST1033 | B35: Robert Jones DDS | C35: 25 | D35: Male | E35: Tristanton | F35: Oklahoma | G35: USA | H35: Platinum | I35: =TRIM(PROPER(B35)) -> Robert Jones Dds | J35: {=IF(H35<>"", H35, INDEX($H$2:$H$501, MODE(IF($H$2:$H$501<>"", MATCH($H$2:$H$501, $H$2:$H$501, 0)))))} -> Platinum
A36: CUST1034 | B36: Christopher Olson | C36: 27 | D36: Female | E36: West Richard | F36: Maryland | G36: USA | H36: Platinum | I36: =TRIM(PROPER(B36)) -> Christopher Olson | J36: {=IF(H36<>"", H36, INDEX($H$2:$H$501, MODE(IF($H$2:$H$501<>"", MATCH($H$2:$H$501, $H$2:$H$501, 0)))))} -> Platinum
A37: CUST1035 | B37: Rachel Myers | C37: 52 | D37: Male | E37: Robertberg | F37: North Dakota | G37: USA | H37: Silver | I37: =TRIM(PROPER(B37)) -> Rachel Myers | J37: {=IF(H37<>"", H37, INDEX($H$2:$H$501, MODE(IF($H$2:$H$501<>"", MATCH($H$2:$H$501, $H$2:$H$501, 0)))))} -> Silver
A38: CUST1036 | B38: Thomas Phillips | C38: 20 | D38: Female | E38: Luisfurt | F38: Georgia | G38: USA | H38: Gold | I38: =TRIM(PROPER(B38)) -> Thomas Phillips | J38: {=IF(H38<>"", H38, INDEX($H$2:$H$501, MODE(IF($H$2:$H$501<>"", MATCH($H$2:$H$501, $H$2:$H$501, 0)))))} -> Gold
A39: CUST1037 | B39: Christopher Carter | C39: 27 | D39: Female | E39: Brendastad | F39: South Dakota | G39: USA | I39: =TRIM(PROPER(B39)) -> Christopher Carter | J39: {=IF(H39<>"", H39, INDEX($H$2:$H$501, MODE(IF($H$2:$H$501<>"", MATCH($H$2:$H$501, $H$2:$H$501, 0)))))} -> Platinum
A40: CUST1038 | B40: Deanna Simpson | C40: 35 | D40: Female | E40: Brownport | F40: North Dakota | G40: USA | H40: Bronze | I40: =TRIM(PROPER(B40)) -> Deanna Simpson | J40: {=IF(H40<>"", H40, INDEX($H$2:$H$501, MODE(IF($H$2:$H$501<>"", MATCH($H$2:$H$501, $H$2:$H$501, 0)))))} -> Bronze
A41: CUST1039 | B41: Tonya Reynolds | C41: 55 | D41: Female | E41: Darleneton | F41: Michigan | G41: USA | H41: Gold | I41: =TRIM(PROPER(B41)) -> Tonya Reynolds | J41: {=IF(H41<>"", H41, INDEX($H$2:$H$501, MODE(IF($H$2:$H$501<>"", MATCH($H$2:$H$501, $H$2:$H$501, 0)))))} -> Gold
A42: CUST1040 | B42: Eric Vega | C42: 50 | D42: Male | E42: Williamsonland | F42: Kansas | G42: USA | H42: Gold | I42: =TRIM(PROPER(B42)) -> Eric Vega | J42: {=IF(H42<>"", H42, INDEX($H$2:$H$501, MODE(IF($H$2:$H$501<>"", MATCH($H$2:$H$501, $H$2:$H$501, 0)))))} -> Gold
A43: CUST1041 | B43: James Gibbs | C43: 21 | D43: Male | E43: Mooneyshire | F43: Alaska | G43: USA | H43: Platinum | I43: =TRIM(PROPER(B43)) -> James Gibbs | J43: {=IF(H43<>"", H43, INDEX($H$2:$H$501, MODE(IF($H$2:$H$501<>"", MATCH($H$2:$H$501, $H$2:$H$501, 0)))))} -> Platinum
A44: CUST1042 | B44: William Martin | C44: 19 | D44: Male | E44: Ryanburgh | F44: Connecticut | G44: USA | H44: Platinum | I44: =TRIM(PROPER(B44)) -> William Martin | J44: {=IF(H44<>"", H44, INDEX($H$2:$H$501, MODE(IF($H$2:$H$501<>"", MATCH($H$2:$H$501, $H$2:$H$501, 0)))))} -> Platinum
A45: CUST1043 | B45: Joseph Snow | C45: 45 | D45: Male | E45: South Michaelfort | F45: Vermont | G45: USA | H45: Gold | I45: =TRIM(PROPER(B45)) -> Joseph Snow | J45: {=IF(H45<>"", H45, INDEX($H$2:$H$501, MODE(IF($H$2:$H$501<>"", MATCH($H$2:$H$501, $H$2:$H$501, 0)))))} -> Gold
A46: CUST1044 | B46: Denise Williams | C46: 34 | D46: Male | E46: Christianstad | F46: Hawaii | G46: USA | H46: Bronze | I46: =TRIM(PROPER(B46)) -> Denise Williams | J46: {=IF(H46<>"", H46, INDEX($H$2:$H$501, MODE(IF($H$2:$H$501<>"", MATCH($H$2:$H$501, $H$2:$H$501, 0)))))} -> Bronze
A47: CUST1045 | B47: Jordan Jackson DDS | C47: 54 | D47: Male | E47: North Johnview | F47: Arizona | G47: USA | H47: Gold | I47: =TRIM(PROPER(B47)) -> Jordan Jackson Dds | J47: {=IF(H47<>"", H47, INDEX($H$2:$H$501, MODE(IF($H$2:$H$501<>"", MATCH($H$2:$H$501, $H$2:$H$501, 0)))))} -> Gold
A48: CUST1046 | B48: Michelle Garcia DDS | C48: 55 | D48: Female | E48: Perezbury | F48: Ohio | G48: USA | H48: Platinum | I48: =TRIM(PROPER(B48)) -> Michelle Garcia Dds | J48: {=IF(H48<>"", H48, INDEX($H$2:$H$501, MODE(IF($H$2:$H$501<>"", MATCH($H$2:$H$501, $H$2:$H$501, 0)))))} -> Platinum
A49: CUST1047 | B49: Gina Knight | C49: 54 | D49: Female | E49: Lake Roberthaven | F49: Nevada | G49: USA | H49: Silver | I49: =TRIM(PROPER(B49)) -> Gina Knight | J49: {=IF(H49<>"", H49, INDEX($H$2:$H$501, MODE(IF($H$2:$H$501<>"", MATCH($H$2:$H$501, $H$2:$H$501, 0)))))} -> Silver
A50: CUST1048 | B50: April Mullins | C50: 54 | D50: Male | E50: Dawsonbury | F50: North Carolina | G50: USA | H50: Platinum | I50: =TRIM(PROPER(B50)) -> April Mullins | J50: {=IF(H50<>"", H50, INDEX($H$2:$H$501, MODE(IF($H$2:$H$501<>"", MATCH($H$2:$H$501, $H$2:$H$501, 0)))))} -> Platinum
A51: CUST1049 | B51: Timothy Weaver | C51: 45 | D51: Female | E51: New Amy | F51: Ohio | G51: USA | H51: Gold | I51: =TRIM(PROPER(B51)) -> Timothy Weaver | J51: {=IF(H51<>"", H51, INDEX($H$2:$H$501, MODE(IF($H$2:$H$501<>"", MATCH($H$2:$H$501, $H$2:$H$501, 0)))))} -> Gold
... A501: CUST1499 | B501: Philip Pennington | C501: 27 | D501: Female | E501: East Valerieview | F501: Oregon | G501: USA | H501: Platinum | I501: =TRIM(PROPER(B501)) -> Philip Pennington | J501: {=IF(H501<>"", H501, INDEX($H$2:$H$501, MODE(IF($H$2:$H$501<>"", MATCH($H$2:$H$501, $H$2:$H$501, 0)))))} -> Platinum

Sheet Product
A1: Product id | B1: Product_Name | C1: Category | D1: Sub_Category | E1: Brand | F1: Cost | G1: Stock | H1: Cost Corrected | I1: Stock Corrected
A2: PROD0 | B2: Brother Laser Printer | C2: Electronics | D2: Computer | E2: Hunt Inc | F2: 112.42 | G2: 416 | H2: =IF(F2="", AVERAGEIF($C$2:$C$101, C2, $F$2:$F$101), F2) -> 112.42 | I2: =IF(G2="", AVERAGEIF($C$2:$C$101, C2, $G$2:$G$101), G2) -> 416
A3: PROD1 | B3: Men's Graphic T-Shirt | C3: Clothing | D3: Tops | E3: Terry-Moore | F3: 342.56 | G3: 181 | H3: =IF(F3="", AVERAGEIF($C$2:$C$101, C3, $F$2:$F$101), F3) -> 342.56 | I3: =IF(G3="", AVERAGEIF($C$2:$C$101, C3, $G$2:$G$101), G3) -> 181
A4: PROD2 | B4: Women's Casual Hoodie | C4: Clothing | D4: Outerwear | E4: Sims Inc | G4: 352 | H4: =IF(F4="", AVERAGEIF($C$2:$C$101, C4, $F$2:$F$101), F4) -> 265.73267 | I4: =IF(G4="", AVERAGEIF($C$2:$C$101, C4, $G$2:$G$101), G4) -> 352 | K4: Summary
A5: PROD3 | B5: Men's Running Jacket | C5: Clothing | D5: Outerwear | E5: Pineda Ltd | F5: 364.67 | G5: 452 | H5: =IF(F5="", AVERAGEIF($C$2:$C$101, C5, $F$2:$F$101), F5) -> 364.67 | I5: =IF(G5="", AVERAGEIF($C$2:$C$101, C5, $G$2:$G$101), G5) -> 452 | K5: 1)Cost and Stock finded by if formula
A6: PROD4 | B6: Women's Yoga Pants | C6: Clothing | D6: Bottoms | E6: Gonzales-Davis | F6: 306.46 | G6: 487 | H6: =IF(F6="", AVERAGEIF($C$2:$C$101, C6, $F$2:$F$101), F6) -> 306.46 | I6: =IF(G6="", AVERAGEIF($C$2:$C$101, C6, $G$2:$G$101), G6) -> 487 | K6: 2)P3,P16 change to PROD3, PROD16 by find and replace
A7: PROD5 | B7: Men's Leather Belt | C7: Clothing | D7: Accessories | E7: Baldwin, Garza and Gonzalez | F7: 261 | G7: 59 | H7: =IF(F7="", AVERAGEIF($C$2:$C$101, C7, $F$2:$F$101), F7) -> 261 | I7: =IF(G7="", AVERAGEIF($C$2:$C$101, C7, $G$2:$G$101), G7) -> 59
A8: PROD6 | B8: Herbal Face Moisturizer | C8: Beauty | D8: Skincare | E8: Davidson PLC | F8: 312.8 | G8: 350 | H8: =IF(F8="", AVERAGEIF($C$2:$C$101, C8, $F$2:$F$101), F8) -> 312.8 | I8: =IF(G8="", AVERAGEIF($C$2:$C$101, C8, $G$2:$G$101), G8) -> 350
A9: PROD7 | B9: LED Table Lamp | C9: Home | D9: Lighting | E9: Harrell LLC | F9: 218.86 | G9: 170 | H9: =IF(F9="", AVERAGEIF($C$2:$C$101, C9, $F$2:$F$101), F9) -> 218.86 | I9: =IF(G9="", AVERAGEIF($C$2:$C$101, C9, $G$2:$G$101), G9) -> 170
A10: PROD8 | B10: Wireless Bluetooth Earbuds | C10: Electronics | D10: Audio | E10: Perez-Johnston | F10: 439.07 | G10: 142 | H10: =IF(F10="", AVERAGEIF($C$2:$C$101, C10, $F$2:$F$101), F10) -> 439.07 | I10: =IF(G10="", AVERAGEIF($C$2:$C$101, C10, $G$2:$G$101), G10) -> 142
A11: PROD9 | B11: Adjustable Dumbbell Set | C11: Sports | D11: Fitness | E11: Hill PLC | F11: 495.72 | G11: 323 | H11: =IF(F11="", AVERAGEIF($C$2:$C$101, C11, $F$2:$F$101), F11) -> 495.72 | I11: =IF(G11="", AVERAGEIF($C$2:$C$101, C11, $G$2:$G$101), G11) -> 323
A12: PROD10 | B12: Ceramic Kitchen Bowl Set | C12: Home | D12: Kitchen | E12: Hamilton Group | F12: 298.86 | G12: 308 | H12: =IF(F12="", AVERAGEIF($C$2:$C$101, C12, $F$2:$F$101), F12) -> 298.86 | I12: =IF(G12="", AVERAGEIF($C$2:$C$101, C12, $G$2:$G$101), G12) -> 308
A13: PROD11 | B13: HD Smart TV Stick | C13: Electronics | D13: Accessories | E13: Gibson, Hobbs and Weaver | F13: 449.4 | H13: =IF(F13="", AVERAGEIF($C$2:$C$101, C13, $F$2:$F$101), F13) -> 449.4 | I13: =IF(G13="", AVERAGEIF($C$2:$C$101, C13, $G$2:$G$101), G13) -> 274.7
A14: PROD12 | B14: Hair Strengthening Shampoo | C14: Beauty | D14: Haircare | E14: Rice LLC | F14: 115.82 | G14: 460 | H14: =IF(F14="", AVERAGEIF($C$2:$C$101, C14, $F$2:$F$101), F14) -> 115.82 | I14: =IF(G14="", AVERAGEIF($C$2:$C$101, C14, $G$2:$G$101), G14) -> 460
A15: PROD13 | B15: USB-C Fast Charger | C15: Electronics | D15: Accessories | E15: Dawson-Perkins | F15: 242.23 | G15: 453 | H15: =IF(F15="", AVERAGEIF($C$2:$C$101, C15, $F$2:$F$101), F15) -> 242.23 | I15: =IF(G15="", AVERAGEIF($C$2:$C$101, C15, $G$2:$G$101), G15) -> 453
A16: PROD14 | B16: Decorative Wall Mirror | C16: Home | D16: Decor | E16: Luna, Anderson and Bowman | F16: 48.01 | G16: 439 | H16: =IF(F16="", AVERAGEIF($C$2:$C$101, C16, $F$2:$F$101), F16) -> 48.01 | I16: =IF(G16="", AVERAGEIF($C$2:$C$101, C16, $G$2:$G$101), G16) -> 439
A17: PROD15 | B17: 4K Home Projector | C17: Electronics | D17: Appliances | E17: Thomas LLC | F17: 465.34 | G17: 301 | H17: =IF(F17="", AVERAGEIF($C$2:$C$101, C17, $F$2:$F$101), F17) -> 465.34 | I17: =IF(G17="", AVERAGEIF($C$2:$C$101, C17, $G$2:$G$101), G17) -> 301
A18: PROD16 | B18: Beard Grooming Kit | C18: Beauty | D18: Grooming | E18: Erickson-Green | F18: 337.42 | G18: 256 | H18: =IF(F18="", AVERAGEIF($C$2:$C$101, C18, $F$2:$F$101), F18) -> 337.42 | I18: =IF(G18="", AVERAGEIF($C$2:$C$101, C18, $G$2:$G$101), G18) -> 256
A19: PROD17 | B19: Soccer Training Cone Set | C19: Sports | D19: Accessories | E19: Ford, Murphy and Wilson | F19: 144.53 | G19: 367 | H19: =IF(F19="", AVERAGEIF($C$2:$C$101, C19, $F$2:$F$101), F19) -> 144.53 | I19: =IF(G19="", AVERAGEIF($C$2:$C$101, C19, $G$2:$G$101), G19) -> 367
A20: PROD18 | B20: Women's Denim Jeans | C20: Clothing | D20: Bottoms | E20: Guerra-Hendrix | G20: 343 | H20: =IF(F20="", AVERAGEIF($C$2:$C$101, C20, $F$2:$F$101), F20) -> 265.73267 | I20: =IF(G20="", AVERAGEIF($C$2:$C$101, C20, $G$2:$G$101), G20) -> 343
A21: PROD19 | B21: Knee Support Brace | C21: Sports | D21: Equipment | E21: May-Reese | F21: 21.34 | G21: 65 | H21: =IF(F21="", AVERAGEIF($C$2:$C$101, C21, $F$2:$F$101), F21) -> 21.34 | I21: =IF(G21="", AVERAGEIF($C$2:$C$101, C21, $G$2:$G$101), G21) -> 65
A22: PROD20 | B22: Outdoor Sports Water Bottle | C22: Sports | D22: Accessories | E22: Soto-Ellis | F22: 131.51 | H22: =IF(F22="", AVERAGEIF($C$2:$C$101, C22, $F$2:$F$101), F22) -> 131.51 | I22: =IF(G22="", AVERAGEIF($C$2:$C$101, C22, $G$2:$G$101), G22) -> 281.95833
A23: PROD21 | B23: Multi-Purpose Storage Box | C23: Home | D23: Storage | E23: Gardner-Montes | F23: 123.46 | G23: 76 | H23: =IF(F23="", AVERAGEIF($C$2:$C$101, C23, $F$2:$F$101), F23) -> 123.46 | I23: =IF(G23="", AVERAGEIF($C$2:$C$101, C23, $G$2:$G$101), G23) -> 76
A24: PROD22 | B24: Carbon Fiber Tennis Racket | C24: Sports | D24: Equipment | E24: Flores, Pineda and Rodriguez | F24: 484.62 | G24: 432 | H24: =IF(F24="", AVERAGEIF($C$2:$C$101, C24, $F$2:$F$101), F24) -> 484.62 | I24: =IF(G24="", AVERAGEIF($C$2:$C$101, C24, $G$2:$G$101), G24) -> 432
A25: PROD23 | B25: Men's Formal Shirt | C25: Clothing | D25: Tops | E25: Moon, Mora and Santos | G25: 360 | H25: =IF(F25="", AVERAGEIF($C$2:$C$101, C25, $F$2:$F$101), F25) -> 265.73267 | I25: =IF(G25="", AVERAGEIF($C$2:$C$101, C25, $G$2:$G$101), G25) -> 360
A26: PROD24 | B26: Foldable Camping Chair | C26: Sports | D26: Outdoor | E26: Cook Ltd | F26: 166.06 | G26: 340 | H26: =IF(F26="", AVERAGEIF($C$2:$C$101, C26, $F$2:$F$101), F26) -> 166.06 | I26: =IF(G26="", AVERAGEIF($C$2:$C$101, C26, $G$2:$G$101), G26) -> 340
A27: PROD25 | B27: Women's Scarf Set | C27: Clothing | D27: Accessories | E27: Brown and Sons | F27: 174.02 | G27: 268 | H27: =IF(F27="", AVERAGEIF($C$2:$C$101, C27, $F$2:$F$101), F27) -> 174.02 | I27: =IF(G27="", AVERAGEIF($C$2:$C$101, C27, $G$2:$G$101), G27) -> 268
A28: PROD26 | B28: Wireless Bluetooth Speaker | C28: Electronics | D28: Audio | E28: Reed-Schmidt | F28: 322.41 | G28: 213 | H28: =IF(F28="", AVERAGEIF($C$2:$C$101, C28, $F$2:$F$101), F28) -> 322.41 | I28: =IF(G28="", AVERAGEIF($C$2:$C$101, C28, $G$2:$G$101), G28) -> 213
A29: PROD27 | B29: Decorative Floor Vase | C29: Home | D29: Decor | E29: Khan, Jones and Paul | G29: 378 | H29: =IF(F29="", AVERAGEIF($C$2:$C$101, C29, $F$2:$F$101), F29) -> 234.806 | I29: =IF(G29="", AVERAGEIF($C$2:$C$101, C29, $G$2:$G$101), G29) -> 378
A30: PROD28 | B30: Sports Stopwatch Timer | C30: Sports | D30: Accessories | E30: Burns-Hansen | F30: 38.76 | G30: 137 | H30: =IF(F30="", AVERAGEIF($C$2:$C$101, C30, $F$2:$F$101), F30) -> 38.76 | I30: =IF(G30="", AVERAGEIF($C$2:$C$101, C30, $G$2:$G$101), G30) -> 137
A31: PROD29 | B31: Fabric Sofa Throw Blanket | C31: Home | D31: Decor | E31: Hoffman Group | F31: 218.48 | G31: 276 | H31: =IF(F31="", AVERAGEIF($C$2:$C$101, C31, $F$2:$F$101), F31) -> 218.48 | I31: =IF(G31="", AVERAGEIF($C$2:$C$101, C31, $G$2:$G$101), G31) -> 276
A32: PROD30 | B32: Stainless Steel Cutlery Set | C32: Home | D32: Kitchen | E32: Stevens, Fernandez and Martin | F32: 19.52 | G32: 57 | H32: =IF(F32="", AVERAGEIF($C$2:$C$101, C32, $F$2:$F$101), F32) -> 19.52 | I32: =IF(G32="", AVERAGEIF($C$2:$C$101, C32, $G$2:$G$101), G32) -> 57
A33: PROD31 | B33: Basketball | C33: Sports | D33: Team Sports | E33: Nolan-Snow | F33: 204.39 | G33: 281 | H33: =IF(F33="", AVERAGEIF($C$2:$C$101, C33, $F$2:$F$101), F33) -> 204.39 | I33: =IF(G33="", AVERAGEIF($C$2:$C$101, C33, $G$2:$G$101), G33) -> 281
A34: PROD32 | B34: Vitamin C Face Serum | C34: Beauty | D34: Skincare | E34: Griffin Ltd | F34: 283.83 | G34: 244 | H34: =IF(F34="", AVERAGEIF($C$2:$C$101, C34, $F$2:$F$101), F34) -> 283.83 | I34: =IF(G34="", AVERAGEIF($C$2:$C$101, C34, $G$2:$G$101), G34) -> 244
A35: PROD33 | B35: Modern Wall Clock | C35: Home | D35: Decor | E35: Weiss-Watson | F35: 179.77 | G35: 305 | H35: =IF(F35="", AVERAGEIF($C$2:$C$101, C35, $F$2:$F$101), F35) -> 179.77 | I35: =IF(G35="", AVERAGEIF($C$2:$C$101, C35, $G$2:$G$101), G35) -> 305
A36: PROD34 | B36: Gaming Mechanical Keyboard | C36: Electronics | D36: Computer | E36: Lucero LLC | F36: 419.28 | G36: 86 | H36: =IF(F36="", AVERAGEIF($C$2:$C$101, C36, $F$2:$F$101), F36) -> 419.28 | I36: =IF(G36="", AVERAGEIF($C$2:$C$101, C36, $G$2:$G$101), G36) -> 86
A37: PROD35 | B37: Bedroom Table Lamp | C37: Home | D37: Lighting | E37: Jones LLC | F37: 382.22 | G37: 329 | H37: =IF(F37="", AVERAGEIF($C$2:$C$101, C37, $F$2:$F$101), F37) -> 382.22 | I37: =IF(G37="", AVERAGEIF($C$2:$C$101, C37, $G$2:$G$101), G37) -> 329
A38: PROD36 | B38: Women's Summer Dress | C38: Clothing | D38: Tops | E38: Smith-Mills | F38: 223.43 | G38: 154 | H38: =IF(F38="", AVERAGEIF($C$2:$C$101, C38, $F$2:$F$101), F38) -> 223.43 | I38: =IF(G38="", AVERAGEIF($C$2:$C$101, C38, $G$2:$G$101), G38) -> 154
A39: PROD37 | B39: Men's Casual Sneakers | C39: Clothing | D39: Footwear | E39: Hogan-Lee | F39: 353.47 | G39: 214 | H39: =IF(F39="", AVERAGEIF($C$2:$C$101, C39, $F$2:$F$101), F39) -> 353.47 | I39: =IF(G39="", AVERAGEIF($C$2:$C$101, C39, $G$2:$G$101), G39) -> 214
A40: PROD38 | B40: Sports Water Hydration Pack | C40: Sports | D40: Outdoor | E40: Sims-Smith | F40: 135.61 | G40: 394 | H40: =IF(F40="", AVERAGEIF($C$2:$C$101, C40, $F$2:$F$101), F40) -> 135.61 | I40: =IF(G40="", AVERAGEIF($C$2:$C$101, C40, $G$2:$G$101), G40) -> 394
A41: PROD39 | B41: Portable Power Bank | C41: Electronics | D41: Mobile | E41: Cummings and Sons | F41: 326.06 | G41: 301 | H41: =IF(F41="", AVERAGEIF($C$2:$C$101, C41, $F$2:$F$101), F41) -> 326.06 | I41: =IF(G41="", AVERAGEIF($C$2:$C$101, C41, $G$2:$G$101), G41) -> 301
... A48: PROD46 | B48: Men's Winter Jacket | C48: Clothing | D48: Outerwear | E48: Kelly, Smith and Perez | F48: 167.34 | G48: 296 | H48: =IF(F48="", AVERAGEIF($C$2:$C$101, C48, $F$2:$F$101), F48) -> 167.34 | I48: =IF(G48="", AVERAGEIF($C$2:$C$101, C48, $G$2:$G$101), G48) -> 296
A49: PROD47 | B49: Makeup Brush Set | C49: Beauty | D49: Makeup | E49: Cook Inc | G49: 431 | H49: =IF(F49="", AVERAGEIF($C$2:$C$101, C49, $F$2:$F$101), F49) -> 250.41615 | I49: =IF(G49="", AVERAGEIF($C$2:$C$101, C49, $G$2:$G$101), G49) -> 431
A50: PROD48 | B50: Car Dashboard Phone Holder | C50: Electronics | D50: Accessories | E50: Byrd, Stewart and Valdez | F50: 177.98 | G50: 103 | H50: =IF(F50="", AVERAGEIF($C$2:$C$101, C50, $F$2:$F$101), F50) -> 177.98 | I50: =IF(G50="", AVERAGEIF($C$2:$C$101, C50, $G$2:$G$101), G50) -> 103
A51: PROD49 | B51: Men's Roll-On Perfume | C51: Beauty | D51: Fragrance | E51: Sullivan and Sons | F51: 43.29 | G51: 267 | H51: =IF(F51="", AVERAGEIF($C$2:$C$101, C51, $F$2:$F$101), F51) -> 43.29 | I51: =IF(G51="", AVERAGEIF($C$2:$C$101, C51, $G$2:$G$101), G51) -> 267
A52: PROD50 | B52: Boxing Hand Wraps | C52: Sports | D52: Fitness | E52: Smith-King | F52: 190.29 | G52: 260 | H52: =IF(F52="", AVERAGEIF($C$2:$C$101, C52, $F$2:$F$101), F52) -> 190.29 | I52: =IF(G52="", AVERAGEIF($C$2:$C$101, C52, $G$2:$G$101), G52) -> 260
A53: PROD51 | B53: HDMI Cable – 2m | C53: Electronics | D53: Accessories | E53: Bautista, Green and Hale | F53: 88.49 | G53: 246 | H53: =IF(F53="", AVERAGEIF($C$2:$C$101, C53, $F$2:$F$101), F53) -> 88.49 | I53: =IF(G53="", AVERAGEIF($C$2:$C$101, C53, $G$2:$G$101), G53) -> 246
A54: PROD52 | B54: Rugby Ball | C54: Sports | D54: Team Sports | E54: Harris Inc | F54: 212.26 | G54: 82 | H54: =IF(F54="", AVERAGEIF($C$2:$C$101, C54, $F$2:$F$101), F54) -> 212.26 | I54: =IF(G54="", AVERAGEIF($C$2:$C$101, C54, $G$2:$G$101), G54) -> 82
A55: PROD53 | B55: Men's Track Pants | C55: Clothing | D55: Bottoms | E55: Hamilton, Woods and Walker | F55: 386.56 | G55: 125 | H55: =IF(F55="", AVERAGEIF($C$2:$C$101, C55, $F$2:$F$101), F55) -> 386.56 | I55: =IF(G55="", AVERAGEIF($C$2:$C$101, C55, $G$2:$G$101), G55) -> 125
A56: PROD54 | B56: Sports Stopwatch Pro | C56: Sports | D56: Accessories | E56: Thompson-French | F56: 434.84 | G56: 185 | H56: =IF(F56="", AVERAGEIF($C$2:$C$101, C56, $F$2:$F$101), F56) -> 434.84 | I56: =IF(G56="", AVERAGEIF($C$2:$C$101, C56, $G$2:$G$101), G56) -> 185
A57: PROD55 | B57: Ceramic Plant Pot | C57: Home | D57: Decor | E57: Hatfield, Baird and Torres | F57: 81.75 | H57: =IF(F57="", AVERAGEIF($C$2:$C$101, C57, $F$2:$F$101), F57) -> 81.75 | I57: =IF(G57="", AVERAGEIF($C$2:$C$101, C57, $G$2:$G$101), G57) -> 226.05
A58: PROD56 | B58: Premium Blanket Throw | C58: Home | D58: Decor | E58: Hernandez, Kennedy and Porter | F58: 461.47 | G58: 190 | H58: =IF(F58="", AVERAGEIF($C$2:$C$101, C58, $F$2:$F$101), F58) -> 461.47 | I58: =IF(G58="", AVERAGEIF($C$2:$C$101, C58, $G$2:$G$101), G58) -> 190
A59: PROD57 | B59: Foam Roller | C59: Sports | D59: Fitness | E59: Atkinson, Camacho and Oliver | F59: 30.62 | G59: 138 | H59: =IF(F59="", AVERAGEIF($C$2:$C$101, C59, $F$2:$F$101), F59) -> 30.62 | I59: =IF(G59="", AVERAGEIF($C$2:$C$101, C59, $G$2:$G$101), G59) -> 138
A60: PROD58 | B60: Womens Cotton Scarf | C60: Clothing | D60: Accessories | E60: Shepherd-Gould | F60: 113.83 | G60: 485 | H60: =IF(F60="", AVERAGEIF($C$2:$C$101, C60, $F$2:$F$101), F60) -> 113.83 | I60: =IF(G60="", AVERAGEIF($C$2:$C$101, C60, $G$2:$G$101), G60) -> 485
A61: PROD59 | B61: Men's Hair Styling Gel | C61: Beauty | D61: Haircare | E61: Cline-Mccarthy | F61: 17.31 | G61: 399 | H61: =IF(F61="", AVERAGEIF($C$2:$C$101, C61, $F$2:$F$101), F61) -> 17.31 | I61: =IF(G61="", AVERAGEIF($C$2:$C$101, C61, $G$2:$G$101), G61) -> 399
A62: PROD60 | B62: Luxury Perfume Spray | C62: Beauty | D62: Fragrance | E62: Gibson, Green and Lopez | F62: 482.75 | G62: 444 | H62: =IF(F62="", AVERAGEIF($C$2:$C$101, C62, $F$2:$F$101), F62) -> 482.75 | I62: =IF(G62="", AVERAGEIF($C$2:$C$101, C62, $G$2:$G$101), G62) -> 444
A63: PROD61 | B63: Tennis Ball 3-Pack | C63: Sports | D63: Equipment | E63: Lopez LLC | F63: 103.45 | G63: 465 | H63: =IF(F63="", AVERAGEIF($C$2:$C$101, C63, $F$2:$F$101), F63) -> 103.45 | I63: =IF(G63="", AVERAGEIF($C$2:$C$101, C63, $G$2:$G$101), G63) -> 465
A64: PROD62 | B64: Laptop Cooling Pad | C64: Electronics | D64: Computer | E64: Murray, Gould and Ware | F64: 86.42 | G64: 222 | H64: =IF(F64="", AVERAGEIF($C$2:$C$101, C64, $F$2:$F$101), F64) -> 86.42 | I64: =IF(G64="", AVERAGEIF($C$2:$C$101, C64, $G$2:$G$101), G64) -> 222
A65: PROD63 | B65: Organic Sunscreen Lotion | C65: Beauty | D65: Skincare | E65: Anderson-Riley | F65: 266.86 | G65: 458 | H65: =IF(F65="", AVERAGEIF($C$2:$C$101, C65, $F$2:$F$101), F65) -> 266.86 | I65: =IF(G65="", AVERAGEIF($C$2:$C$101, C65, $G$2:$G$101), G65) -> 458
A66: PROD64 | B66: Matte Lipstick Set | C66: Beauty | D66: Makeup | E66: Zhang Inc | F66: 299.11 | G66: 118 | H66: =IF(F66="", AVERAGEIF($C$2:$C$101, C66, $F$2:$F$101), F66) -> 299.11 | I66: =IF(G66="", AVERAGEIF($C$2:$C$101, C66, $G$2:$G$101), G66) -> 118
A67: PROD65 | B67: Adjustable Dumbbells 20kg | C67: Sports | D67: Fitness | E67: Montgomery, Benton and Miller | F67: 240.63 | G67: 423 | H67: =IF(F67="", AVERAGEIF($C$2:$C$101, C67, $F$2:$F$101), F67) -> 240.63 | I67: =IF(G67="", AVERAGEIF($C$2:$C$101, C67, $G$2:$G$101), G67) -> 423
A68: PROD66 | B68: Women's Hair Dryer Brush | C68: Beauty | D68: Haircare | E68: Torres, Spencer and Potter | F68: 340.39 | G68: 177 | H68: =IF(F68="", AVERAGEIF($C$2:$C$101, C68, $F$2:$F$101), F68) -> 340.39 | I68: =IF(G68="", AVERAGEIF($C$2:$C$101, C68, $G$2:$G$101), G68) -> 177
A69: PROD67 | B69: Smart LED Light Strip | C69: Electronics | D69: Accessories | E69: Flores-Davis | F69: 349.17 | G69: 476 | H69: =IF(F69="", AVERAGEIF($C$2:$C$101, C69, $F$2:$F$101), F69) -> 349.17 | I69: =IF(G69="", AVERAGEIF($C$2:$C$101, C69, $G$2:$G$101), G69) -> 476
... A84: PROD82 | B84: Fitness Resistance Bands | C84: Sports | D84: Fitness | E84: Reese-Watson | F84: 152.92 | G84: 281 | H84: =IF(F84="", AVERAGEIF($C$2:$C$101, C84, $F$2:$F$101), F84) -> 152.92 | I84: =IF(G84="", AVERAGEIF($C$2:$C$101, C84, $G$2:$G$101), G84) -> 281
A85: PROD83 | B85: Hydrating Face Cleanser | C85: Beauty | D85: Skincare | E85: Butler Group | G85: 159 | H85: =IF(F85="", AVERAGEIF($C$2:$C$101, C85, $F$2:$F$101), F85) -> 250.41615 | I85: =IF(G85="", AVERAGEIF($C$2:$C$101, C85, $G$2:$G$101), G85) -> 159
A86: PROD84 | B86: Wooden Bookshelf | C86: Home | D86: Furniture | E86: Collins-Stephenson | F86: 388.46 | G86: 208 | H86: =IF(F86="", AVERAGEIF($C$2:$C$101, C86, $F$2:$F$101), F86) -> 388.46 | I86: =IF(G86="", AVERAGEIF($C$2:$C$101, C86, $G$2:$G$101), G86) -> 208
A87: PROD85 | B87: Women's Beanie Hat | C87: Clothing | D87: Accessories | E87: Richardson-Carrillo | F87: 119.57 | G87: 210 | H87: =IF(F87="", AVERAGEIF($C$2:$C$101, C87, $F$2:$F$101), F87) -> 119.57 | I87: =IF(G87="", AVERAGEIF($C$2:$C$101, C87, $G$2:$G$101), G87) -> 210
A88: PROD86 | B88: Kitchen Cutting Board | C88: Home | D88: Kitchen | E88: Taylor, Dodson and Johnston | F88: 176.07 | G88: 82 | H88: =IF(F88="", AVERAGEIF($C$2:$C$101, C88, $F$2:$F$101), F88) -> 176.07 | I88: =IF(G88="", AVERAGEIF($C$2:$C$101, C88, $G$2:$G$101), G88) -> 82
A89: PROD87 | B89: LED Bedside Lamp | C89: Home | D89: Lighting | E89: Aguilar, Horton and Lewis | F89: 371.38 | G89: 220 | H89: =IF(F89="", AVERAGEIF($C$2:$C$101, C89, $F$2:$F$101), F89) -> 371.38 | I89: =IF(G89="", AVERAGEIF($C$2:$C$101, C89, $G$2:$G$101), G89) -> 220
A90: PROD88 | B90: Sports Wrist Sweatbands | C90: Sports | D90: Accessories | E90: Olsen-Daniels | F90: 131.24 | G90: 232 | H90: =IF(F90="", AVERAGEIF($C$2:$C$101, C90, $F$2:$F$101), F90) -> 131.24 | I90: =IF(G90="", AVERAGEIF($C$2:$C$101, C90, $G$2:$G$101), G90) -> 232
A91: PROD89 | B91: Face Foundation Kit | C91: Beauty | D91: Makeup | E91: Taylor-Elliott | F91: 183.04 | G91: 457 | H91: =IF(F91="", AVERAGEIF($C$2:$C$101, C91, $F$2:$F$101), F91) -> 183.04 | I91: =IF(G91="", AVERAGEIF($C$2:$C$101, C91, $G$2:$G$101), G91) -> 457
A92: PROD90 | B92: Gaming Mouse Pad XL | C92: Electronics | D92: Accessories | E92: Sharp, Taylor and Rodriguez | F92: 340.14 | G92: 361 | H92: =IF(F92="", AVERAGEIF($C$2:$C$101, C92, $F$2:$F$101), F92) -> 340.14 | I92: =IF(G92="", AVERAGEIF($C$2:$C$101, C92, $G$2:$G$101), G92) -> 361
A93: PROD91 | B93: Women's High Heels | C93: Clothing | D93: Footwear | E93: Smith-Charles | F93: 438.25 | G93: 496 | H93: =IF(F93="", AVERAGEIF($C$2:$C$101, C93, $F$2:$F$101), F93) -> 438.25 | I93: =IF(G93="", AVERAGEIF($C$2:$C$101, C93, $G$2:$G$101), G93) -> 496
A94: PROD92 | B94: Microwave Oven | C94: Home | D94: Appliances | E94: Green, Powell and Palmer | F94: 447.43 | G94: 191 | H94: =IF(F94="", AVERAGEIF($C$2:$C$101, C94, $F$2:$F$101), F94) -> 447.43 | I94: =IF(G94="", AVERAGEIF($C$2:$C$101, C94, $G$2:$G$101), G94) -> 191
A95: PROD93 | B95: USB-C Laptop Charger | C95: Electronics | D95: Computer | E95: Martin LLC | F95: 377.52 | G95: 485 | H95: =IF(F95="", AVERAGEIF($C$2:$C$101, C95, $F$2:$F$101), F95) -> 377.52 | I95: =IF(G95="", AVERAGEIF($C$2:$C$101, C95, $G$2:$G$101), G95) -> 485
A96: PROD94 | B96: Vitamin E Body Lotion | C96: Beauty | D96: Skincare | E96: Hoffman-Williams | F96: 358.47 | G96: 213 | H96: =IF(F96="", AVERAGEIF($C$2:$C$101, C96, $F$2:$F$101), F96) -> 358.47 | I96: =IF(G96="", AVERAGEIF($C$2:$C$101, C96, $G$2:$G$101), G96) -> 213
A97: PROD95 | B97: Sports Stopwatch Basic | C97: Sports | D97: Accessories | E97: Wilson Group | F97: 60.65 | G97: 75 | H97: =IF(F97="", AVERAGEIF($C$2:$C$101, C97, $F$2:$F$101), F97) -> 60.65 | I97: =IF(G97="", AVERAGEIF($C$2:$C$101, C97, $G$2:$G$101), G97) -> 75
... A101: PROD99 | B101: Stainless Steel Cookware Set | C101: Home | D101: Kitchen | E101: Campbell Ltd | F101: 201.41 | G101: 146 | H101: =IF(F101="", AVERAGEIF($C$2:$C$101, C101, $F$2:$F$101), F101) -> 201.41 | I101: =IF(G101="", AVERAGEIF($C$2:$C$101, C101, $G$2:$G$101), G101) -> 146

Sheet Sales
A1: Sales_ID | B1: Order_Date | C1: Customer_ID | D1: Product_ID | E1: hj | F1: Store_ID | G1: Quantity | H1: Unit_Price | I1: Discount | J1: Payment_Type | K1: Total_Amount | L1: Quantity Corrected | M1: Unit Price Corrected | N1: Discount Corrected | O1: Total Amount Corrected
A2: SALE0 | B2: 45480 | C2: CUST1409 | D2: PROD97 | E2: =VLOOKUP(D2,Product!$A$2:$I$101,3,FALSE) -> Sports | F2: STORE3 | G2: 1 | H2: 218.04 | I2: 0.09 | J2: Credit Card | K2: 198.4164 | L2: =IF(G2="", AVERAGEIF($E$2:$E$101, E3, $G$2:$G$101), G2) -> 1 | M2: =IF(H2="", IFERROR(AVERAGEIF($E$2:$E$101, E2, $H$2:$H$101), ""), H2) -> 218.04 | N2: =IF(I2="", AVERAGEIF($E$2:$E$101, E3, $I$2:$I$101), I2) -> 0.09 | O2: =IF(K2="", AVERAGEIF($E$2:$E$101, E3, $K$2:$K$101), K2) -> 198.4164
A3: SALE1 | B3: 45285 | C3: CUST1467 | D3: PROD74 | E3: =VLOOKUP(D3,Product!$A$2:$I$101,3,FALSE) -> Electronics | F3: STORE17 | G3: 3 | H3: 104.47 | I3: 0.27 | J3: PayPal | K3: 228.7893 | L3: =IF(G3="", AVERAGEIF($E$2:$E$101, E4, $G$2:$G$101), G3) -> 3 | M3: =IF(H3="", IFERROR(AVERAGEIF($E$2:$E$101, E3, $H$2:$H$101), ""), H3) -> 104.47 | N3: =IF(I3="", AVERAGEIF($E$2:$E$101, E4, $I$2:$I$101), I3) -> 0.27 | O3: =IF(K3="", AVERAGEIF($E$2:$E$101, E4, $K$2:$K$101), K3) -> 228.7893 | Q3: Summary
A4: SALE2 | B4: 45446 | C4: CUST1056 | D4: PROD49 | E4: =VLOOKUP(D4,Product!$A$2:$I$101,3,FALSE) -> Beauty | F4: STORE8 | G4: 4 | H4: 914.05 | I4: 0.25 | J4: Credit Card | K4: 2742.15 | L4: =IF(G4="", AVERAGEIF($E$2:$E$101, E5, $G$2:$G$101), G4) -> 4 | M4: =IF(H4="", IFERROR(AVERAGEIF($E$2:$E$101, E4, $H$2:$H$101), ""), H4) -> 914.05 | N4: =IF(I4="", AVERAGEIF($E$2:$E$101, E5, $I$2:$I$101), I4) -> 0.25 | O4: =IF(K4="", AVERAGEIF($E$2:$E$101, E5, $K$2:$K$101), K4) -> 2742.15 | Q4: 1)use if, iferror, averageif to find quantity, unit price,
A5: SALE3 | B5: 45259 | C5: CUST1346 | D5: PROD76 | E5: =VLOOKUP(D5,Product!$A$2:$I$101,3,FALSE) -> Electronics | F5: STORE8 | G5: 1 | H5: 921.51 | I5: 0.16 | J5: COD | K5: 774.0684 | L5: =IF(G5="", AVERAGEIF($E$2:$E$101, E6, $G$2:$G$101), G5) -> 1 | M5: =IF(H5="", IFERROR(AVERAGEIF($E$2:$E$101, E5, $H$2:$H$101), ""), H5) -> 921.51 | N5: =IF(I5="", AVERAGEIF($E$2:$E$101, E6, $I$2:$I$101), I5) -> 0.16 | O5: =IF(K5="", AVERAGEIF($E$2:$E$101, E6, $K$2:$K$101), K5) -> 774.0684 | Q5: discount, total amount of missing values
A6: SALE4 | B6: 45297 | C6: CUST1493 | D6: PROD59 | E6: =VLOOKUP(D6,Product!$A$2:$I$101,3,FALSE) -> Beauty | F6: STORE5 | G6: 3 | H6: 745.3 | I6: 0.18 | J6: Credit Card | K6: 1833.438 | L6: =IF(G6="", AVERAGEIF($E$2:$E$101, E7, $G$2:$G$101), G6) -> 3 | M6: =IF(H6="", IFERROR(AVERAGEIF($E$2:$E$101, E6, $H$2:$H$101), ""), H6) -> 745.3 | N6: =IF(I6="", AVERAGEIF($E$2:$E$101, E7, $I$2:$I$101), I6) -> 0.18 | O6: =IF(K6="", AVERAGEIF($E$2:$E$101, E7, $K$2:$K$101), K6) -> 1833.438 | Q6: 2) used text formula to makes rupees in unit price
A7: SALE5 | B7: 45499 | C7: CUST1116 | D7: PROD15 | E7: =VLOOKUP(D7,Product!$A$2:$I$101,3,FALSE) -> Electronics | F7: STORE7 | G7: 3 | H7: 147.01 | I7: 0.19 | J7: COD | K7: 357.2343 | L7: =IF(G7="", AVERAGEIF($E$2:$E$101, E8, $G$2:$G$101), G7) -> 3 | M7: =IF(H7="", IFERROR(AVERAGEIF($E$2:$E$101, E7, $H$2:$H$101), ""), H7) -> 147.01 | N7: =IF(I7="", AVERAGEIF($E$2:$E$101, E8, $I$2:$I$101), I7) -> 0.19 | O7: =IF(K7="", AVERAGEIF($E$2:$E$101, E8, $K$2:$K$101), K7) -> 357.2343
A8: SALE6 | B8: 45850 | C8: CUST1016 | D8: PROD56 | E8: =VLOOKUP(D8,Product!$A$2:$I$101,3,FALSE) -> Home | F8: STORE4 | G8: 2 | H8: 785.31 | I8: 0.15 | J8: PayPal | K8: 1335.027 | L8: =IF(G8="", AVERAGEIF($E$2:$E$101, E9, $G$2:$G$101), G8) -> 2 | M8: =IF(H8="", IFERROR(AVERAGEIF($E$2:$E$101, E8, $H$2:$H$101), ""), H8) -> 785.31 | N8: =IF(I8="", AVERAGEIF($E$2:$E$101, E9, $I$2:$I$101), I8) -> 0.15 | O8: =IF(K8="", AVERAGEIF($E$2:$E$101, E9, $K$2:$K$101), K8) -> 1335.027
A9: SALE7 | B9: 45248 | C9: CUST1152 | D9: PROD70 | E9: =VLOOKUP(D9,Product!$A$2:$I$101,3,FALSE) -> Home | F9: STORE8 | G9: 4 | H9: 342.39 | I9: 0.23 | J9: PayPal | K9: 1054.5612 | L9: =IF(G9="", AVERAGEIF($E$2:$E$101, E10, $G$2:$G$101), G9) -> 4 | M9: =IF(H9="", IFERROR(AVERAGEIF($E$2:$E$101, E9, $H$2:$H$101), ""), H9) -> 342.39 | N9: =IF(I9="", AVERAGEIF($E$2:$E$101, E10, $I$2:$I$101), I9) -> 0.23 | O9: =IF(K9="", AVERAGEIF($E$2:$E$101, E10, $K$2:$K$101), K9) -> 1054.5612
A10: SALE8 | B10: 45781 | C10: CUST1187 | D10: PROD99 | E10: =VLOOKUP(D10,Product!$A$2:$I$101,3,FALSE) -> Home | F10: STORE5 | H10: 448.25 | I10: 0.07 | J10: PayPal | K10: 1250.6175 | L10: =IF(G10="", AVERAGEIF($E$2:$E$101, E11, $G$2:$G$101), G10) -> 2.1875 | M10: =IF(H10="", IFERROR(AVERAGEIF($E$2:$E$101, E10, $H$2:$H$101), ""), H10) -> 448.25 | N10: =IF(I10="", AVERAGEIF($E$2:$E$101, E11, $I$2:$I$101), I10) -> 0.07 | O10: =IF(K10="", AVERAGEIF($E$2:$E$101, E11, $K$2:$K$101), K10) -> 1250.6175
A11: SALE9 | B11: 45869 | C11: CUST1464 | D11: PROD33 | E11: =VLOOKUP(D11,Product!$A$2:$I$101,3,FALSE) -> Home | F11: STORE0 | G11: 2 | H11: 873.17 | I11: 0.23 | J11: PayPal | K11: 1344.6818 | L11: =IF(G11="", AVERAGEIF($E$2:$E$101, E12, $G$2:$G$101), G11) -> 2 | M11: =IF(H11="", IFERROR(AVERAGEIF($E$2:$E$101, E11, $H$2:$H$101), ""), H11) -> 873.17 | N11: =IF(I11="", AVERAGEIF($E$2:$E$101, E12, $I$2:$I$101), I11) -> 0.23 | O11: =IF(K11="", AVERAGEIF($E$2:$E$101, E12, $K$2:$K$101), K11) -> 1344.6818
A12: SALE10 | B12: 45335 | C12: CUST1065 | D12: PROD24 | E12: =VLOOKUP(D12,Product!$A$2:$I$101,3,FALSE) -> Sports | F12: STORE14 | G12: 1 | H12: 278.63 | I12: 0.07 | J12: Credit Card | K12: 259.1259 | L12: =IF(G12="", AVERAGEIF($E$2:$E$101, E13, $G$2:$G$101), G12) -> 1 | M12: =IF(H12="", IFERROR(AVERAGEIF($E$2:$E$101, E12, $H$2:$H$101), ""), H12) -> 278.63 | N12: =IF(I12="", AVERAGEIF($E$2:$E$101, E13, $I$2:$I$101), I12) -> 0.07 | O12: =IF(K12="", AVERAGEIF($E$2:$E$101, E13, $K$2:$K$101), K12) -> 259.1259
A13: SALE11 | B13: 45801 | C13: CUST1320 | D13: PROD39 | E13: =VLOOKUP(D13,Product!$A$2:$I$101,3,FALSE) -> Electronics | F13: STORE1 | G13: 4 | H13: 286.92 | I13: 0.17 | J13: Credit Card | K13: 952.5744 | L13: =IF(G13="", AVERAGEIF($E$2:$E$101, E14, $G$2:$G$101), G13) -> 4 | M13: =IF(H13="", IFERROR(AVERAGEIF($E$2:$E$101, E13, $H$2:$H$101), ""), H13) -> 286.92 | N13: =IF(I13="", AVERAGEIF($E$2:$E$101, E14, $I$2:$I$101), I13) -> 0.17 | O13: =IF(K13="", AVERAGEIF($E$2:$E$101, E14, $K$2:$K$101), K13) -> 952.5744
A14: SALE12 | B14: 45528 | C14: CUST1237 | D14: PROD88 | E14: =VLOOKUP(D14,Product!$A$2:$I$101,3,FALSE) -> Sports | F14: STORE4 | G14: 4 | H14: 644.58 | I14: 0.01 | J14: Credit Card | K14: 2552.5368 | L14: =IF(G14="", AVERAGEIF($E$2:$E$101, E15, $G$2:$G$101), G14) -> 4 | M14: =IF(H14="", IFERROR(AVERAGEIF($E$2:$E$101, E14, $H$2:$H$101), ""), H14) -> 644.58 | N14: =IF(I14="", AVERAGEIF($E$2:$E$101, E15, $I$2:$I$101), I14) -> 0.01 | O14: =IF(K14="", AVERAGEIF($E$2:$E$101, E15, $K$2:$K$101), K14) -> 2552.5368
A15: SALE13 | B15: 45875 | C15: CUST1443 | D15: PROD34 | E15: =VLOOKUP(D15,Product!$A$2:$I$101,3,FALSE) -> Electronics | F15: STORE16 | G15: 2 | H15: 316.9 | I15: 0.3 | J15: PayPal | K15: 443.66 | L15: =IF(G15="", AVERAGEIF($E$2:$E$101, E16, $G$2:$G$101), G15) -> 2 | M15: =IF(H15="", IFERROR(AVERAGEIF($E$2:$E$101, E15, $H$2:$H$101), ""), H15) -> 316.9 | N15: =IF(I15="", AVERAGEIF($E$2:$E$101, E16, $I$2:$I$101), I15) -> 0.3 | O15: =IF(K15="", AVERAGEIF($E$2:$E$101, E16, $K$2:$K$101), K15) -> 443.66
A16: SALE14 | B16: 45829 | C16: CUST1348 | D16: PROD24 | E16: =VLOOKUP(D16,Product!$A$2:$I$101,3,FALSE) -> Sports | F16: STORE15 | G16: 4 | H16: 403.47 | I16: 0.29 | J16: PayPal | K16: 1145.8548 | L16: =IF(G16="", AVERAGEIF($E$2:$E$101, E17, $G$2:$G$101), G16) -> 4 | M16: =IF(H16="", IFERROR(AVERAGEIF($E$2:$E$101, E16, $H$2:$H$101), ""), H16) -> 403.47 | N16: =IF(I16="", AVERAGEIF($E$2:$E$101, E17, $I$2:$I$101), I16) -> 0.29 | O16: =IF(K16="", AVERAGEIF($E$2:$E$101, E17, $K$2:$K$101), K16) -> 1145.8548
A17: SALE15 | B17: 45636 | C17: CUST1435 | D17: PROD36 | E17: =VLOOKUP(D17,Product!$A$2:$I$101,3,FALSE) -> Clothing | F17: STORE9 | H17: 871.34 | I17: 0.04 | J17: COD | K17: 2509.4592 | L17: =IF(G17="", AVERAGEIF($E$2:$E$101, E18, $G$2:$G$101), G17) -> 2.2962963 | M17: =IF(H17="", IFERROR(AVERAGEIF($E$2:$E$101, E17, $H$2:$H$101), ""), H17) -> 871.34 | N17: =IF(I17="", AVERAGEIF($E$2:$E$101, E18, $I$2:$I$101), I17) -> 0.04 | O17: =IF(K17="", AVERAGEIF($E$2:$E$101, E18, $K$2:$K$101), K17) -> 2509.4592
A18: SALE16 | B18: 45913 | C18: CUST1276 | D18: PROD65 | E18: =VLOOKUP(D18,Product!$A$2:$I$101,3,FALSE) -> Sports | F18: STORE19 | G18: 2 | H18: 451.98 | I18: 0.25 | J18: Credit Card | K18: 677.97 | L18: =IF(G18="", AVERAGEIF($E$2:$E$101, E19, $G$2:$G$101), G18) -> 2 | M18: =IF(H18="", IFERROR(AVERAGEIF($E$2:$E$101, E18, $H$2:$H$101), ""), H18) -> 451.98 | N18: =IF(I18="", AVERAGEIF($E$2:$E$101, E19, $I$2:$I$101), I18) -> 0.25 | O18: =IF(K18="", AVERAGEIF($E$2:$E$101, E19, $K$2:$K$101), K18) -> 677.97
A19: SALE17 | B19: 45637 | C19: CUST1079 | D19: PROD27 | E19: =VLOOKUP(D19,Product!$A$2:$I$101,3,FALSE) -> Home | F19: STORE4 | G19: 2 | H19: 502.69 | I19: 0.23 | J19: Credit Card | K19: 774.1426 | L19: =IF(G19="", AVERAGEIF($E$2:$E$101, E20, $G$2:$G$101), G19) -> 2 | M19: =IF(H19="", IFERROR(AVERAGEIF($E$2:$E$101, E19, $H$2:$H$101), ""), H19) -> 502.69 | N19: =IF(I19="", AVERAGEIF($E$2:$E$101, E20, $I$2:$I$101), I19) -> 0.23 | O19: =IF(K19="", AVERAGEIF($E$2:$E$101, E20, $K$2:$K$101), K19) -> 774.1426
A20: SALE18 | B20: 45517 | C20: CUST1094 | D20: PROD39 | E20: =VLOOKUP(D20,Product!$A$2:$I$101,3,FALSE) -> Electronics | F20: STORE4 | G20: 2 | H20: 559.23 | I20: 0.25 | J20: COD | K20: 838.845 | L20: =IF(G20="", AVERAGEIF($E$2:$E$101, E21, $G$2:$G$101), G20) -> 2 | M20: =IF(H20="", IFERROR(AVERAGEIF($E$2:$E$101, E20, $H$2:$H$101), ""), H20) -> 559.23 | N20: =IF(I20="", AVERAGEIF($E$2:$E$101, E21, $I$2:$I$101), I20) -> 0.25 | O20: =IF(K20="", AVERAGEIF($E$2:$E$101, E21, $K$2:$K$101), K20) -> 838.845
A21: SALE19 | B21: 45369 | C21: CUST1239 | D21: PROD60 | E21: =VLOOKUP(D21,Product!$A$2:$I$101,3,FALSE) -> Beauty | F21: STORE13 | G21: 4 | I21: 0.04 | J21: COD | K21: 1782.4512 | L21: =IF(G21="", AVERAGEIF($E$2:$E$101, E22, $G$2:$G$101), G21) -> 4 | M21: =IF(H21="", AVERAGEIF($E$2:$E$101, E22, $H$2:$H$101), H21) -> 443.50037 | N21: =IF(I21="", AVERAGEIF($E$2:$E$101, E22, $I$2:$I$101), I21) -> 0.04 | O21: =IF(K21="", AVERAGEIF($E$2:$E$101, E22, $K$2:$K$101), K21) -> 1782.4512
A22: SALE20 | B22: 45843 | C22: CUST1144 | D22: PROD72 | E22: =VLOOKUP(D22,Product!$A$2:$I$101,3,FALSE) -> Sports | F22: STORE17 | G22: 3 | H22: 986.04 | I22: 0.27 | J22: COD | K22: 2159.4276 | L22: =IF(G22="", AVERAGEIF($E$2:$E$101, E23, $G$2:$G$101), G22) -> 3 | M22: =IF(H22="", IFERROR(AVERAGEIF($E$2:$E$101, E22, $H$2:$H$101), ""), H22) -> 986.04 | N22: =IF(I22="", AVERAGEIF($E$2:$E$101, E23, $I$2:$I$101), I22) -> 0.27 | O22: =IF(K22="", AVERAGEIF($E$2:$E$101, E23, $K$2:$K$101), K22) -> 2159.4276
A23: SALE21 | B23: 45447 | C23: CUST1396 | D23: PROD43 | E23: =VLOOKUP(D23,Product!$A$2:$I$101,3,FALSE) -> Electronics | F23: STORE18 | G23: 1 | H23: 589.56 | I23: 0.22 | J23: Credit Card | K23: 459.8568 | L23: =IF(G23="", AVERAGEIF($E$2:$E$101, E24, $G$2:$G$101), G23) -> 1 | M23: =IF(H23="", IFERROR(AVERAGEIF($E$2:$E$101, E23, $H$2:$H$101), ""), H23) -> 589.56 | N23: =IF(I23="", AVERAGEIF($E$2:$E$101, E24, $I$2:$I$101), I23) -> 0.22 | O23: =IF(K23="", AVERAGEIF($E$2:$E$101, E24, $K$2:$K$101), K23) -> 459.8568
A24: SALE22 | B24: 45394 | C24: CUST1476 | D24: PROD69 | E24: =VLOOKUP(D24,Product!$A$2:$I$101,3,FALSE) -> Clothing | F24: STORE10 | G24: 3 | H24: 979.42 | I24: 0.03 | J24: PayPal | K24: 2850.1122 | L24: =IF(G24="", AVERAGEIF($E$2:$E$101, E25, $G$2:$G$101), G24) -> 3 | M24: =IF(H24="", IFERROR(AVERAGEIF($E$2:$E$101, E24, $H$2:$H$101), ""), H24) -> 979.42 | N24: =IF(I24="", AVERAGEIF($E$2:$E$101, E25, $I$2:$I$101), I24) -> 0.03 | O24: =IF(K24="", AVERAGEIF($E$2:$E$101, E25, $K$2:$K$101), K24) -> 2850.1122
A25: SALE23 | B25: 45466 | C25: CUST1368 | D25: PROD12 | E25: =VLOOKUP(D25,Product!$A$2:$I$101,3,FALSE) -> Beauty | F25: STORE8 | G25: 1 | H25: 719.28 | I25: 0.08 | J25: Credit Card | K25: 661.7376 | L25: =IF(G25="", AVERAGEIF($E$2:$E$101, E26, $G$2:$G$101), G25) -> 1 | M25: =IF(H25="", IFERROR(AVERAGEIF($E$2:$E$101, E25, $H$2:$H$101), ""), H25) -> 719.28 | N25: =IF(I25="", AVERAGEIF($E$2:$E$101, E26, $I$2:$I$101), I25) -> 0.08 | O25: =IF(K25="", AVERAGEIF($E$2:$E$101, E26, $K$2:$K$101), K25) -> 661.7376
A26: SALE24 | B26: 45908 | C26: CUST1186 | D26: PROD67 | E26: =VLOOKUP(D26,Product!$A$2:$I$101,3,FALSE) -> Electronics | F26: STORE6 | G26: 3 | H26: 77.6 | I26: 0.07 | J26: Credit Card | K26: 216.504 | L26: =IF(G26="", AVERAGEIF($E$2:$E$101, E27, $G$2:$G$101), G26) -> 3 | M26: =IF(H26="", IFERROR(AVERAGEIF($E$2:$E$101, E26, $H$2:$H$101), ""), H26) -> 77.6 | N26: =IF(I26="", AVERAGEIF($E$2:$E$101, E27, $I$2:$I$101), I26) -> 0.07 | O26: =IF(K26="", AVERAGEIF($E$2:$E$101, E27, $K$2:$K$101), K26) -> 216.504
A27: SALE25 | B27: 45552 | C27: CUST1381 | D27: PROD5 | E27: =VLOOKUP(D27,Product!$A$2:$I$101,3,FALSE) -> Clothing | F27: STORE3 | G27: 4 | H27: 852.71 | I27: 0.14 | J27: PayPal | K27: 2933.3224 | L27: =IF(G27="", AVERAGEIF($E$2:$E$101, E28, $G$2:$G$101), G27) -> 4 | M27: =IF(H27="", IFERROR(AVERAGEIF($E$2:$E$101, E27, $H$2:$H$101), ""), H27) -> 852.71 | N27: =IF(I27="", AVERAGEIF($E$2:$E$101, E28, $I$2:$I$101), I27) -> 0.14 | O27: =IF(K27="", AVERAGEIF($E$2:$E$101, E28, $K$2:$K$101), K27) -> 2933.3224
A28: SALE26 | B28: 45294 | C28: CUST1213 | D28: PROD98 | E28: =VLOOKUP(D28,Product!$A$2:$I$101,3,FALSE) -> Electronics | F28: STORE8 | G28: 4 | H28: 156.16 | J28: Credit Card | K28: 599.6544 | L28: =IF(G28="", AVERAGEIF($E$2:$E$101, E29, $G$2:$G$101), G28) -> 4 | M28: =IF(H28="", IFERROR(AVERAGEIF($E$2:$E$101, E28, $H$2:$H$101), ""), H28) -> 156.16 | N28: =IF(I28="", AVERAGEIF($E$2:$E$101, E29, $I$2:$I$101), I28) -> 0.17894737 | O28: =IF(K28="", AVERAGEIF($E$2:$E$101, E29, $K$2:$K$101), K28) -> 599.6544
A29: SALE27 | B29: 45710 | C29: CUST1200 | D29: PROD77 | E29: =VLOOKUP(D29,Product!$A$2:$I$101,3,FALSE) -> Electronics | F29: STORE8 | G29: 3 | H29: 815.49 | I29: 0.17 | J29: Credit Card | K29: 2030.5701 | L29: =IF(G29="", AVERAGEIF($E$2:$E$101, E30, $G$2:$G$101), G29) -> 3 | M29: =IF(H29="", IFERROR(AVERAGEIF($E$2:$E$101, E29, $H$2:$H$101), ""), H29) -> 815.49 | N29: =IF(I29="", AVERAGEIF($E$2:$E$101, E30, $I$2:$I$101), I29) -> 0.17 | O29: =IF(K29="", AVERAGEIF($E$2:$E$101, E30, $K$2:$K$101), K29) -> 2030.5701
A30: SALE28 | B30: 45923 | C30: CUST1148 | D30: PROD13 | E30: =VLOOKUP(D30,Product!$A$2:$I$101,3,FALSE) -> Electronics | F30: STORE2 | G30: 2 | H30: 74.21 | I30: 0.11 | J30: PayPal | K30: 132.0938 | L30: =IF(G30="", AVERAGEIF($E$2:$E$101, E31, $G$2:$G$101), G30) -> 2 | M30: =IF(H30="", IFERROR(AVERAGEIF($E$2:$E$101, E30, $H$2:$H$101), ""), H30) -> 74.21 | N30: =IF(I30="", AVERAGEIF($E$2:$E$101, E31, $I$2:$I$101), I30) -> 0.11 | O30: =IF(K30="", AVERAGEIF($E$2:$E$101, E31, $K$2:$K$101), K30) -> 132.0938
A31: SALE29 | B31: 45302 | C31: CUST1348 | D31: PROD99 | E31: =VLOOKUP(D31,Product!$A$2:$I$101,3,FALSE) -> Home | F31: STORE3 | H31: 451.67 | I31: 0.15 | J31: Credit Card | K31: 1535.678 | L31: =IF(G31="", AVERAGEIF($E$2:$E$101, E32, $G$2:$G$101), G31) -> 2.6923077 | M31: =IF(H31="", IFERROR(AVERAGEIF($E$2:$E$101, E31, $H$2:$H$101), ""), H31) -> 451.67 | N31: =IF(I31="", AVERAGEIF($E$2:$E$101, E32, $I$2:$I$101), I31) -> 0.15 | O31: =IF(K31="", AVERAGEIF($E$2:$E$101, E32, $K$2:$K$101), K31) -> 1535.678
A32: SALE30 | B32: 45217 | C32: CUST1028 | D32: PROD5 | E32: =VLOOKUP(D32,Product!$A$2:$I$101,3,FALSE) -> Clothing | F32: STORE19 | G32: 1 | H32: 429.38 | I32: 0.13 | J32: PayPal | K32: 373.5606 | L32: =IF(G32="", AVERAGEIF($E$2:$E$101, E33, $G$2:$G$101), G32) -> 1 | M32: =IF(H32="", IFERROR(AVERAGEIF($E$2:$E$101, E32, $H$2:$H$101), ""), H32) -> 429.38 | N32: =IF(I32="", AVERAGEIF($E$2:$E$101, E33, $I$2:$I$101), I32) -> 0.13 | O32: =IF(K32="", AVERAGEIF($E$2:$E$101, E33, $K$2:$K$101), K32) -> 373.5606
A33: SALE31 | B33: 45593 | C33: CUST1412 | D33: PROD53 | E33: =VLOOKUP(D33,Product!$A$2:$I$101,3,FALSE) -> Clothing | F33: STORE12 | G33: 2 | H33: 148.96 | I33: 0.03 | J33: COD | K33: 288.9824 | L33: =IF(G33="", AVERAGEIF($E$2:$E$101, E34, $G$2:$G$101), G33) -> 2 | M33: =IF(H33="", IFERROR(AVERAGEIF($E$2:$E$101, E33, $H$2:$H$101), ""), H33) -> 148.96 | N33: =IF(I33="", AVERAGEIF($E$2:$E$101, E34, $I$2:$I$101), I33) -> 0.03 | O33: =IF(K33="", AVERAGEIF($E$2:$E$101, E34, $K$2:$K$101), K33) -> 288.9824
A34: SALE32 | B34: 45597 | C34: CUST1398 | D34: PROD75 | E34: =VLOOKUP(D34,Product!$A$2:$I$101,3,FALSE) -> Clothing | F34: STORE8 | G34: 4 | H34: 313.83 | I34: 0.08 | J34: Credit Card | K34: 1154.8944 | L34: =IF(G34="", AVERAGEIF($E$2:$E$101, E35, $G$2:$G$101), G34) -> 4 | M34: =IF(H34="", IFERROR(AVERAGEIF($E$2:$E$101, E34, $H$2:$H$101), ""), H34) -> 313.83 | N34: =IF(I34="", AVERAGEIF($E$2:$E$101, E35, $I$2:$I$101), I34) -> 0.08 | O34: =IF(K34="", AVERAGEIF($E$2:$E$101, E35, $K$2:$K$101), K34) -> 1154.8944
A35: SALE33 | B35: 45620 | C35: CUST1453 | D35: PROD12 | E35: =VLOOKUP(D35,Product!$A$2:$I$101,3,FALSE) -> Beauty | F35: STORE6 | G35: 2 | H35: 717.31 | I35: 0.15 | J35: Credit Card | K35: 1219.427 | L35: =IF(G35="", AVERAGEIF($E$2:$E$101, E36, $G$2:$G$101), G35) -> 2 | M35: =IF(H35="", IFERROR(AVERAGEIF($E$2:$E$101, E35, $H$2:$H$101), ""), H35) -> 717.31 | N35: =IF(I35="", AVERAGEIF($E$2:$E$101, E36, $I$2:$I$101), I35) -> 0.15 | O35: =IF(K35="", AVERAGEIF($E$2:$E$101, E36, $K$2:$K$101), K35) -> 1219.427
A36: SALE34 | B36: 45215 | C36: CUST1344 | D36: PROD79 | E36: =VLOOKUP(D36,Product!$A$2:$I$101,3,FALSE) -> Home | F36: STORE1 | H36: 873.22 | I36: 0.18 | J36: Credit Card | K36: 2148.1212 | L36: =IF(G36="", AVERAGEIF($E$2:$E$101, E37, $G$2:$G$101), G36) -> 2.5 | M36: =IF(H36="", IFERROR(AVERAGEIF($E$2:$E$101, E36, $H$2:$H$101), ""), H36) -> 873.22 | N36: =IF(I36="", AVERAGEIF($E$2:$E$101, E37, $I$2:$I$101), I36) -> 0.18 | O36: =IF(K36="", AVERAGEIF($E$2:$E$101, E37, $K$2:$K$101), K36) -> 2148.1212
A37: SALE35 | B37: 45878 | C37: CUST1218 | D37: PROD16 | E37: =VLOOKUP(D37,Product!$A$2:$I$101,3,FALSE) -> Beauty | F37: STORE3 | G37: 4 | H37: 109.36 | I37: 0.19 | J37: COD | K37: 354.3264 | L37: =IF(G37="", AVERAGEIF($E$2:$E$101, E38, $G$2:$G$101), G37) -> 4 | M37: =IF(H37="", IFERROR(AVERAGEIF($E$2:$E$101, E37, $H$2:$H$101), ""), H37) -> 109.36 | N37: =IF(I37="", AVERAGEIF($E$2:$E$101, E38, $I$2:$I$101), I37) -> 0.19 | O37: =IF(K37="", AVERAGEIF($E$2:$E$101, E38, $K$2:$K$101), K37) -> 354.3264
A38: SALE36 | B38: 45635 | C38: CUST1086 | D38: PROD5 | E38: =VLOOKUP(D38,Product!$A$2:$I$101,3,FALSE) -> Clothing | F38: STORE7 | G38: 3 | H38: 559.52 | I38: 0.16 | J38: PayPal | K38: 1409.9904 | L38: =IF(G38="", AVERAGEIF($E$2:$E$101, E39, $G$2:$G$101), G38) -> 3 | M38: =IF(H38="", IFERROR(AVERAGEIF($E$2:$E$101, E38, $H$2:$H$101), ""), H38) -> 559.52 | N38: =IF(I38="", AVERAGEIF($E$2:$E$101, E39, $I$2:$I$101), I38) -> 0.16 | O38: =IF(K38="", AVERAGEIF($E$2:$E$101, E39, $K$2:$K$101), K38) -> 1409.9904
A39: SALE37 | B39: 45329 | C39: CUST1492 | D39: PROD10 | E39: =VLOOKUP(D39,Product!$A$2:$I$101,3,FALSE) -> Home | F39: STORE17 | G39: 3 | H39: 121.76 | I39: 0.27 | J39: PayPal | K39: 266.6544 | L39: =IF(G39="", AVERAGEIF($E$2:$E$101, E40, $G$2:$G$101), G39) -> 3 | M39: =IF(H39="", IFERROR(AVERAGEIF($E$2:$E$101, E39, $H$2:$H$101), ""), H39) -> 121.76 | N39: =IF(I39="", AVERAGEIF($E$2:$E$101, E40, $I$2:$I$101), I39) -> 0.27 | O39: =IF(K39="", AVERAGEIF($E$2:$E$101, E40, $K$2:$K$101), K39) -> 266.6544
A40: SALE38 | B40: 45378 | C40: CUST1189 | D40: PROD33 | E40: =VLOOKUP(D40,Product!$A$2:$I$101,3,FALSE) -> Home | F40: STORE13 | G40: 4 | H40: 735.32 | I40: 0.06 | J40: COD | K40: 2764.8032 | L40: =IF(G40="", AVERAGEIF($E$2:$E$101, E41, $G$2:$G$101), G40) -> 4 | M40: =IF(H40="", IFERROR(AVERAGEIF($E$2:$E$101, E40, $H$2:$H$101), ""), H40) -> 735.32 | N40: =IF(I40="", AVERAGEIF($E$2:$E$101, E41, $I$2:$I$101), I40) -> 0.06 | O40: =IF(K40="", AVERAGEIF($E$2:$E$101, E41, $K$2:$K$101), K40) -> 2764.8032
A41: SALE39 | B41: 45264 | C41: CUST1431 | D41: PROD94 | E41: =VLOOKUP(D41,Product!$A$2:$I$101,3,FALSE) -> Beauty | F41: STORE3 | G41: 2 | H41: 600.73 | I41: 0.08 | J41: Credit Card | K41: 1105.3432 | L41: =IF(G41="", AVERAGEIF($E$2:$E$101, E42, $G$2:$G$101), G41) -> 2 | M41: =IF(H41="", IFERROR(AVERAGEIF($E$2:$E$101, E41, $H$2:$H$101), ""), H41) -> 600.73 | N41: =IF(I41="", AVERAGEIF($E$2:$E$101, E42, $I$2:$I$101), I41) -> 0.08 | O41: =IF(K41="", AVERAGEIF($E$2:$E$101, E42, $K$2:$K$101), K41) -> 1105.3432 | P41: =AVERAGE(H4:H1999) -> 514.34584
A42: SALE40 | B42: 45486 | C42: CUST1072 | D42: PROD26 | E42: =VLOOKUP(D42,Product!$A$2:$I$101,3,FALSE) -> Electronics | F42: STORE19 | G42: 2 | H42: 873.86 | I42: 0.07 | J42: COD | K42: 1625.3796 | L42: =IF(G42="", AVERAGEIF($E$2:$E$101, E43, $G$2:$G$101), G42) -> 2 | M42: =IF(H42="", IFERROR(AVERAGEIF($E$2:$E$101, E42, $H$2:$H$101), ""), H42) -> 873.86 | N42: =IF(I42="", AVERAGEIF($E$2:$E$101, E43, $I$2:$I$101), I42) -> 0.07 | O42: =IF(K42="", AVERAGEIF($E$2:$E$101, E43, $K$2:$K$101), K42) -> 1625.3796
A43: SALE41 | B43: 45241 | C43: CUST1302 | D43: PROD23 | E43: =VLOOKUP(D43,Product!$A$2:$I$101,3,FALSE) -> Clothing | F43: STORE8 | G43: 3 | H43: 342.47 | I43: 0.08 | J43: PayPal | K43: 945.2172 | L43: =IF(G43="", AVERAGEIF($E$2:$E$101, E44, $G$2:$G$101), G43) -> 3 | M43: =IF(H43="", IFERROR(AVERAGEIF($E$2:$E$101, E43, $H$2:$H$101), ""), H43) -> 342.47 | N43: =IF(I43="", AVERAGEIF($E$2:$E$101, E44, $I$2:$I$101), I43) -> 0.08 | O43: =IF(K43="", AVERAGEIF($E$2:$E$101, E44, $K$2:$K$101), K43) -> 945.2172
A44: SALE42 | B44: 45649 | C44: CUST1335 | D44: PROD29 | E44: =VLOOKUP(D44,Product!$A$2:$I$101,3,FALSE) -> Home | F44: STORE9 | G44: 2 | H44: 915.15 | I44: 0.16 | J44: PayPal | K44: 1537.452 | L44: =IF(G44="", AVERAGEIF($E$2:$E$101, E45, $G$2:$G$101), G44) -> 2 | M44: =IF(H44="", IFERROR(AVERAGEIF($E$2:$E$101, E44, $H$2:$H$101), ""), H44) -> 915.15 | N44: =IF(I44="", AVERAGEIF($E$2:$E$101, E45, $I$2:$I$101), I44) -> 0.16 | O44: =IF(K44="", AVERAGEIF($E$2:$E$101, E45, $K$2:$K$101), K44) -> 1537.452
A45: SALE43 | B45: 45677 | C45: CUST1084 | D45: PROD33 | E45: =VLOOKUP(D45,Product!$A$2:$I$101,3,FALSE) -> Home | F45: STORE17 | H45: 863.11 | I45: 0.28 | J45: PayPal | K45: 1864.3176 | L45: =IF(G45="", AVERAGEIF($E$2:$E$101, E46, $G$2:$G$101), G45) -> 2.5714286 | M45: =IF(H45="", IFERROR(AVERAGEIF($E$2:$E$101, E45, $H$2:$H$101), ""), H45) -> 863.11 | N45: =IF(I45="", AVERAGEIF($E$2:$E$101, E46, $I$2:$I$101), I45) -> 0.28 | O45: =IF(K45="", AVERAGEIF($E$2:$E$101, E46, $K$2:$K$101), K45) -> 1864.3176
A46: SALE44 | B46: 45538 | C46: CUST1203 | D46: PROD43 | E46: =VLOOKUP(D46,Product!$A$2:$I$101,3,FALSE) -> Electronics | F46: STORE12 | G46: 2 | H46: 209.32 | I46: 0.23 | J46: COD | K46: 322.3528 | L46: =IF(G46="", AVERAGEIF($E$2:$E$101, E47, $G$2:$G$101), G46) -> 2 | M46: =IF(H46="", IFERROR(AVERAGEIF($E$2:$E$101, E46, $H$2:$H$101), ""), H46) -> 209.32 | N46: =IF(I46="", AVERAGEIF($E$2:$E$101, E47, $I$2:$I$101), I46) -> 0.23 | O46: =IF(K46="", AVERAGEIF($E$2:$E$101, E47, $K$2:$K$101), K46) -> 322.3528
A47: SALE45 | B47: 45606 | C47: CUST1470 | D47: PROD59 | E47: =VLOOKUP(D47,Product!$A$2:$I$101,3,FALSE) -> Beauty | F47: STORE8 | G47: 4 | H47: 288.6 | I47: 0.09 | J47: PayPal | K47: 1050.504 | L47: =IF(G47="", AVERAGEIF($E$2:$E$101, E48, $G$2:$G$101), G47) -> 4 | M47: =IF(H47="", IFERROR(AVERAGEIF($E$2:$E$101, E47, $H$2:$H$101), ""), H47) -> 288.6 | N47: =IF(I47="", AVERAGEIF($E$2:$E$101, E48, $I$2:$I$101), I47) -> 0.09 | O47: =IF(K47="", AVERAGEIF($E$2:$E$101, E48, $K$2:$K$101), K47) -> 1050.504
A48: SALE46 | B48: 45570 | C48: CUST1070 | D48: PROD78 | E48: =VLOOKUP(D48,Product!$A$2:$I$101,3,FALSE) -> Home | F48: STORE16 | G48: 1 | H48: 418.69 | I48: 0.06 | J48: PayPal | K48: 393.5686 | L48: =IF(G48="", AVERAGEIF($E$2:$E$101, E49, $G$2:$G$101), G48) -> 1 | M48: =IF(H48="", IFERROR(AVERAGEIF($E$2:$E$101, E48, $H$2:$H$101), ""), H48) -> 418.69 | N48: =IF(I48="", AVERAGEIF($E$2:$E$101, E49, $I$2:$I$101), I48) -> 0.06 | O48: =IF(K48="", AVERAGEIF($E$2:$E$101, E49, $K$2:$K$101), K48) -> 393.5686
A49: SALE47 | B49: 45466 | C49: CUST1008 | D49: PROD30 | E49: =VLOOKUP(D49,Product!$A$2:$I$101,3,FALSE) -> Home | F49: STORE11 | G49: 1 | H49: 135.78 | I49: 0.14 | J49: PayPal | K49: 116.7708 | L49: =IF(G49="", AVERAGEIF($E$2:$E$101, E50, $G$2:$G$101), G49) -> 1 | M49: =IF(H49="", IFERROR(AVERAGEIF($E$2:$E$101, E49, $H$2:$H$101), ""), H49) -> 135.78 | N49: =IF(I49="", AVERAGEIF($E$2:$E$101, E50, $I$2:$I$101), I49) -> 0.14 | O49: =IF(K49="", AVERAGEIF($E$2:$E$101, E50, $K$2:$K$101), K49) -> 116.7708
A50: SALE48 | B50: 45218 | C50: CUST1203 | D50: PROD44 | E50: =VLOOKUP(D50,Product!$A$2:$I$101,3,FALSE) -> Sports | F50: STORE17 | G50: 1 | H50: 517.13 | I50: 0.28 | J50: Credit Card | K50: 372.3336 | L50: =IF(G50="", AVERAGEIF($E$2:$E$101, E51, $G$2:$G$101), G50) -> 1 | M50: =IF(H50="", IFERROR(AVERAGEIF($E$2:$E$101, E50, $H$2:$H$101), ""), H50) -> 517.13 | N50: =IF(I50="", AVERAGEIF($E$2:$E$101, E51, $I$2:$I$101), I50) -> 0.28 | O50: =IF(K50="", AVERAGEIF($E$2:$E$101, E51, $K$2:$K$101), K50) -> 372.3336
A51: SALE49 | B51: 45607 | C51: CUST1420 | D51: PROD21 | E51: =VLOOKUP(D51,Product!$A$2:$I$101,3,FALSE) -> Home | F51: STORE16 | G51: 2 | H51: 384.66 | I51: 0.08 | J51: COD | K51: 707.7744 | L51: =IF(G51="", AVERAGEIF($E$2:$E$101, E52, $G$2:$G$101), G51) -> 2 | M51: =IF(H51="", IFERROR(AVERAGEIF($E$2:$E$101, E51, $H$2:$H$101), ""), H51) -> 384.66 | N51: =IF(I51="", AVERAGEIF($E$2:$E$101, E52, $I$2:$I$101), I51) -> 0.08 | O51: =IF(K51="", AVERAGEIF($E$2:$E$101, E52, $K$2:$K$101), K51) -> 707.7744
A52: SALE50 | B52: 45291 | C52: CUST1070 | D52: PROD52 | E52: =VLOOKUP(D52,Product!$A$2:$I$101,3,FALSE) -> Sports | F52: STORE9 | G52: 3 | H52: 83.7 | I52: 0.24 | J52: PayPal | K52: 190.836 | L52: =IF(G52="", AVERAGEIF($E$2:$E$101, E53, $G$2:$G$101), G52) -> 3 | M52: =IF(H52="", IFERROR(AVERAGEIF($E$2:$E$101, E52, $H$2:$H$101), ""), H52) -> 83.7 | N52: =IF(I52="", AVERAGEIF($E$2:$E$101, E53, $I$2:$I$101), I52) -> 0.24 | O52: =IF(K52="", AVERAGEIF($E$2:$E$101, E53, $K$2:$K$101), K52) -> 190.836
A53: SALE51 | B53: 45689 | C53: CUST1142 | D53: PROD69 | E53: =VLOOKUP(D53,Product!$A$2:$I$101,3,FALSE) -> Clothing | F53: STORE7 | G53: 3 | H53: 76.57 | I53: 0.26 | J53: Credit Card | K53: 169.9854 | L53: =IF(G53="", AVERAGEIF($E$2:$E$101, E54, $G$2:$G$101), G53) -> 3 | M53: =IF(H53="", IFERROR(AVERAGEIF($E$2:$E$101, E53, $H$2:$H$101), ""), H53) -> 76.57 | N53: =IF(I53="", AVERAGEIF($E$2:$E$101, E54, $I$2:$I$101), I53) -> 0.26 | O53: =IF(K53="", AVERAGEIF($E$2:$E$101, E54, $K$2:$K$101), K53) -> 169.9854
A54: SALE52 | B54: 45894 | C54: CUST1148 | D54: PROD89 | E54: =VLOOKUP(D54,Product!$A$2:$I$101,3,FALSE) -> Beauty | F54: STORE6 | G54: 3 | J54: Credit Card | K54: 486.0633 | L54: =IF(G54="", AVERAGEIF($E$2:$E$101, E55, $G$2:$G$101), G54) -> 3 | M54: =IF(H54="", AVERAGEIF($E$2:$E$101, E55, $H$2:$H$101), H54) -> 443.50037 | N54: =IF(I54="", AVERAGEIF($E$2:$E$101, E55, $I$2:$I$101), I54) -> 0.14703704 | O54: =IF(K54="", AVERAGEIF($E$2:$E$101, E55, $K$2:$K$101), K54) -> 486.0633
A55: SALE53 | B55: 45677 | C55: CUST1324 | D55: PROD20 | E55: =VLOOKUP(D55,Product!$A$2:$I$101,3,FALSE) -> Sports | F55: STORE8 | G55: 1 | H55: 900.35 | I55: 0.13 | J55: COD | K55: 783.3045 | L55: =IF(G55="", AVERAGEIF($E$2:$E$101, E56, $G$2:$G$101), G55) -> 1 | M55: =IF(H55="", IFERROR(AVERAGEIF($E$2:$E$101, E55, $H$2:$H$101), ""), H55) -> 900.35 | N55: =IF(I55="", AVERAGEIF($E$2:$E$101, E56, $I$2:$I$101), I55) -> 0.13 | O55: =IF(K55="", AVERAGEIF($E$2:$E$101, E56, $K$2:$K$101), K55) -> 783.3045
A56: SALE54 | B56: 45706 | C56: CUST1095 | D56: PROD40 | E56: =VLOOKUP(D56,Product!$A$2:$I$101,3,FALSE) -> Electronics | F56: STORE10 | G56: 4 | H56: 428.09 | I56: 0.07 | J56: Credit Card | K56: 1592.4948 | L56: =IF(G56="", AVERAGEIF($E$2:$E$101, E57, $G$2:$G$101), G56) -> 4 | M56: =IF(H56="", IFERROR(AVERAGEIF($E$2:$E$101, E56, $H$2:$H$101), ""), H56) -> 428.09 | N56: =IF(I56="", AVERAGEIF($E$2:$E$101, E57, $I$2:$I$101), I56) -> 0.07 | O56: =IF(K56="", AVERAGEIF($E$2:$E$101, E57, $K$2:$K$101), K56) -> 1592.4948
A57: SALE55 | B57: 45589 | C57: CUST1416 | D57: PROD49 | E57: =VLOOKUP(D57,Product!$A$2:$I$101,3,FALSE) -> Beauty | F57: STORE11 | G57: 2 | H57: 559.71 | I57: 0.3 | J57: COD | K57: 783.594 | L57: =IF(G57="", AVERAGEIF($E$2:$E$101, E58, $G$2:$G$101), G57) -> 2 | M57: =IF(H57="", IFERROR(AVERAGEIF($E$2:$E$101, E57, $H$2:$H$101), ""), H57) -> 559.71 | N57: =IF(I57="", AVERAGEIF($E$2:$E$101, E58, $I$2:$I$101), I57) -> 0.3 | O57: =IF(K57="", AVERAGEIF($E$2:$E$101, E58, $K$2:$K$101), K57) -> 783.594
A58: SALE56 | B58: 45282 | C58: CUST1080 | D58: PROD34 | E58: =VLOOKUP(D58,Product!$A$2:$I$101,3,FALSE) -> Electronics | F58: STORE6 | G58: 2 | H58: 833.7 | I58: 0.06 | J58: PayPal | K58: 1567.356 | L58: =IF(G58="", AVERAGEIF($E$2:$E$101, E59, $G$2:$G$101), G58) -> 2 | M58: =IF(H58="", IFERROR(AVERAGEIF($E$2:$E$101, E58, $H$2:$H$101), ""), H58) -> 833.7 | N58: =IF(I58="", AVERAGEIF($E$2:$E$101, E59, $I$2:$I$101), I58) -> 0.06 | O58: =IF(K58="", AVERAGEIF($E$2:$E$101, E59, $K$2:$K$101), K58) -> 1567.356
A59: SALE57 | B59: 45462 | C59: CUST1467 | D59: PROD47 | E59: =VLOOKUP(D59,Product!$A$2:$I$101,3,FALSE) -> Beauty | F59: STORE14 | G59: 2 | H59: 680.16 | I59: 0.28 | J59: Credit Card | K59: 979.4304 | L59: =IF(G59="", AVERAGEIF($E$2:$E$101, E60, $G$2:$G$101), G59) -> 2 | M59: =IF(H59="", IFERROR(AVERAGEIF($E$2:$E$101, E59, $H$2:$H$101), ""), H59) -> 680.16 | N59: =IF(I59="", AVERAGEIF($E$2:$E$101, E60, $I$2:$I$101), I59) -> 0.28 | O59: =IF(K59="", AVERAGEIF($E$2:$E$101, E60, $K$2:$K$101), K59) -> 979.4304
A60: SALE58 | B60: 45633 | C60: CUST1404 | D60: PROD15 | E60: =VLOOKUP(D60,Product!$A$2:$I$101,3,FALSE) -> Electronics | F60: STORE7 | G60: 4 | H60: 733.42 | J60: PayPal | K60: 2552.3016 | L60: =IF(G60="", AVERAGEIF($E$2:$E$101, E61, $G$2:$G$101), G60) -> 4 | M60: =IF(H60="", IFERROR(AVERAGEIF($E$2:$E$101, E60, $H$2:$H$101), ""), H60) -> 733.42 | N60: =IF(I60="", AVERAGEIF($E$2:$E$101, E61, $I$2:$I$101), I60) -> 0.17529412 | O60: =IF(K60="", AVERAGEIF($E$2:$E$101, E61, $K$2:$K$101), K60) -> 2552.3016
A61: SALE59 | B61: 45257 | C61: CUST1367 | D61: PROD89 | E61: =VLOOKUP(D61,Product!$A$2:$I$101,3,FALSE) -> Beauty | F61: STORE11 | G61: 1 | H61: 996.33 | I61: 0.23 | J61: PayPal | K61: 767.1741 | L61: =IF(G61="", AVERAGEIF($E$2:$E$101, E62, $G$2:$G$101), G61) -> 1 | M61: =IF(H61="", IFERROR(AVERAGEIF($E$2:$E$101, E61, $H$2:$H$101), ""), H61) -> 996.33 | N61: =IF(I61="", AVERAGEIF($E$2:$E$101, E62, $I$2:$I$101), I61) -> 0.23 | O61: =IF(K61="", AVERAGEIF($E$2:$E$101, E62, $K$2:$K$101), K61) -> 767.1741
A62: SALE60 | B62: 45854 | C62: CUST1408 | D62: PROD31 | E62: =VLOOKUP(D62,Product!$A$2:$I$101,3,FALSE) -> Sports | F62: STORE10 | G62: 1 | H62: 198.83 | I62: 0.09 | J62: COD | K62: 180.9353 | L62: =IF(G62="", AVERAGEIF($E$2:$E$101, E63, $G$2:$G$101), G62) -> 1 | M62: =IF(H62="", IFERROR(AVERAGEIF($E$2:$E$101, E62, $H$2:$H$101), ""), H62) -> 198.83 | N62: =IF(I62="", AVERAGEIF($E$2:$E$101, E63, $I$2:$I$101), I62) -> 0.09 | O62: =IF(K62="", AVERAGEIF($E$2:$E$101, E63, $K$2:$K$101), K62) -> 180.9353
A63: SALE61 | B63: 45716 | C63: CUST1239 | D63: PROD19 | E63: =VLOOKUP(D63,Product!$A$2:$I$101,3,FALSE) -> Sports | F63: STORE7 | G63: 1 | H63: 374.92 | I63: 0.18 | J63: PayPal | K63: 307.4344 | L63: =IF(G63="", AVERAGEIF($E$2:$E$101, E64, $G$2:$G$101), G63) -> 1 | M63: =IF(H63="", IFERROR(AVERAGEIF($E$2:$E$101, E63, $H$2:$H$101), ""), H63) -> 374.92 | N63: =IF(I63="", AVERAGEIF($E$2:$E$101, E64, $I$2:$I$101), I63) -> 0.18 | O63: =IF(K63="", AVERAGEIF($E$2:$E$101, E64, $K$2:$K$101), K63) -> 307.4344
A64: SALE62 | B64: 45515 | C64: CUST1464 | D64: PROD93 | E64: =VLOOKUP(D64,Product!$A$2:$I$101,3,FALSE) -> Electronics | F64: STORE16 | G64: 1 | H64: 468.94 | I64: 0.12 | J64: Credit Card | K64: 412.6672 | L64: =IF(G64="", AVERAGEIF($E$2:$E$101, E65, $G$2:$G$101), G64) -> 1 | M64: =IF(H64="", IFERROR(AVERAGEIF($E$2:$E$101, E64, $H$2:$H$101), ""), H64) -> 468.94 | N64: =IF(I64="", AVERAGEIF($E$2:$E$101, E65, $I$2:$I$101), I64) -> 0.12 | O64: =IF(K64="", AVERAGEIF($E$2:$E$101, E65, $K$2:$K$101), K64) -> 412.6672
A65: SALE63 | B65: 45927 | C65: CUST1126 | D65: PROD89 | E65: =VLOOKUP(D65,Product!$A$2:$I$101,3,FALSE) -> Beauty | F65: STORE12 | G65: 2 | H65: 121.37 | I65: 0.05 | J65: Credit Card | K65: 230.603 | L65: =IF(G65="", AVERAGEIF($E$2:$E$101, E66, $G$2:$G$101), G65) -> 2 | M65: =IF(H65="", IFERROR(AVERAGEIF($E$2:$E$101, E65, $H$2:$H$101), ""), H65) -> 121.37 | N65: =IF(I65="", AVERAGEIF($E$2:$E$101, E66, $I$2:$I$101), I65) -> 0.05 | O65: =IF(K65="", AVERAGEIF($E$2:$E$101, E66, $K$2:$K$101), K65) -> 230.603
A66: SALE64 | B66: 45914 | C66: CUST1255 | D66: PROD53 | E66: =VLOOKUP(D66,Product!$A$2:$I$101,3,FALSE) -> Clothing | F66: STORE10 | G66: 3 | H66: 480.06 | I66: 0.01 | J66: Credit Card | L66: =IF(G66="", AVERAGEIF($E$2:$E$101, E67, $G$2:$G$101), G66) -> 3 | M66: =IF(H66="", IFERROR(AVERAGEIF($E$2:$E$101, E66, $H$2:$H$101), ""), H66) -> 480.06 | N66: =IF(I66="", AVERAGEIF($E$2:$E$101, E67, $I$2:$I$101), I66) -> 0.01 | O66: =IF(K66="", AVERAGEIF($E$2:$E$101, E67, $K$2:$K$101), K66) -> 1078.9595
A67: SALE65 | B67: 45290 | C67: CUST1162 | D67: PROD99 | E67: =VLOOKUP(D67,Product!$A$2:$I$101,3,FALSE) -> Home | F67: STORE17 | G67: 2 | H67: 856.57 | I67: 0.24 | J67: Credit Card | K67: 1301.9864 | L67: =IF(G67="", AVERAGEIF($E$2:$E$101, E68, $G$2:$G$101), G67) -> 2 | M67: =IF(H67="", IFERROR(AVERAGEIF($E$2:$E$101, E67, $H$2:$H$101), ""), H67) -> 856.57 | N67: =IF(I67="", AVERAGEIF($E$2:$E$101, E68, $I$2:$I$101), I67) -> 0.24 | O67: =IF(K67="", AVERAGEIF($E$2:$E$101, E68, $K$2:$K$101), K67) -> 1301.9864
A68: SALE66 | B68: 45213 | C68: CUST1269 | D68: PROD77 | E68: =VLOOKUP(D68,Product!$A$2:$I$101,3,FALSE) -> Electronics | F68: STORE2 | G68: 4 | H68: 814.25 | I68: 0.18 | J68: Credit Card | K68: 2670.74 | L68: =IF(G68="", AVERAGEIF($E$2:$E$101, E69, $G$2:$G$101), G68) -> 4 | M68: =IF(H68="", IFERROR(AVERAGEIF($E$2:$E$101, E68, $H$2:$H$101), ""), H68) -> 814.25 | N68: =IF(I68="", AVERAGEIF($E$2:$E$101, E69, $I$2:$I$101), I68) -> 0.18 | O68: =IF(K68="", AVERAGEIF($E$2:$E$101, E69, $K$2:$K$101), K68) -> 2670.74
A69: SALE67 | B69: 45255 | C69: CUST1483 | D69: PROD12 | E69: =VLOOKUP(D69,Product!$A$2:$I$101,3,FALSE) -> Beauty | F69: STORE2 | G69: 1 | H69: 989.17 | I69: 0.2 | J69: PayPal | K69: 791.336 | L69: =IF(G69="", AVERAGEIF($E$2:$E$101, E70, $G$2:$G$101), G69) -> 1 | M69: =IF(H69="", IFERROR(AVERAGEIF($E$2:$E$101, E69, $H$2:$H$101), ""), H69) -> 989.17 | N69: =IF(I69="", AVERAGEIF($E$2:$E$101, E70, $I$2:$I$101), I69) -> 0.2 | O69: =IF(K69="", AVERAGEIF($E$2:$E$101, E70, $K$2:$K$101), K69) -> 791.336
A70: SALE68 | B70: 45270 | C70: CUST1372 | D70: PROD72 | E70: =VLOOKUP(D70,Product!$A$2:$I$101,3,FALSE) -> Sports | F70: STORE10 | G70: 4 | H70: 62.48 | I70: 0.18 | J70: Credit Card | K70: 204.9344 | L70: =IF(G70="", AVERAGEIF($E$2:$E$101, E71, $G$2:$G$101), G70) -> 4 | M70: =IF(H70="", IFERROR(AVERAGEIF($E$2:$E$101, E70, $H$2:$H$101), ""), H70) -> 62.48 | N70: =IF(I70="", AVERAGEIF($E$2:$E$101, E71, $I$2:$I$101), I70) -> 0.18 | O70: =IF(K70="", AVERAGEIF($E$2:$E$101, E71, $K$2:$K$101), K70) -> 204.9344
A71: SALE69 | B71: 45897 | C71: CUST1423 | D71: PROD13 | E71: =VLOOKUP(D71,Product!$A$2:$I$101,3,FALSE) -> Electronics | F71: STORE16 | G71: 4 | H71: 561.24 | I71: 0.24 | J71: Credit Card | K71: 1706.1696 | L71: =IF(G71="", AVERAGEIF($E$2:$E$101, E72, $G$2:$G$101), G71) -> 4 | M71: =IF(H71="", IFERROR(AVERAGEIF($E$2:$E$101, E71, $H$2:$H$101), ""), H71) -> 561.24 | N71: =IF(I71="", AVERAGEIF($E$2:$E$101, E72, $I$2:$I$101), I71) -> 0.24 | O71: =IF(K71="", AVERAGEIF($E$2:$E$101, E72, $K$2:$K$101), K71) -> 1706.1696
A72: SALE70 | B72: 45849 | C72: CUST1058 | D72: PROD60 | E72: =VLOOKUP(D72,Product!$A$2:$I$101,3,FALSE) -> Beauty | F72: STORE5 | G72: 3 | H72: 92.24 | I72: 0.28 | J72: COD | L72: =IF(G72="", AVERAGEIF($E$2:$E$101, E73, $G$2:$G$101), G72) -> 3 | M72: =IF(H72="", IFERROR(AVERAGEIF($E$2:$E$101, E72, $H$2:$H$101), ""), H72) -> 92.24 | N72: =IF(I72="", AVERAGEIF($E$2:$E$101, E73, $I$2:$I$101), I72) -> 0.28 | O72: =IF(K72="", AVERAGEIF($E$2:$E$101, E73, $K$2:$K$101), K72) -> 792.89603
A73: SALE71 | B73: 45889 | C73: CUST1168 | D73: PROD72 | E73: =VLOOKUP(D73,Product!$A$2:$I$101,3,FALSE) -> Sports | F73: STORE1 | G73: 2 | H73: 668.3 | I73: 0.07 | J73: Credit Card | K73: 1243.038 | L73: =IF(G73="", AVERAGEIF($E$2:$E$101, E74, $G$2:$G$101), G73) -> 2 | M73: =IF(H73="", IFERROR(AVERAGEIF($E$2:$E$101, E73, $H$2:$H$101), ""), H73) -> 668.3 | N73: =IF(I73="", AVERAGEIF($E$2:$E$101, E74, $I$2:$I$101), I73) -> 0.07 | O73: =IF(K73="", AVERAGEIF($E$2:$E$101, E74, $K$2:$K$101), K73) -> 1243.038
A74: SALE72 | B74: 45533 | C74: CUST1409 | D74: PROD38 | E74: =VLOOKUP(D74,Product!$A$2:$I$101,3,FALSE) -> Sports | F74: STORE5 | G74: 1 | H74: 553.82 | I74: 0.09 | J74: Credit Card | K74: 503.9762 | L74: =IF(G74="", AVERAGEIF($E$2:$E$101, E75, $G$2:$G$101), G74) -> 1 | M74: =IF(H74="", IFERROR(AVERAGEIF($E$2:$E$101, E74, $H$2:$H$101), ""), H74) -> 553.82 | N74: =IF(I74="", AVERAGEIF($E$2:$E$101, E75, $I$2:$I$101), I74) -> 0.09 | O74: =IF(K74="", AVERAGEIF($E$2:$E$101, E75, $K$2:$K$101), K74) -> 503.9762
A75: SALE73 | B75: 45626 | C75: CUST1037 | D75: PROD45 | E75: =VLOOKUP(D75,Product!$A$2:$I$101,3,FALSE) -> Sports | F75: STORE11 | G75: 2 | H75: 556.43 | I75: 0.13 | J75: Credit Card | K75: 968.1882 | L75: =IF(G75="", AVERAGEIF($E$2:$E$101, E76, $G$2:$G$101), G75) -> 2 | M75: =IF(H75="", IFERROR(AVERAGEIF($E$2:$E$101, E75, $H$2:$H$101), ""), H75) -> 556.43 | N75: =IF(I75="", AVERAGEIF($E$2:$E$101, E76, $I$2:$I$101), I75) -> 0.13 | O75: =IF(K75="", AVERAGEIF($E$2:$E$101, E76, $K$2:$K$101), K75) -> 968.1882
A76: SALE74 | B76: 45942 | C76: CUST1273 | D76: PROD20 | E76: =VLOOKUP(D76,Product!$A$2:$I$101,3,FALSE) -> Sports | F76: STORE8 | G76: 1 | H76: 184.98 | I76: 0.1 | J76: COD | K76: 166.482 | L76: =IF(G76="", AVERAGEIF($E$2:$E$101, E77, $G$2:$G$101), G76) -> 1 | M76: =IF(H76="", IFERROR(AVERAGEIF($E$2:$E$101, E76, $H$2:$H$101), ""), H76) -> 184.98 | N76: =IF(I76="", AVERAGEIF($E$2:$E$101, E77, $I$2:$I$101), I76) -> 0.1 | O76: =IF(K76="", AVERAGEIF($E$2:$E$101, E77, $K$2:$K$101), K76) -> 166.482
A77: SALE75 | B77: 45500 | C77: CUST1035 | D77: PROD97 | E77: =VLOOKUP(D77,Product!$A$2:$I$101,3,FALSE) -> Sports | F77: STORE12 | G77: 4 | H77: 700.18 | I77: 0.23 | J77: Credit Card | K77: 2156.5544 | L77: =IF(G77="", AVERAGEIF($E$2:$E$101, E78, $G$2:$G$101), G77) -> 4 | M77: =IF(H77="", IFERROR(AVERAGEIF($E$2:$E$101, E77, $H$2:$H$101), ""), H77) -> 700.18 | N77: =IF(I77="", AVERAGEIF($E$2:$E$101, E78, $I$2:$I$101), I77) -> 0.23 | O77: =IF(K77="", AVERAGEIF($E$2:$E$101, E78, $K$2:$K$101), K77) -> 2156.5544
A78: SALE76 | B78: 45285 | C78: CUST1019 | D78: PROD76 | E78: =VLOOKUP(D78,Product!$A$2:$I$101,3,FALSE) -> Electronics | F78: STORE10 | G78: 2 | H78: 686.31 | I78: 0.25 | J78: Credit Card | K78: 1029.465 | L78: =IF(G78="", AVERAGEIF($E$2:$E$101, E79, $G$2:$G$101), G78) -> 2 | M78: =IF(H78="", IFERROR(AVERAGEIF($E$2:$E$101, E78, $H$2:$H$101), ""), H78) -> 686.31 | N78: =IF(I78="", AVERAGEIF($E$2:$E$101, E79, $I$2:$I$101), I78) -> 0.25 | O78: =IF(K78="", AVERAGEIF($E$2:$E$101, E79, $K$2:$K$101), K78) -> 1029.465
A79: SALE77 | B79: 45800 | C79: CUST1007 | D79: PROD67 | E79: =VLOOKUP(D79,Product!$A$2:$I$101,3,FALSE) -> Electronics | F79: STORE15 | G79: 1 | H79: 687.82 | I79: 0.27 | J79: COD | K79: 502.1086 | L79: =IF(G79="", AVERAGEIF($E$2:$E$101, E80, $G$2:$G$101), G79) -> 1 | M79: =IF(H79="", IFERROR(AVERAGEIF($E$2:$E$101, E79, $H$2:$H$101), ""), H79) -> 687.82 | N79: =IF(I79="", AVERAGEIF($E$2:$E$101, E80, $I$2:$I$101), I79) -> 0.27 | O79: =IF(K79="", AVERAGEIF($E$2:$E$101, E80, $K$2:$K$101), K79) -> 502.1086
A80: SALE78 | B80: 45609 | C80: CUST1221 | D80: PROD83 | E80: =VLOOKUP(D80,Product!$A$2:$I$101,3,FALSE) -> Beauty | F80: STORE8 | G80: 2 | H80: 900.55 | I80: 0.16 | J80: Credit Card | K80: 1512.924 | L80: =IF(G80="", AVERAGEIF($E$2:$E$101, E81, $G$2:$G$101), G80) -> 2 | M80: =IF(H80="", IFERROR(AVERAGEIF($E$2:$E$101, E80, $H$2:$H$101), ""), H80) -> 900.55 | N80: =IF(I80="", AVERAGEIF($E$2:$E$101, E81, $I$2:$I$101), I80) -> 0.16 | O80: =IF(K80="", AVERAGEIF($E$2:$E$101, E81, $K$2:$K$101), K80) -> 1512.924
A81: SALE79 | B81: 45268 | C81: CUST1115 | D81: PROD21 | E81: =VLOOKUP(D81,Product!$A$2:$I$101,3,FALSE) -> Home | F81: STORE2 | G81: 1 | H81: 341.17 | I81: 0.15 | J81: Credit Card | K81: 289.9945 | L81: =IF(G81="", AVERAGEIF($E$2:$E$101, E82, $G$2:$G$101), G81) -> 1 | M81: =IF(H81="", IFERROR(AVERAGEIF($E$2:$E$101, E81, $H$2:$H$101), ""), H81) -> 341.17 | N81: =IF(I81="", AVERAGEIF($E$2:$E$101, E82, $I$2:$I$101), I81) -> 0.15 | O81: =IF(K81="", AVERAGEIF($E$2:$E$101, E82, $K$2:$K$101), K81) -> 289.9945
A82: SALE80 | B82: 45885 | C82: CUST1176 | D82: PROD52 | E82: =VLOOKUP(D82,Product!$A$2:$I$101,3,FALSE) -> Sports | F82: STORE8 | G82: 1 | H82: 442.27 | I82: 0.06 | J82: COD | K82: 415.7338 | L82: =IF(G82="", AVERAGEIF($E$2:$E$101, E83, $G$2:$G$101), G82) -> 1 | M82: =IF(H82="", IFERROR(AVERAGEIF($E$2:$E$101, E82, $H$2:$H$101), ""), H82) -> 442.27 | N82: =IF(I82="", AVERAGEIF($E$2:$E$101, E83, $I$2:$I$101), I82) -> 0.06 | O82: =IF(K82="", AVERAGEIF($E$2:$E$101, E83, $K$2:$K$101), K82) -> 415.7338
A83: SALE81 | B83: 45616 | C83: CUST1253 | D83: PROD71 | E83: =VLOOKUP(D83,Product!$A$2:$I$101,3,FALSE) -> Beauty | F83: STORE9 | G83: 1 | H83: 363.73 | I83: 0.25 | J83: PayPal | K83: 272.7975 | L83: =IF(G83="", AVERAGEIF($E$2:$E$101, E84, $G$2:$G$101), G83) -> 1 | M83: =IF(H83="", IFERROR(AVERAGEIF($E$2:$E$101, E83, $H$2:$H$101), ""), H83) -> 363.73 | N83: =IF(I83="", AVERAGEIF($E$2:$E$101, E84, $I$2:$I$101), I83) -> 0.25 | O83: =IF(K83="", AVERAGEIF($E$2:$E$101, E84, $K$2:$K$101), K83) -> 272.7975
A84: SALE82 | B84: 45518 | C84: CUST1378 | D84: PROD91 | E84: =VLOOKUP(D84,Product!$A$2:$I$101,3,FALSE) -> Clothing | F84: STORE17 | G84: 2 | H84: 601.33 | I84: 0.16 | J84: PayPal | K84: 1010.2344 | L84: =IF(G84="", AVERAGEIF($E$2:$E$101, E85, $G$2:$G$101), G84) -> 2 | M84: =IF(H84="", IFERROR(AVERAGEIF($E$2:$E$101, E84, $H$2:$H$101), ""), H84) -> 601.33 | N84: =IF(I84="", AVERAGEIF($E$2:$E$101, E85, $I$2:$I$101), I84) -> 0.16 | O84: =IF(K84="", AVERAGEIF($E$2:$E$101, E85, $K$2:$K$101), K84) -> 1010.2344
A85: SALE83 | B85: 45427 | C85: CUST1403 | D85: PROD17 | E85: =VLOOKUP(D85,Product!$A$2:$I$101,3,FALSE) -> Sports | F85: STORE18 | G85: 4 | H85: 34.39 | I85: 0.03 | J85: PayPal | K85: 133.4332 | L85: =IF(G85="", AVERAGEIF($E$2:$E$101, E86, $G$2:$G$101), G85) -> 4 | M85: =IF(H85="", IFERROR(AVERAGEIF($E$2:$E$101, E85, $H$2:$H$101), ""), H85) -> 34.39 | N85: =IF(I85="", AVERAGEIF($E$2:$E$101, E86, $I$2:$I$101), I85) -> 0.03 | O85: =IF(K85="", AVERAGEIF($E$2:$E$101, E86, $K$2:$K$101), K85) -> 133.4332
A86: SALE84 | B86: 45268 | C86: CUST1423 | D86: PROD46 | E86: =VLOOKUP(D86,Product!$A$2:$I$101,3,FALSE) -> Clothing | F86: STORE17 | G86: 1 | H86: 773.57 | I86: 0.05 | J86: COD | L86: =IF(G86="", AVERAGEIF($E$2:$E$101, E87, $G$2:$G$101), G86) -> 1 | M86: =IF(H86="", IFERROR(AVERAGEIF($E$2:$E$101, E86, $H$2:$H$101), ""), H86) -> 773.57 | N86: =IF(I86="", AVERAGEIF($E$2:$E$101, E87, $I$2:$I$101), I86) -> 0.05 | O86: =IF(K86="", AVERAGEIF($E$2:$E$101, E87, $K$2:$K$101), K86) -> 792.89603
A87: SALE85 | B87: 45282 | C87: CUST1054 | D87: PROD88 | E87: =VLOOKUP(D87,Product!$A$2:$I$101,3,FALSE) -> Sports | F87: STORE7 | G87: 4 | H87: 127.1 | I87: 0.24 | J87: COD | K87: 386.384 | L87: =IF(G87="", AVERAGEIF($E$2:$E$101, E88, $G$2:$G$101), G87) -> 4 | M87: =IF(H87="", IFERROR(AVERAGEIF($E$2:$E$101, E87, $H$2:$H$101), ""), H87) -> 127.1 | N87: =IF(I87="", AVERAGEIF($E$2:$E$101, E88, $I$2:$I$101), I87) -> 0.24 | O87: =IF(K87="", AVERAGEIF($E$2:$E$101, E88, $K$2:$K$101), K87) -> 386.384
A88: SALE86 | B88: 45545 | C88: CUST1303 | D88: PROD20 | E88: =VLOOKUP(D88,Product!$A$2:$I$101,3,FALSE) -> Sports | F88: STORE3 | G88: 3 | H88: 899.58 | I88: 0.28 | J88: PayPal | K88: 1943.0928 | L88: =IF(G88="", AVERAGEIF($E$2:$E$101, E89, $G$2:$G$101), G88) -> 3 | M88: =IF(H88="", IFERROR(AVERAGEIF($E$2:$E$101, E88, $H$2:$H$101), ""), H88) -> 899.58 | N88: =IF(I88="", AVERAGEIF($E$2:$E$101, E89, $I$2:$I$101), I88) -> 0.28 | O88: =IF(K88="", AVERAGEIF($E$2:$E$101, E89, $K$2:$K$101), K88) -> 1943.0928
A89: SALE87 | B89: 45755 | C89: CUST1327 | D89: PROD1 | E89: =VLOOKUP(D89,Product!$A$2:$I$101,3,FALSE) -> Clothing | F89: STORE10 | G89: 3 | H89: 964.39 | I89: 0.04 | J89: Credit Card | K89: 2777.4432 | L89: =IF(G89="", AVERAGEIF($E$2:$E$101, E90, $G$2:$G$101), G89) -> 3 | M89: =IF(H89="", IFERROR(AVERAGEIF($E$2:$E$101, E89, $H$2:$H$101), ""), H89) -> 964.39 | N89: =IF(I89="", AVERAGEIF($E$2:$E$101, E90, $I$2:$I$101), I89) -> 0.04 | O89: =IF(K89="", AVERAGEIF($E$2:$E$101, E90, $K$2:$K$101), K89) -> 2777.4432
A90: SALE88 | B90: 45588 | C90: CUST1183 | D90: PROD38 | E90: =VLOOKUP(D90,Product!$A$2:$I$101,3,FALSE) -> Sports | F90: STORE0 | G90: 2 | H90: 217.83 | I90: 0.14 | J90: PayPal | K90: 374.6676 | L90: =IF(G90="", AVERAGEIF($E$2:$E$101, E91, $G$2:$G$101), G90) -> 2 | M90: =IF(H90="", IFERROR(AVERAGEIF($E$2:$E$101, E90, $H$2:$H$101), ""), H90) -> 217.83 | N90: =IF(I90="", AVERAGEIF($E$2:$E$101, E91, $I$2:$I$101), I90) -> 0.14 | O90: =IF(K90="", AVERAGEIF($E$2:$E$101, E91, $K$2:$K$101), K90) -> 374.6676
A91: SALE89 | B91: 45848 | C91: CUST1143 | D91: PROD17 | E91: =VLOOKUP(D91,Product!$A$2:$I$101,3,FALSE) -> Sports | F91: STORE1 | G91: 4 | H91: 187.71 | I91: 0.06 | J91: COD | K91: 705.7896 | L91: =IF(G91="", AVERAGEIF($E$2:$E$101, E92, $G$2:$G$101), G91) -> 4 | M91: =IF(H91="", IFERROR(AVERAGEIF($E$2:$E$101, E91, $H$2:$H$101), ""), H91) -> 187.71 | N91: =IF(I91="", AVERAGEIF($E$2:$E$101, E92, $I$2:$I$101), I91) -> 0.06 | O91: =IF(K91="", AVERAGEIF($E$2:$E$101, E92, $K$2:$K$101), K91) -> 705.7896
A92: SALE90 | B92: 45577 | C92: CUST1010 | D92: PROD33 | E92: =VLOOKUP(D92,Product!$A$2:$I$101,3,FALSE) -> Home | F92: STORE18 | G92: 2 | H92: 350.12 | I92: 0.12 | J92: COD | K92: 616.2112 | L92: =IF(G92="", AVERAGEIF($E$2:$E$101, E93, $G$2:$G$101), G92) -> 2 | M92: =IF(H92="", IFERROR(AVERAGEIF($E$2:$E$101, E92, $H$2:$H$101), ""), H92) -> 350.12 | N92: =IF(I92="", AVERAGEIF($E$2:$E$101, E93, $I$2:$I$101), I92) -> 0.12 | O92: =IF(K92="", AVERAGEIF($E$2:$E$101, E93, $K$2:$K$101), K92) -> 616.2112
A93: SALE91 | B93: 45312 | C93: CUST1406 | D93: PROD16 | E93: =VLOOKUP(D93,Product!$A$2:$I$101,3,FALSE) -> Beauty | F93: STORE1 | G93: 4 | H93: 102.19 | I93: 0.17 | J93: PayPal | K93: 339.2708 | L93: =IF(G93="", AVERAGEIF($E$2:$E$101, E94, $G$2:$G$101), G93) -> 4 | M93: =IF(H93="", IFERROR(AVERAGEIF($E$2:$E$101, E93, $H$2:$H$101), ""), H93) -> 102.19 | N93: =IF(I93="", AVERAGEIF($E$2:$E$101, E94, $I$2:$I$101), I93) -> 0.17 | O93: =IF(K93="", AVERAGEIF($E$2:$E$101, E94, $K$2:$K$101), K93) -> 339.2708
A94: SALE92 | B94: 45350 | C94: CUST1007 | D94: PROD86 | E94: =VLOOKUP(D94,Product!$A$2:$I$101,3,FALSE) -> Home | F94: STORE4 | G94: 1 | H94: 696.53 | I94: 0.17 | J94: Credit Card | K94: 578.1199 | L94: =IF(G94="", AVERAGEIF($E$2:$E$101, E95, $G$2:$G$101), G94) -> 1 | M94: =IF(H94="", IFERROR(AVERAGEIF($E$2:$E$101, E94, $H$2:$H$101), ""), H94) -> 696.53 | N94: =IF(I94="", AVERAGEIF($E$2:$E$101, E95, $I$2:$I$101), I94) -> 0.17 | O94: =IF(K94="", AVERAGEIF($E$2:$E$101, E95, $K$2:$K$101), K94) -> 578.1199
A95: SALE93 | B95: 45657 | C95: CUST1065 | D95: PROD19 | E95: =VLOOKUP(D95,Product!$A$2:$I$101,3,FALSE) -> Sports | F95: STORE4 | G95: 2 | H95: 327.52 | I95: 0.15 | J95: PayPal | K95: 556.784 | L95: =IF(G95="", AVERAGEIF($E$2:$E$101, E96, $G$2:$G$101), G95) -> 2 | M95: =IF(H95="", IFERROR(AVERAGEIF($E$2:$E$101, E95, $H$2:$H$101), ""), H95) -> 327.52 | N95: =IF(I95="", AVERAGEIF($E$2:$E$101, E96, $I$2:$I$101), I95) -> 0.15 | O95: =IF(K95="", AVERAGEIF($E$2:$E$101, E96, $K$2:$K$101), K95) -> 556.784
A96: SALE94 | B96: 45530 | C96: CUST1298 | D96: PROD97 | E96: =VLOOKUP(D96,Product!$A$2:$I$101,3,FALSE) -> Sports | F96: STORE19 | G96: 2 | H96: 569.36 | I96: 0.01 | J96: PayPal | L96: =IF(G96="", AVERAGEIF($E$2:$E$101, E97, $G$2:$G$101), G96) -> 2 | M96: =IF(H96="", IFERROR(AVERAGEIF($E$2:$E$101, E96, $H$2:$H$101), ""), H96) -> 569.36 | N96: =IF(I96="", AVERAGEIF($E$2:$E$101, E97, $I$2:$I$101), I96) -> 0.01 | O96: =IF(K96="", AVERAGEIF($E$2:$E$101, E97, $K$2:$K$101), K96) -> 1078.9595
A97: SALE95 | B97: 45556 | C97: CUST1321 | D97: PROD99 | E97: =VLOOKUP(D97,Product!$A$2:$I$101,3,FALSE) -> Home | F97: STORE6 | G97: 2 | H97: 68.29 | I97: 0.14 | J97: COD | K97: 117.4588 | L97: =IF(G97="", AVERAGEIF($E$2:$E$101, E98, $G$2:$G$101), G97) -> 2 | M97: =IF(H97="", IFERROR(AVERAGEIF($E$2:$E$101, E97, $H$2:$H$101), ""), H97) -> 68.29 | N97: =IF(I97="", AVERAGEIF($E$2:$E$101, E98, $I$2:$I$101), I97) -> 0.14 | O97: =IF(K97="", AVERAGEIF($E$2:$E$101, E98, $K$2:$K$101), K97) -> 117.4588
A98: SALE96 | B98: 45523 | C98: CUST1244 | D98: PROD50 | E98: =VLOOKUP(D98,Product!$A$2:$I$101,3,FALSE) -> Sports | F98: STORE10 | G98: 1 | H98: 842.9 | I98: 0.06 | J98: COD | K98: 792.326 | L98: =IF(G98="", AVERAGEIF($E$2:$E$101, E99, $G$2:$G$101), G98) -> 1 | M98: =IF(H98="", IFERROR(AVERAGEIF($E$2:$E$101, E98, $H$2:$H$101), ""), H98) -> 842.9 | N98: =IF(I98="", AVERAGEIF($E$2:$E$101, E99, $I$2:$I$101), I98) -> 0.06 | O98: =IF(K98="", AVERAGEIF($E$2:$E$101, E99, $K$2:$K$101), K98) -> 792.326
A99: SALE97 | B99: 45587 | C99: CUST1287 | D99: PROD3 | E99: =VLOOKUP(D99,Product!$A$2:$I$101,3,FALSE) -> Clothing | F99: STORE3 | G99: 3 | H99: 751.94 | I99: 0.26 | J99: PayPal | K99: 1669.3068 | L99: =IF(G99="", AVERAGEIF($E$2:$E$101, E100, $G$2:$G$101), G99) -> 3 | M99: =IF(H99="", IFERROR(AVERAGEIF($E$2:$E$101, E99, $H$2:$H$101), ""), H99) -> 751.94 | N99: =IF(I99="", AVERAGEIF($E$2:$E$101, E100, $I$2:$I$101), I99) -> 0.26 | O99: =IF(K99="", AVERAGEIF($E$2:$E$101, E100, $K$2:$K$101), K99) -> 1669.3068
A100: SALE98 | B100: 45580 | C100: CUST1131 | D100: PROD56 | E100: =VLOOKUP(D100,Product!$A$2:$I$101,3,FALSE) -> Home | F100: STORE7 | G100: 4 | H100: 476.28 | I100: 0.17 | J100: Credit Card | K100: 1581.2496 | L100: =IF(G100="", AVERAGEIF($E$2:$E$101, E101, $G$2:$G$101), G100) -> 4 | M100: =IF(H100="", IFERROR(AVERAGEIF($E$2:$E$101, E100, $H$2:$H$101), ""), H100) -> 476.28 | N100: =IF(I100="", AVERAGEIF($E$2:$E$101, E101, $I$2:$I$101), I100) -> 0.17 | O100: =IF(K100="", AVERAGEIF($E$2:$E$101, E101, $K$2:$K$101), K100) -> 1581.2496
...

Sheet Summary Statistics
A1: Total Sales | D1: Cost | G1: Stock
A3: Mean | B3: 1087.7408 | D3: Mean | E3: 256.44308 | G3: Mean | H3: 273.42239
A4: Standard Error | B4: 18.359318 | D4: Standard Error | E4: 2.9573834 | G4: Standard Error | H4: 2.8696345
A5: Median | B5: 868.4564 | D5: Median | E5: 250.41615 | G5: Median | H5: 276
A6: Mode | B6: 1078.9595 | D6: Mode | E6: 265.73267 | G6: Mode | H6: 301
A7: Standard Deviation | B7: 819.61557 | D7: Standard Deviation | E7: 132.22514 | G7: Standard Deviation | H7: 128.30187
A8: Sample Variance | B8: 671769.68 | D8: Sample Variance | E8: 17483.487 | G8: Sample Variance | H8: 16461.37
A9: Kurtosis | B9: 0.048453215 | D9: Kurtosis | E9: -1.0231998 | G9: Kurtosis | H9: -1.1349752
A10: Skewness | B10: 0.88049627 | D10: Skewness | E10: 0.017982216 | G10: Skewness | H10: -0.0128037
A11: Range | B11: 3889.7838 | D11: Range | E11: 478.41 | G11: Range | H11: 439
A12: Minimum | B12: 18.459 | D12: Minimum | E12: 17.31 | G12: Minimum | H12: 57
A13: Maximum | B13: 3908.2428 | D13: Maximum | E13: 495.72 | G13: Maximum | H13: 496
A14: Sum | B14: 2167867.5 | D14: Sum | E14: 512629.72 | G14: Sum | H14: 546571.37
A15: Count | B15: 1993 | D15: Count | E15: 1999 | G15: Count | H15: 1999
A18: Summary
A19: 1) I find summary statistics using analysis toolpak

Sheet Cleaned Table
A1: Customer_ID | B1: Name | C1: Age | D1: Gender | E1: City | F1: State | G1: Country | H1: Loyalty_Level | I1: Product_ID | J1: Product_Name | K1: Category | L1: Sub_Category | M1: Brand | N1: Cost | O1: Stock | P1: Store_ID | Q1: Store_Name | R1: Region | S1: City2 | T1: Store_Type | U1: Sales_ID | V1: Order_Date | W1: Quantity | X1: Unit_Price | Y1: Discount | Z1: Payment_Type | AA1: Total_Amount
A2: CUST1409 | B2: =PROPER(VLOOKUP(A2,Customer!$A$2:$J$501,9,FALSE)) -> Sarah Smith | C2: =PROPER(VLOOKUP(A2,Customer!$A$2:$H$501,3,FALSE)) -> 55 | D2: =PROPER(VLOOKUP(A2,Customer!$A$2:$H$501,4,FALSE)) -> Male | E2: =PROPER(VLOOKUP(A2,Customer!$A$2:$H$501,5,FALSE)) -> Kathleenport | F2: =PROPER(VLOOKUP(A2,Customer!$A$2:$H$501,6,FALSE)) -> Wyoming | G2: =VLOOKUP(A2,Customer!$A$2:$H$501,7,FALSE) -> USA | H2: =PROPER(VLOOKUP(A2,Customer!$A$1:$J$501,10,FALSE)) -> Gold | I2: PROD97 | J2: =VLOOKUP(I2,Product!$A$2:$G$101,2,FALSE) -> Cricket Bat | K2: =VLOOKUP(I2,Product!$A$2:$H$501,3,FALSE) -> Sports | L2: =VLOOKUP(I2, Product!$A$2:$H$501, 4,FALSE) -> Team Sports | M2: =VLOOKUP(I2, Product!$A$2:$H$501,5,FALSE) -> Khan LLC | N2: =VLOOKUP(I2, Product!$A$2:$I$501,8,FALSE) -> 245.98 | O2: =VLOOKUP(I2, Product!$A$2:$I$501,9,FALSE) -> 471 | P2: STORE3 | Q2: =VLOOKUP(P2,Store_Dim!$A$2:$E$21,2,FALSE) -> Johnson-Wright | R2: =VLOOKUP(P2,Store_Dim!$A$2:$E$21,3,FALSE) -> North | S2: =VLOOKUP(P2,Store_Dim!$A$2:$E$21,4,FALSE) -> Hoodberg | T2: =VLOOKUP(P2,Store_Dim!$A$2:$E$21,5,FALSE) -> Outlet | U2: SALE0 | V2: =VLOOKUP(Table1[[#This Row],[Sales_ID]],Sales!$A$2:$O$2001,2,FALSE) -> 45480 | W2: =VLOOKUP(Table1[[#This Row],[Sales_ID]],Sales!$A$2:$O$2001,12,FALSE) -> 1 | X2: =TEXT(VLOOKUP(Table1[[#This Row],[Sales_ID]],Sales!$A$2:$O$2001,13,FALSE),"₹#,##0") -> ₹218 | Y2: =VLOOKUP(Table1[[#This Row],[Sales_ID]],Sales!$A$2:$O$2001,14,FALSE) -> 0.09 | Z2: =VLOOKUP(Table1[[#This Row],[Sales_ID]],Sales!$A$2:$O$2001,10,FALSE) -> Credit Card | AA2: =VLOOKUP(Table1[[#This Row],[Sales_ID]],Sales!$A$2:$O$2001,15,FALSE) -> 198.4164 | AC2: Summary
A3: CUST1467 | B3: =PROPER(VLOOKUP(A3,Customer!$A$2:$J$501,9,FALSE)) -> Michael Foley | C3: =PROPER(VLOOKUP(A3,Customer!$A$2:$H$501,3,FALSE)) -> 63 | D3: =PROPER(VLOOKUP(A3,Customer!$A$2:$H$501,4,FALSE)) -> Female | E3: =PROPER(VLOOKUP(A3,Customer!$A$2:$H$501,5,FALSE)) -> Oneillfurt | F3: =PROPER(VLOOKUP(A3,Customer!$A$2:$H$501,6,FALSE)) -> Vermont | G3: =VLOOKUP(A3,Customer!$A$2:$H$501,7,FALSE) -> USA | H3: =PROPER(VLOOKUP(A3,Customer!$A$1:$J$501,10,FALSE)) -> Gold | I3: PROD74 | J3: =VLOOKUP(I3, Product!$A$2:$H$501, 2,FALSE) -> Bluetooth Car Audio System | K3: =VLOOKUP(I3,Product!$A$2:$H$501,3,FALSE) -> Electronics | L3: =VLOOKUP(I3, Product!$A$2:$H$501, 4,FALSE) -> Audio | M3: =VLOOKUP(I3, Product!$A$2:$H$501,5,FALSE) -> Bruce-Bowen | N3: =VLOOKUP(I3, Product!$A$2:$I$501,8,FALSE) -> 403.71 | O3: =VLOOKUP(I3, Product!$A$2:$I$501,9,FALSE) -> 159 | P3: STORE17 | Q3: =VLOOKUP(P3,Store_Dim!$A$2:$E$21,2,FALSE) -> Holloway Ltd | R3: =VLOOKUP(P3,Store_Dim!$A$2:$E$21,3,FALSE) -> North | S3: =VLOOKUP(P3,Store_Dim!$A$2:$E$21,4,FALSE) -> Bensonhaven | T3: =VLOOKUP(P3,Store_Dim!$A$2:$E$21,5,FALSE) -> Flagship | U3: SALE1 | V3: =VLOOKUP(Table1[[#This Row],[Sales_ID]],Sales!$A$2:$O$2001,2,FALSE) -> 45285 | W3: =VLOOKUP(Table1[[#This Row],[Sales_ID]],Sales!$A$2:$O$2001,12,FALSE) -> 3 | X3: =TEXT(VLOOKUP(Table1[[#This Row],[Sales_ID]],Sales!$A$2:$O$2001,13,FALSE),"₹#,##0") -> ₹104 | Y3: =VLOOKUP(Table1[[#This Row],[Sales_ID]],Sales!$A$2:$O$2001,14,FALSE) -> 0.27 | Z3: =VLOOKUP(Table1[[#This Row],[Sales_ID]],Sales!$A$2:$O$2001,10,FALSE) -> PayPal | AA3: =VLOOKUP(Table1[[#This Row],[Sales_ID]],Sales!$A$2:$O$2001,15,FALSE) -> 228.7893 | AC3: 1)use vlookup to bring
A4: CUST1065 | B4: =PROPER(VLOOKUP(A4,Customer!$A$2:$J$501,9,FALSE)) -> Michael Thomas | C4: =PROPER(VLOOKUP(A4,Customer!$A$2:$H$501,3,FALSE)) -> 21 | D4: =PROPER(VLOOKUP(A4,Customer!$A$2:$H$501,4,FALSE)) -> Female | E4: =PROPER(VLOOKUP(A4,Customer!$A$2:$H$501,5,FALSE)) -> Woodmouth | F4: =PROPER(VLOOKUP(A4,Customer!$A$2:$H$501,6,FALSE)) -> Nevada | G4: =VLOOKUP(A4,Customer!$A$2:$H$501,7,FALSE) -> USA | H4: =PROPER(VLOOKUP(A4,Customer!$A$1:$J$501,10,FALSE)) -> Silver | I4: PROD24 | J4: =VLOOKUP(I4, Product!$A$2:$H$501, 2,FALSE) -> Foldable Camping Chair | K4: =VLOOKUP(I4,Product!$A$2:$H$501,3,FALSE) -> Sports | L4: =VLOOKUP(I4, Product!$A$2:$H$501, 4,FALSE) -> Outdoor | M4: =VLOOKUP(I4, Product!$A$2:$H$501,5,FALSE) -> Cook Ltd | N4: =VLOOKUP(I4, Product!$A$2:$I$501,8,FALSE) -> 166.06 | O4: =VLOOKUP(I4, Product!$A$2:$I$501,9,FALSE) -> 340 | P4: STORE14 | Q4: =VLOOKUP(P4,Store_Dim!$A$2:$E$21,2,FALSE) -> Mcdonald Inc | R4: =VLOOKUP(P4,Store_Dim!$A$2:$E$21,3,FALSE) -> South | S4: =VLOOKUP(P4,Store_Dim!$A$2:$E$21,4,FALSE) -> Christopherland | T4: =VLOOKUP(P4,Store_Dim!$A$2:$E$21,5,FALSE) -> Outlet | U4: SALE10 | V4: =VLOOKUP(Table1[[#This Row],[Sales_ID]],Sales!$A$2:$O$2001,2,FALSE) -> 45335 | W4: =VLOOKUP(Table1[[#This Row],[Sales_ID]],Sales!$A$2:$O$2001,12,FALSE) -> 1 | X4: =TEXT(VLOOKUP(Table1[[#This Row],[Sales_ID]],Sales!$A$2:$O$2001,13,FALSE),"₹#,##0") -> ₹279 | Y4: =VLOOKUP(Table1[[#This Row],[Sales_ID]],Sales!$A$2:$O$2001,14,FALSE) -> 0.07 | Z4: =VLOOKUP(Table1[[#This Row],[Sales_ID]],Sales!$A$2:$O$2001,10,FALSE) -> Credit Card | AA4: =VLOOKUP(Table1[[#This Row],[Sales_ID]],Sales!$A$2:$O$2001,15,FALSE) -> 259.1259 | AC4: columns from the other sheet
A5: CUST1369 | B5: =PROPER(VLOOKUP(A5,Customer!$A$2:$J$501,9,FALSE)) -> Gregory Allen | C5: =PROPER(VLOOKUP(A5,Customer!$A$2:$H$501,3,FALSE)) -> 20 | D5: =PROPER(VLOOKUP(A5,Customer!$A$2:$H$501,4,FALSE)) -> Female | E5: =PROPER(VLOOKUP(A5,Customer!$A$2:$H$501,5,FALSE)) -> West Bruce | F5: =PROPER(VLOOKUP(A5,Customer!$A$2:$H$501,6,FALSE)) -> Vermont | G5: =VLOOKUP(A5,Customer!$A$2:$H$501,7,FALSE) -> USA | H5: =PROPER(VLOOKUP(A5,Customer!$A$1:$J$501,10,FALSE)) -> Platinum | I5: PROD33 | J5: =VLOOKUP(I5, Product!$A$2:$H$501, 2,FALSE) -> Modern Wall Clock | K5: =VLOOKUP(I5,Product!$A$2:$H$501,3,FALSE) -> Home | L5: =VLOOKUP(I5, Product!$A$2:$H$501, 4,FALSE) -> Decor | M5: =VLOOKUP(I5, Product!$A$2:$H$501,5,FALSE) -> Weiss-Watson | N5: =VLOOKUP(I5, Product!$A$2:$I$501,8,FALSE) -> 179.77 | O5: =VLOOKUP(I5, Product!$A$2:$I$501,9,FALSE) -> 305 | P5: STORE5 | Q5: =VLOOKUP(P5,Store_Dim!$A$2:$E$21,2,FALSE) -> Gray Ltd | R5: =VLOOKUP(P5,Store_Dim!$A$2:$E$21,3,FALSE) -> North | S5: =VLOOKUP(P5,Store_Dim!$A$2:$E$21,4,FALSE) -> New Michaelchester | T5: =VLOOKUP(P5,Store_Dim!$A$2:$E$21,5,FALSE) -> Outlet | U5: SALE100 | V5: =VLOOKUP(Table1[[#This Row],[Sales_ID]],Sales!$A$2:$O$2001,2,FALSE) -> 45677 | W5: =VLOOKUP(Table1[[#This Row],[Sales_ID]],Sales!$A$2:$O$2001,12,FALSE) -> 2 | X5: =TEXT(VLOOKUP(Table1[[#This Row],[Sales_ID]],Sales!$A$2:$O$2001,13,FALSE),"₹#,##0") -> ₹402 | Y5: =VLOOKUP(Table1[[#This Row],[Sales_ID]],Sales!$A$2:$O$2001,14,FALSE) -> 0.18 | Z5: =VLOOKUP(Table1[[#This Row],[Sales_ID]],Sales!$A$2:$O$2001,10,FALSE) -> Credit Card | AA5: =VLOOKUP(Table1[[#This Row],[Sales_ID]],Sales!$A$2:$O$2001,15,FALSE) -> 658.46 | AC5: 2) used text formula to makes rupees in unit price
A6: CUST1190 | B6: =PROPER(VLOOKUP(A6,Customer!$A$2:$J$501,9,FALSE)) -> Christopher Stewart | C6: =PROPER(VLOOKUP(A6,Customer!$A$2:$H$501,3,FALSE)) -> 21 | D6: =PROPER(VLOOKUP(A6,Customer!$A$2:$H$501,4,FALSE)) -> Male | E6: =PROPER(VLOOKUP(A6,Customer!$A$2:$H$501,5,FALSE)) -> Amandaside | F6: =PROPER(VLOOKUP(A6,Customer!$A$2:$H$501,6,FALSE)) -> New York | G6: =VLOOKUP(A6,Customer!$A$2:$H$501,7,FALSE) -> USA | H6: =PROPER(VLOOKUP(A6,Customer!$A$1:$J$501,10,FALSE)) -> Bronze | I6: PROD59 | J6: =VLOOKUP(I6, Product!$A$2:$H$501, 2,FALSE) -> Men's Hair Styling Gel | K6: =VLOOKUP(I6,Product!$A$2:$H$501,3,FALSE) -> Beauty | L6: =VLOOKUP(I6, Product!$A$2:$H$501, 4,FALSE) -> Haircare | M6: =VLOOKUP(I6, Product!$A$2:$H$501,5,FALSE) -> Cline-Mccarthy | N6: =VLOOKUP(I6, Product!$A$2:$I$501,8,FALSE) -> 17.31 | O6: =VLOOKUP(I6, Product!$A$2:$I$501,9,FALSE) -> 399 | P6: STORE2 | Q6: =VLOOKUP(P6,Store_Dim!$A$2:$E$21,2,FALSE) -> Black-Horn | R6: =VLOOKUP(P6,Store_Dim!$A$2:$E$21,3,FALSE) -> South | S6: =VLOOKUP(P6,Store_Dim!$A$2:$E$21,4,FALSE) -> North Nancyview | T6: =VLOOKUP(P6,Store_Dim!$A$2:$E$21,5,FALSE) -> Outlet | U6: SALE1000 | V6: =VLOOKUP(Table1[[#This Row],[Sales_ID]],Sales!$A$2:$O$2001,2,FALSE) -> 45456 | W6: =VLOOKUP(Table1[[#This Row],[Sales_ID]],Sales!$A$2:$O$2001,12,FALSE) -> 2 | X6: =TEXT(VLOOKUP(Table1[[#This Row],[Sales_ID]],Sales!$A$2:$O$2001,13,FALSE),"₹#,##0") -> ₹910 | Y6: =VLOOKUP(Table1[[#This Row],[Sales_ID]],Sales!$A$2:$O$2001,14,FALSE) -> 0.27 | Z6: =VLOOKUP(Table1[[#This Row],[Sales_ID]],Sales!$A$2:$O$2001,10,FALSE) -> Credit Card | AA6: =VLOOKUP(Table1[[#This Row],[Sales_ID]],Sales!$A$2:$O$2001,15,FALSE) -> 1327.8846
A7: CUST1052 | B7: =PROPER(VLOOKUP(A7,Customer!$A$2:$J$501,9,FALSE)) -> Debra Liu | C7: =PROPER(VLOOKUP(A7,Customer!$A$2:$H$501,3,FALSE)) -> 55 | D7: =PROPER(VLOOKUP(A7,Customer!$A$2:$H$501,4,FALSE)) -> Male | E7: =PROPER(VLOOKUP(A7,Customer!$A$2:$H$501,5,FALSE)) -> South Timtown | F7: =PROPER(VLOOKUP(A7,Customer!$A$2:$H$501,6,FALSE)) -> Minnesota | G7: =VLOOKUP(A7,Customer!$A$2:$H$501,7,FALSE) -> USA | H7: =PROPER(VLOOKUP(A7,Customer!$A$1:$J$501,10,FALSE)) -> Bronze | I7: PROD69 | J7: =VLOOKUP(I7, Product!$A$2:$H$501, 2,FALSE) -> Men's Sports Shorts | K7: =VLOOKUP(I7,Product!$A$2:$H$501,3,FALSE) -> Clothing | L7: =VLOOKUP(I7, Product!$A$2:$H$501, 4,FALSE) -> Bottoms | M7: =VLOOKUP(I7, Product!$A$2:$H$501,5,FALSE) -> Fitzpatrick Ltd | N7: =VLOOKUP(I7, Product!$A$2:$I$501,8,FALSE) -> 218.22 | O7: =VLOOKUP(I7, Product!$A$2:$I$501,9,FALSE) -> 224 | P7: STORE14 | Q7: =VLOOKUP(P7,Store_Dim!$A$2:$E$21,2,FALSE) -> Mcdonald Inc | R7: =VLOOKUP(P7,Store_Dim!$A$2:$E$21,3,FALSE) -> South | S7: =VLOOKUP(P7,Store_Dim!$A$2:$E$21,4,FALSE) -> Christopherland | T7: =VLOOKUP(P7,Store_Dim!$A$2:$E$21,5,FALSE) -> Outlet | U7: SALE1001 | V7: =VLOOKUP(Table1[[#This Row],[Sales_ID]],Sales!$A$2:$O$2001,2,FALSE) -> 45776 | W7: =VLOOKUP(Table1[[#This Row],[Sales_ID]],Sales!$A$2:$O$2001,12,FALSE) -> 4 | X7: =TEXT(VLOOKUP(Table1[[#This Row],[Sales_ID]],Sales!$A$2:$O$2001,13,FALSE),"₹#,##0") -> ₹594 | Y7: =VLOOKUP(Table1[[#This Row],[Sales_ID]],Sales!$A$2:$O$2001,14,FALSE) -> 0.24 | Z7: =VLOOKUP(Table1[[#This Row],[Sales_ID]],Sales!$A$2:$O$2001,10,FALSE) -> PayPal | AA7: =VLOOKUP(Table1[[#This Row],[Sales_ID]],Sales!$A$2:$O$2001,15,FALSE) -> 1805.2736
A8: CUST1109 | B8: =PROPER(VLOOKUP(A8,Customer!$A$2:$J$501,9,FALSE)) -> Amy Walker | C8: =PROPER(VLOOKUP(A8,Customer!$A$2:$H$501,3,FALSE)) -> 27 | D8: =PROPER(VLOOKUP(A8,Customer!$A$2:$H$501,4,FALSE)) -> Male | E8: =PROPER(VLOOKUP(A8,Customer!$A$2:$H$501,5,FALSE)) -> Smithland | F8: =PROPER(VLOOKUP(A8,Customer!$A$2:$H$501,6,FALSE)) -> West Virginia | G8: =VLOOKUP(A8,Customer!$A$2:$H$501,7,FALSE) -> USA | H8: =PROPER(VLOOKUP(A8,Customer!$A$1:$J$501,10,FALSE)) -> Silver | I8: PROD73 | J8: =VLOOKUP(I8, Product!$A$2:$H$501, 2,FALSE) -> Shin Guards – Adult | K8: =VLOOKUP(I8,Product!$A$2:$H$501,3,FALSE) -> Sports | L8: =VLOOKUP(I8, Product!$A$2:$H$501, 4,FALSE) -> Team Sports | M8: =VLOOKUP(I8, Product!$A$2:$H$501,5,FALSE) -> French Ltd | N8: =VLOOKUP(I8, Product!$A$2:$I$501,8,FALSE) -> 107.06 | O8: =VLOOKUP(I8, Product!$A$2:$I$501,9,FALSE) -> 359 | P8: STORE10 | Q8: =VLOOKUP(P8,Store_Dim!$A$2:$E$21,2,FALSE) -> Hill, Wagner and Ballard | R8: =VLOOKUP(P8,Store_Dim!$A$2:$E$21,3,FALSE) -> East | S8: =VLOOKUP(P8,Store_Dim!$A$2:$E$21,4,FALSE) -> East Davidville | T8: =VLOOKUP(P8,Store_Dim!$A$2:$E$21,5,FALSE) -> Online | U8: SALE1002 | V8: =VLOOKUP(Table1[[#This Row],[Sales_ID]],Sales!$A$2:$O$2001,2,FALSE) -> 45566 | W8: =VLOOKUP(Table1[[#This Row],[Sales_ID]],Sales!$A$2:$O$2001,12,FALSE) -> 3 | X8: =TEXT(VLOOKUP(Table1[[#This Row],[Sales_ID]],Sales!$A$2:$O$2001,13,FALSE),"₹#,##0") -> ₹909 | Y8: =VLOOKUP(Table1[[#This Row],[Sales_ID]],Sales!$A$2:$O$2001,14,FALSE) -> 0.23 | Z8: =VLOOKUP(Table1[[#This Row],[Sales_ID]],Sales!$A$2:$O$2001,10,FALSE) -> COD | AA8: =VLOOKUP(Table1[[#This Row],[Sales_ID]],Sales!$A$2:$O$2001,15,FALSE) -> 2100.0441
A9: CUST1399 | B9: =PROPER(VLOOKUP(A9,Customer!$A$2:$J$501,9,FALSE)) -> John Donaldson | C9: =PROPER(VLOOKUP(A9,Customer!$A$2:$H$501,3,FALSE)) -> 27 | D9: =PROPER(VLOOKUP(A9,Customer!$A$2:$H$501,4,FALSE)) -> Male | E9: =PROPER(VLOOKUP(A9,Customer!$A$2:$H$501,5,FALSE)) -> New Edward | F9: =PROPER(VLOOKUP(A9,Customer!$A$2:$H$501,6,FALSE)) -> Maine | G9: =VLOOKUP(A9,Customer!$A$2:$H$501,7,FALSE) -> USA | H9: =PROPER(VLOOKUP(A9,Customer!$A$1:$J$501,10,FALSE)) -> Bronze | I9: PROD24 | J9: =VLOOKUP(I9, Product!$A$2:$H$501, 2,FALSE) -> Foldable Camping Chair | K9: =VLOOKUP(I9,Product!$A$2:$H$501,3,FALSE) -> Sports | L9: =VLOOKUP(I9, Product!$A$2:$H$501, 4,FALSE) -> Outdoor | M9: =VLOOKUP(I9, Product!$A$2:$H$501,5,FALSE) -> Cook Ltd | N9: =VLOOKUP(I9, Product!$A$2:$I$501,8,FALSE) -> 166.06 | O9: =VLOOKUP(I9, Product!$A$2:$I$501,9,FALSE) -> 340 | P9: STORE1 | Q9: =VLOOKUP(P9,Store_Dim!$A$2:$E$21,2,FALSE) -> Martinez, Adkins and Johnson | R9: =VLOOKUP(P9,Store_Dim!$A$2:$E$21,3,FALSE) -> North | S9: =VLOOKUP(P9,Store_Dim!$A$2:$E$21,4,FALSE) -> Danielmouth | T9: =VLOOKUP(P9,Store_Dim!$A$2:$E$21,5,FALSE) -> Flagship | U9: SALE1003 | V9: =VLOOKUP(Table1[[#This Row],[Sales_ID]],Sales!$A$2:$O$2001,2,FALSE) -> 45542 | W9: =VLOOKUP(Table1[[#This Row],[Sales_ID]],Sales!$A$2:$O$2001,12,FALSE) -> 4 | X9: =TEXT(VLOOKUP(Table1[[#This Row],[Sales_ID]],Sales!$A$2:$O$2001,13,FALSE),"₹#,##0") -> ₹997 | Y9: =VLOOKUP(Table1[[#This Row],[Sales_ID]],Sales!$A$2:$O$2001,14,FALSE) -> 0.24 | Z9: =VLOOKUP(Table1[[#This Row],[Sales_ID]],Sales!$A$2:$O$2001,10,FALSE) -> PayPal | AA9: =VLOOKUP(Table1[[#This Row],[Sales_ID]],Sales!$A$2:$O$2001,15,FALSE) -> 3030.424
A10: CUST1300 | B10: =PROPER(VLOOKUP(A10,Customer!$A$2:$J$501,9,FALSE)) -> Matthew Avery | C10: =PROPER(VLOOKUP(A10,Customer!$A$2:$H$501,3,FALSE)) -> 29 | D10: =PROPER(VLOOKUP(A10,Customer!$A$2:$H$501,4,FALSE)) -> Male | E10: =PROPER(VLOOKUP(A10,Customer!$A$2:$H$501,5,FALSE)) -> Lake Melissashire | F10: =PROPER(VLOOKUP(A10,Customer!$A$2:$H$501,6,FALSE)) -> Oregon | G10: =VLOOKUP(A10,Customer!$A$2:$H$501,7,FALSE) -> USA | H10: =PROPER(VLOOKUP(A10,Customer!$A$1:$J$501,10,FALSE)) -> Silver | I10: PROD0 | J10: =VLOOKUP(I10, Product!$A$2:$H$501, 2,FALSE) -> Brother Laser Printer | K10: =VLOOKUP(I10,Product!$A$2:$H$501,3,FALSE) -> Electronics | L10: =VLOOKUP(I10, Product!$A$2:$H$501, 4,FALSE) -> Computer | M10: =VLOOKUP(I10, Product!$A$2:$H$501,5,FALSE) -> Hunt Inc | N10: =VLOOKUP(I10, Product!$A$2:$I$501,8,FALSE) -> 112.42 | O10: =VLOOKUP(I10, Product!$A$2:$I$501,9,FALSE) -> 416 | P10: STORE17 | Q10: =VLOOKUP(P10,Store_Dim!$A$2:$E$21,2,FALSE) -> Holloway Ltd | R10: =VLOOKUP(P10,Store_Dim!$A$2:$E$21,3,FALSE) -> North | S10: =VLOOKUP(P10,Store_Dim!$A$2:$E$21,4,FALSE) -> Bensonhaven | T10: =VLOOKUP(P10,Store_Dim!$A$2:$E$21,5,FALSE) -> Flagship | U10: SALE1004 | V10: =VLOOKUP(Table1[[#This Row],[Sales_ID]],Sales!$A$2:$O$2001,2,FALSE) -> 45834 | W10: =VLOOKUP(Table1[[#This Row],[Sales_ID]],Sales!$A$2:$O$2001,12,FALSE) -> 1 | X10: =TEXT(VLOOKUP(Table1[[#This Row],[Sales_ID]],Sales!$A$2:$O$2001,13,FALSE),"₹#,##0") -> ₹523 | Y10: =VLOOKUP(Table1[[#This Row],[Sales_ID]],Sales!$A$2:$O$2001,14,FALSE) -> 0.06 | Z10: =VLOOKUP(Table1[[#This Row],[Sales_ID]],Sales!$A$2:$O$2001,10,FALSE) -> COD | AA10: =VLOOKUP(Table1[[#This Row],[Sales_ID]],Sales!$A$2:$O$2001,15,FALSE) -> 491.3286
A11: CUST1194 | B11: =PROPER(VLOOKUP(A11,Customer!$A$2:$J$501,9,FALSE)) -> Ashley Ferguson | C11: =PROPER(VLOOKUP(A11,Customer!$A$2:$H$501,3,FALSE)) -> 46 | D11: =PROPER(VLOOKUP(A11,Customer!$A$2:$H$501,4,FALSE)) -> Male | E11: =PROPER(VLOOKUP(A11,Customer!$A$2:$H$501,5,FALSE)) -> Sarahmouth | F11: =PROPER(VLOOKUP(A11,Customer!$A$2:$H$501,6,FALSE)) -> Pennsylvania | G11: =VLOOKUP(A11,Customer!$A$2:$H$501,7,FALSE) -> USA | H11: =PROPER(VLOOKUP(A11,Customer!$A$1:$J$501,10,FALSE)) -> Gold | I11: PROD54 | J11: =VLOOKUP(I11, Product!$A$2:$H$501, 2,FALSE) -> Sports Stopwatch Pro | K11: =VLOOKUP(I11,Product!$A$2:$H$501,3,FALSE) -> Sports | L11: =VLOOKUP(I11, Product!$A$2:$H$501, 4,FALSE) -> Accessories | M11: =VLOOKUP(I11, Product!$A$2:$H$501,5,FALSE) -> Thompson-French | N11: =VLOOKUP(I11, Product!$A$2:$I$501,8,FALSE) -> 434.84 | O11: =VLOOKUP(I11, Product!$A$2:$I$501,9,FALSE) -> 185 | P11: STORE3 | Q11: =VLOOKUP(P11,Store_Dim!$A$2:$E$21,2,FALSE) -> Johnson-Wright | R11: =VLOOKUP(P11,Store_Dim!$A$2:$E$21,3,FALSE) -> North | S11: =VLOOKUP(P11,Store_Dim!$A$2:$E$21,4,FALSE) -> Hoodberg | T11: =VLOOKUP(P11,Store_Dim!$A$2:$E$21,5,FALSE) -> Outlet | U11: SALE1005 | V11: =VLOOKUP(Table1[[#This Row],[Sales_ID]],Sales!$A$2:$O$2001,2,FALSE) -> 45405 | W11: =VLOOKUP(Table1[[#This Row],[Sales_ID]],Sales!$A$2:$O$2001,12,FALSE) -> 3 | X11: =TEXT(VLOOKUP(Table1[[#This Row],[Sales_ID]],Sales!$A$2:$O$2001,13,FALSE),"₹#,##0") -> ₹261 | Y11: =VLOOKUP(Table1[[#This Row],[Sales_ID]],Sales!$A$2:$O$2001,14,FALSE) -> 0.12 | Z11: =VLOOKUP(Table1[[#This Row],[Sales_ID]],Sales!$A$2:$O$2001,10,FALSE) -> PayPal | AA11: =VLOOKUP(Table1[[#This Row],[Sales_ID]],Sales!$A$2:$O$2001,15,FALSE) -> 689.172
A12: CUST1087 | B12: =PROPER(VLOOKUP(A12,Customer!$A$2:$J$501,9,FALSE)) -> Melissa Duffy Md | C12: =PROPER(VLOOKUP(A12,Customer!$A$2:$H$501,3,FALSE)) -> 58 | D12: =PROPER(VLOOKUP(A12,Customer!$A$2:$H$501,4,FALSE)) -> Female | E12: =PROPER(VLOOKUP(A12,Customer!$A$2:$H$501,5,FALSE)) -> East Jenna | F12: =PROPER(VLOOKUP(A12,Customer!$A$2:$H$501,6,FALSE)) -> South Carolina | G12: =VLOOKUP(A12,Customer!$A$2:$H$501,7,FALSE) -> USA | H12: =PROPER(VLOOKUP(A12,Customer!$A$1:$J$501,10,FALSE)) -> Bronze | I12: PROD23 | J12: =VLOOKUP(I12, Product!$A$2:$H$501, 2,FALSE) -> Men's Formal Shirt | K12: =VLOOKUP(I12,Product!$A$2:$H$501,3,FALSE) -> Clothing | L12: =VLOOKUP(I12, Product!$A$2:$H$501, 4,FALSE) -> Tops | M12: =VLOOKUP(I12, Product!$A$2:$H$501,5,FALSE) -> Moon, Mora and Santos | N12: =VLOOKUP(I12, Product!$A$2:$I$501,8,FALSE) -> 265.73267 | O12: =VLOOKUP(I12, Product!$A$2:$I$501,9,FALSE) -> 360 | P12: STORE17 | Q12: =VLOOKUP(P12,Store_Dim!$A$2:$E$21,2,FALSE) -> Holloway Ltd | R12: =VLOOKUP(P12,Store_Dim!$A$2:$E$21,3,FALSE) -> North | S12: =VLOOKUP(P12,Store_Dim!$A$2:$E$21,4,FALSE) -> Bensonhaven | T12: =VLOOKUP(P12,Store_Dim!$A$2:$E$21,5,FALSE) -> Flagship | U12: SALE1006 | V12: =VLOOKUP(Table1[[#This Row],[Sales_ID]],Sales!$A$2:$O$2001,2,FALSE) -> 45918 | W12: =VLOOKUP(Table1[[#This Row],[Sales_ID]],Sales!$A$2:$O$2001,12,FALSE) -> 3 | X12: =TEXT(VLOOKUP(Table1[[#This Row],[Sales_ID]],Sales!$A$2:$O$2001,13,FALSE),"₹#,##0") -> ₹645 | Y12: =VLOOKUP(Table1[[#This Row],[Sales_ID]],Sales!$A$2:$O$2001,14,FALSE) -> 0.01 | Z12: =VLOOKUP(Table1[[#This Row],[Sales_ID]],Sales!$A$2:$O$2001,10,FALSE) -> COD | AA12: =VLOOKUP(Table1[[#This Row],[Sales_ID]],Sales!$A$2:$O$2001,15,FALSE) -> 1914.8481
A13: CUST1198 | B13: =PROPER(VLOOKUP(A13,Customer!$A$2:$J$501,9,FALSE)) -> Wanda Snyder | C13: =PROPER(VLOOKUP(A13,Customer!$A$2:$H$501,3,FALSE)) -> 54 | D13: =PROPER(VLOOKUP(A13,Customer!$A$2:$H$501,4,FALSE)) -> Male | E13: =PROPER(VLOOKUP(A13,Customer!$A$2:$H$501,5,FALSE)) -> Frostmouth | F13: =PROPER(VLOOKUP(A13,Customer!$A$2:$H$501,6,FALSE)) -> Vermont | G13: =VLOOKUP(A13,Customer!$A$2:$H$501,7,FALSE) -> USA | H13: =PROPER(VLOOKUP(A13,Customer!$A$1:$J$501,10,FALSE)) -> Bronze | I13: PROD75 | J13: =VLOOKUP(I13, Product!$A$2:$H$501, 2,FALSE) -> Women's Ankle Boots | K13: =VLOOKUP(I13,Product!$A$2:$H$501,3,FALSE) -> Clothing | L13: =VLOOKUP(I13, Product!$A$2:$H$501, 4,FALSE) -> Footwear | M13: =VLOOKUP(I13, Product!$A$2:$H$501,5,FALSE) -> Poole PLC | N13: =VLOOKUP(I13, Product!$A$2:$I$501,8,FALSE) -> 158.14 | O13: =VLOOKUP(I13, Product!$A$2:$I$501,9,FALSE) -> 82 | P13: STORE2 | Q13: =VLOOKUP(P13,Store_Dim!$A$2:$E$21,2,FALSE) -> Black-Horn | R13: =VLOOKUP(P13,Store_Dim!$A$2:$E$21,3,FALSE) -> South | S13: =VLOOKUP(P13,Store_Dim!$A$2:$E$21,4,FALSE) -> North Nancyview | T13: =VLOOKUP(P13,Store_Dim!$A$2:$E$21,5,FALSE) -> Outlet | U13: SALE1007 | V13: =VLOOKUP(Table1[[#This Row],[Sales_ID]],Sales!$A$2:$O$2001,2,FALSE) -> 45217 | W13: =VLOOKUP(Table1[[#This Row],[Sales_ID]],Sales!$A$2:$O$2001,12,FALSE) -> 2 | X13: =TEXT(VLOOKUP(Table1[[#This Row],[Sales_ID]],Sales!$A$2:$O$2001,13,FALSE),"₹#,##0") -> ₹542 | Y13: =VLOOKUP(Table1[[#This Row],[Sales_ID]],Sales!$A$2:$O$2001,14,FALSE) -> 0.26 | Z13: =VLOOKUP(Table1[[#This Row],[Sales_ID]],Sales!$A$2:$O$2001,10,FALSE) -> PayPal | AA13: =VLOOKUP(Table1[[#This Row],[Sales_ID]],Sales!$A$2:$O$2001,15,FALSE) -> 801.4496
A14: CUST1426 | B14: =PROPER(VLOOKUP(A14,Customer!$A$2:$J$501,9,FALSE)) -> Jeanette Nichols | C14: =PROPER(VLOOKUP(A14,Customer!$A$2:$H$501,3,FALSE)) -> 28 | D14: =PROPER(VLOOKUP(A14,Customer!$A$2:$H$501,4,FALSE)) -> Male | E14: =PROPER(VLOOKUP(A14,Customer!$A$2:$H$501,5,FALSE)) -> Aguilarland | F14: =PROPER(VLOOKUP(A14,Customer!$A$2:$H$501,6,FALSE)) -> North Carolina | G14: =VLOOKUP(A14,Customer!$A$2:$H$501,7,FALSE) -> USA | H14: =PROPER(VLOOKUP(A14,Customer!$A$1:$J$501,10,FALSE)) -> Platinum | I14: PROD63 | J14: =VLOOKUP(I14, Product!$A$2:$H$501, 2,FALSE) -> Organic Sunscreen Lotion | K14: =VLOOKUP(I14,Product!$A$2:$H$501,3,FALSE) -> Beauty | L14: =VLOOKUP(I14, Product!$A$2:$H$501, 4,FALSE) -> Skincare | M14: =VLOOKUP(I14, Product!$A$2:$H$501,5,FALSE) -> Anderson-Riley | N14: =VLOOKUP(I14, Product!$A$2:$I$501,8,FALSE) -> 266.86 | O14: =VLOOKUP(I14, Product!$A$2:$I$501,9,FALSE) -> 458 | P14: STORE10 | Q14: =VLOOKUP(P14,Store_Dim!$A$2:$E$21,2,FALSE) -> Hill, Wagner and Ballard | R14: =VLOOKUP(P14,Store_Dim!$A$2:$E$21,3,FALSE) -> East | S14: =VLOOKUP(P14,Store_Dim!$A$2:$E$21,4,FALSE) -> East Davidville | T14: =VLOOKUP(P14,Store_Dim!$A$2:$E$21,5,FALSE) -> Online | U14: SALE1008 | V14: =VLOOKUP(Table1[[#This Row],[Sales_ID]],Sales!$A$2:$O$2001,2,FALSE) -> 45259 | W14: =VLOOKUP(Table1[[#This Row],[Sales_ID]],Sales!$A$2:$O$2001,12,FALSE) -> 1 | X14: =TEXT(VLOOKUP(Table1[[#This Row],[Sales_ID]],Sales!$A$2:$O$2001,13,FALSE),"₹#,##0") -> ₹395 | Y14: =VLOOKUP(Table1[[#This Row],[Sales_ID]],Sales!$A$2:$O$2001,14,FALSE) -> 0.09 | Z14: =VLOOKUP(Table1[[#This Row],[Sales_ID]],Sales!$A$2:$O$2001,10,FALSE) -> PayPal | AA14: =VLOOKUP(Table1[[#This Row],[Sales_ID]],Sales!$A$2:$O$2001,15,FALSE) -> 359.6138
A15: CUST1100 | B15: =PROPER(VLOOKUP(A15,Customer!$A$2:$J$501,9,FALSE)) -> Diane Watson | C15: =PROPER(VLOOKUP(A15,Customer!$A$2:$H$501,3,FALSE)) -> 53 | D15: =PROPER(VLOOKUP(A15,Customer!$A$2:$H$501,4,FALSE)) -> Female | E15: =PROPER(VLOOKUP(A15,Customer!$A$2:$H$501,5,FALSE)) -> North Codyport | F15: =PROPER(VLOOKUP(A15,Customer!$A$2:$H$501,6,FALSE)) -> Texas | G15: =VLOOKUP(A15,Customer!$A$2:$H$501,7,FALSE) -> USA | H15: =PROPER(VLOOKUP(A15,Customer!$A$1:$J$501,10,FALSE)) -> Platinum | I15: PROD8 | J15: =VLOOKUP(I15, Product!$A$2:$H$501, 2,FALSE) -> Wireless Bluetooth Earbuds | K15: =VLOOKUP(I15,Product!$A$2:$H$501,3,FALSE) -> Electronics | L15: =VLOOKUP(I15, Product!$A$2:$H$501, 4,FALSE) -> Audio | M15: =VLOOKUP(I15, Product!$A$2:$H$501,5,FALSE) -> Perez-Johnston | N15: =VLOOKUP(I15, Product!$A$2:$I$501,8,FALSE) -> 439.07 | O15: =VLOOKUP(I15, Product!$A$2:$I$501,9,FALSE) -> 142 | P15: STORE8 | Q15: =VLOOKUP(P15,Store_Dim!$A$2:$E$21,2,FALSE) -> Bean, Jones and Park | R15: =VLOOKUP(P15,Store_Dim!$A$2:$E$21,3,FALSE) -> West | S15: =VLOOKUP(P15,Store_Dim!$A$2:$E$21,4,FALSE) -> Thompsonborough | T15: =VLOOKUP(P15,Store_Dim!$A$2:$E$21,5,FALSE) -> Online | U15: SALE1009 | V15: =VLOOKUP(Table1[[#This Row],[Sales_ID]],Sales!$A$2:$O$2001,2,FALSE) -> 45740 | W15: =VLOOKUP(Table1[[#This Row],[Sales_ID]],Sales!$A$2:$O$2001,12,FALSE) -> 4 | X15: =TEXT(VLOOKUP(Table1[[#This Row],[Sales_ID]],Sales!$A$2:$O$2001,13,FALSE),"₹#,##0") -> ₹56 | Y15: =VLOOKUP(Table1[[#This Row],[Sales_ID]],Sales!$A$2:$O$2001,14,FALSE) -> 0.17 | Z15: =VLOOKUP(Table1[[#This Row],[Sales_ID]],Sales!$A$2:$O$2001,10,FALSE) -> Credit Card | AA15: =VLOOKUP(Table1[[#This Row],[Sales_ID]],Sales!$A$2:$O$2001,15,FALSE) -> 187.1484
A16: CUST1084 | B16: =PROPER(VLOOKUP(A16,Customer!$A$2:$J$501,9,FALSE)) -> Christy Hoffman | C16: =PROPER(VLOOKUP(A16,Customer!$A$2:$H$501,3,FALSE)) -> 26 | D16: =PROPER(VLOOKUP(A16,Customer!$A$2:$H$501,4,FALSE)) -> Female | E16: =PROPER(VLOOKUP(A16,Customer!$A$2:$H$501,5,FALSE)) -> Garyberg | F16: =PROPER(VLOOKUP(A16,Customer!$A$2:$H$501,6,FALSE)) -> Indiana | G16: =VLOOKUP(A16,Customer!$A$2:$H$501,7,FALSE) -> USA | H16: =PROPER(VLOOKUP(A16,Customer!$A$1:$J$501,10,FALSE)) -> Platinum | I16: PROD25 | J16: =VLOOKUP(I16, Product!$A$2:$H$501, 2,FALSE) -> Women's Scarf Set | K16: =VLOOKUP(I16,Product!$A$2:$H$501,3,FALSE) -> Clothing | L16: =VLOOKUP(I16, Product!$A$2:$H$501, 4,FALSE) -> Accessories | M16: =VLOOKUP(I16, Product!$A$2:$H$501,5,FALSE) -> Brown and Sons | N16: =VLOOKUP(I16, Product!$A$2:$I$501,8,FALSE) -> 174.02 | O16: =VLOOKUP(I16, Product!$A$2:$I$501,9,FALSE) -> 268 | P16: STORE13 | Q16: =VLOOKUP(P16,Store_Dim!$A$2:$E$21,2,FALSE) -> Gardner, Humphrey and Contreras | R16: =VLOOKUP(P16,Store_Dim!$A$2:$E$21,3,FALSE) -> East | S16: =VLOOKUP(P16,Store_Dim!$A$2:$E$21,4,FALSE) -> Johnsonville | T16: =VLOOKUP(P16,Store_Dim!$A$2:$E$21,5,FALSE) -> Flagship | U16: SALE101 | V16: =VLOOKUP(Table1[[#This Row],[Sales_ID]],Sales!$A$2:$O$2001,2,FALSE) -> 45453 | W16: =VLOOKUP(Table1[[#This Row],[Sales_ID]],Sales!$A$2:$O$2001,12,FALSE) -> 3 | X16: =TEXT(VLOOKUP(Table1[[#This Row],[Sales_ID]],Sales!$A$2:$O$2001,13,FALSE),"₹#,##0") -> ₹360 | Y16: =VLOOKUP(Table1[[#This Row],[Sales_ID]],Sales!$A$2:$O$2001,14,FALSE) -> 0.17 | Z16: =VLOOKUP(Table1[[#This Row],[Sales_ID]],Sales!$A$2:$O$2001,10,FALSE) -> PayPal | AA16: =VLOOKUP(Table1[[#This Row],[Sales_ID]],Sales!$A$2:$O$2001,15,FALSE) -> 895.3044
A17: CUST1209 | B17: =PROPER(VLOOKUP(A17,Customer!$A$2:$J$501,9,FALSE)) -> Joan Johnson | C17: =PROPER(VLOOKUP(A17,Customer!$A$2:$H$501,3,FALSE)) -> 50 | D17: =PROPER(VLOOKUP(A17,Customer!$A$2:$H$501,4,FALSE)) -> Female | E17: =PROPER(VLOOKUP(A17,Customer!$A$2:$H$501,5,FALSE)) -> Lake Josephport | F17: =PROPER(VLOOKUP(A17,Customer!$A$2:$H$501,6,FALSE)) -> Maine | G17: =VLOOKUP(A17,Customer!$A$2:$H$501,7,FALSE) -> USA | H17: =PROPER(VLOOKUP(A17,Customer!$A$1:$J$501,10,FALSE)) -> Platinum | I17: PROD79 | J17: =VLOOKUP(I17, Product!$A$2:$H$501, 2,FALSE) -> Decorative Lamp Shade | K17: =VLOOKUP(I17,Product!$A$2:$H$501,3,FALSE) -> Home | L17: =VLOOKUP(I17, Product!$A$2:$H$501, 4,FALSE) -> Lighting | M17: =VLOOKUP(I17, Product!$A$2:$H$501,5,FALSE) -> Ramirez-Hanson | N17: =VLOOKUP(I17, Product!$A$2:$I$501,8,FALSE) -> 228.53 | O17: =VLOOKUP(I17, Product!$A$2:$I$501,9,FALSE) -> 469 | P17: STORE9 | Q17: =VLOOKUP(P17,Store_Dim!$A$2:$E$21,2,FALSE) -> Moore, Padilla and Butler | R17: =VLOOKUP(P17,Store_Dim!$A$2:$E$21,3,FALSE) -> South | S17: =VLOOKUP(P17,Store_Dim!$A$2:$E$21,4,FALSE) -> East Johnstad | T17: =VLOOKUP(P17,Store_Dim!$A$2:$E$21,5,FALSE) -> Flagship | U17: SALE1010 | V17: =VLOOKUP(Table1[[#This Row],[Sales_ID]],Sales!$A$2:$O$2001,2,FALSE) -> 45908 | W17: =VLOOKUP(Table1[[#This Row],[Sales_ID]],Sales!$A$2:$O$2001,12,FALSE) -> 4 | X17: =TEXT(VLOOKUP(Table1[[#This Row],[Sales_ID]],Sales!$A$2:$O$2001,13,FALSE),"₹#,##0") -> ₹203 | Y17: =VLOOKUP(Table1[[#This Row],[Sales_ID]],Sales!$A$2:$O$2001,14,FALSE) -> 0.06 | Z17: =VLOOKUP(Table1[[#This Row],[Sales_ID]],Sales!$A$2:$O$2001,10,FALSE) -> COD | AA17: =VLOOKUP(Table1[[#This Row],[Sales_ID]],Sales!$A$2:$O$2001,15,FALSE) -> 761.7384
A18: CUST1004 | B18: =PROPER(VLOOKUP(A18,Customer!$A$2:$J$501,9,FALSE)) -> Caroline Collins | C18: =PROPER(VLOOKUP(A18,Customer!$A$2:$H$501,3,FALSE)) -> 64 | D18: =PROPER(VLOOKUP(A18,Customer!$A$2:$H$501,4,FALSE)) -> Female | E18: =PROPER(VLOOKUP(A18,Customer!$A$2:$H$501,5,FALSE)) -> Nicholasshire | F18: =PROPER(VLOOKUP(A18,Customer!$A$2:$H$501,6,FALSE)) -> California | G18: =VLOOKUP(A18,Customer!$A$2:$H$501,7,FALSE) -> USA | H18: =PROPER(VLOOKUP(A18,Customer!$A$1:$J$501,10,FALSE)) -> Silver | I18: PROD81 | J18: =VLOOKUP(I18, Product!$A$2:$H$501, 2,FALSE) -> Badminton Racket Set | K18: =VLOOKUP(I18,Product!$A$2:$H$501,3,FALSE) -> Sports | L18: =VLOOKUP(I18, Product!$A$2:$H$501,4,FALSE) -> Equipment | M18: =VLOOKUP(I18, Product!$A$2:$H$501,5,FALSE) -> Robinson-Brown | N18: =VLOOKUP(I18, Product!$A$2:$I$501,8,FALSE) -> 285.54 | O18: =VLOOKUP(I18, Product!$A$2:$I$501,9,FALSE) -> 358 | P18: STORE5 | Q18: =VLOOKUP(P18,Store_Dim!$A$2:$E$21,2,FALSE) -> Gray Ltd | R18: =VLOOKUP(P18,Store_Dim!$A$2:$E$21,3,FALSE) -> North | S18: =VLOOKUP(P18,Store_Dim!$A$2:$E$21,4,FALSE) -> New Michaelchester | T18: =VLOOKUP(P18,Store_Dim!$A$2:$E$21,5,FALSE) -> Outlet | U18: SALE1011 | V18: =VLOOKUP(Table1[[#This Row],[Sales_ID]],Sales!$A$2:$O$2001,2,FALSE) -> 45601 | W18: =VLOOKUP(Table1[[#This Row],[Sales_ID]],Sales!$A$2:$O$2001,12,FALSE) -> 2 | X18: =TEXT(VLOOKUP(Table1[[#This Row],[Sales_ID]],Sales!$A$2:$O$2001,13,FALSE),"₹#,##0") -> ₹358 | Y18: =VLOOKUP(Table1[[#This Row],[Sales_ID]],Sales!$A$2:$O$2001,14,FALSE) -> 0.05 | Z18: =VLOOKUP(Table1[[#This Row],[Sales_ID]],Sales!$A$2:$O$2001,10,FALSE) -> PayPal | AA18: =VLOOKUP(Table1[[#This Row],[Sales_ID]],Sales!$A$2:$O$2001,15,FALSE) -> 680.884
A19: CUST1072 | B19: =PROPER(VLOOKUP(A19,Customer!$A$2:$J$501,9,FALSE)) -> Tonya Burch | C19: =PROPER(VLOOKUP(A19,Customer!$A$2:$H$501,3,FALSE)) -> 39 | D19: =PROPER(VLOOKUP(A19,Customer!$A$2:$H$501,4,FALSE)) -> Female | E19: =PROPER(VLOOKUP(A19,Customer!$A$2:$H$501,5,FALSE)) -> Olsonhaven | F19: =PROPER(VLOOKUP(A19,Customer!$A$2:$H$501,6,FALSE)) -> Iowa | G19: =VLOOKUP(A19,Customer!$A$2:$H$501,7,FALSE) -> USA | H19: =PROPER(VLOOKUP(A19,Customer!$A$1:$J$501,10,FALSE)) -> Gold | I19: PROD37 | J19: =VLOOKUP(I19, Product!$A$2:$H$501, 2,FALSE) -> Men's Casual Sneakers | K19: =VLOOKUP(I19,Product!$A$2:$H$501,3,FALSE) -> Clothing | L19: =VLOOKUP(I19, Product!$A$2:$H$501,4,FALSE) -> Footwear | M19: =VLOOKUP(I19, Product!$A$2:$H$501,5,FALSE) -> Hogan-Lee | N19: =VLOOKUP(I19, Product!$A$2:$I$501,8,FALSE) -> 353.47 | O19: =VLOOKUP(I19, Product!$A$2:$I$501,9,FALSE) -> 214 | P19: STORE18 | Q19: =VLOOKUP(P19,Store_Dim!$A$2:$E$21,2,FALSE) -> Guerrero-Schmitt | R19: =VLOOKUP(P19,Store_Dim!$A$2:$E$21,3,FALSE) -> East | S19: =VLOOKUP(P19,Store_Dim!$A$2:$E$21,4,FALSE) -> East Stevechester | T19: =VLOOKUP(P19,Store_Dim!$A$2:$E$21,5,FALSE) -> Flagship | U19: SALE1012 | V19: =VLOOKUP(Table1[[#This Row],[Sales_ID]],Sales!$A$2:$O$2001,2,FALSE) -> 45535 | W19: =VLOOKUP(Table1[[#This Row],[Sales_ID]],Sales!$A$2:$O$2001,12,FALSE) -> 4 | X19: =TEXT(VLOOKUP(Table1[[#This Row],[Sales_ID]],Sales!$A$2:$O$2001,13,FALSE),"₹#,##0") -> ₹86 | Y19: =VLOOKUP(Table1[[#This Row],[Sales_ID]],Sales!$A$2:$O$2001,14,FALSE) -> 0.28 | Z19: =VLOOKUP(Table1[[#This Row],[Sales_ID]],Sales!$A$2:$O$2001,10,FALSE) -> COD | AA19: =VLOOKUP(Table1[[#This Row],[Sales_ID]],Sales!$A$2:$O$2001,15,FALSE) -> 246.5856
A20: CUST1185 | B20: =PROPER(VLOOKUP(A20,Customer!$A$2:$J$501,9,FALSE)) -> Brent Rivas | C20: =PROPER(VLOOKUP(A20,Customer!$A$2:$H$501,3,FALSE)) -> 54 | D20: =PROPER(VLOOKUP(A20,Customer!$A$2:$H$501,4,FALSE)) -> Female | E20: =PROPER(VLOOKUP(A20,Customer!$A$2:$H$501,5,FALSE)) -> North Kellyberg | F20: =PROPER(VLOOKUP(A20,Customer!$A$2:$H$501,6,FALSE)) -> New Jersey | G20: =VLOOKUP(A20,Customer!$A$2:$H$501,7,FALSE) -> USA | H20: =PROPER(VLOOKUP(A20,Customer!$A$1:$J$501,10,FALSE)) -> Platinum | I20: PROD7 | J20: =VLOOKUP(I20, Product!$A$2:$H$501, 2,FALSE) -> LED Table Lamp | K20: =VLOOKUP(I20,Product!$A$2:$H$501,3,FALSE) -> Home | L20: =VLOOKUP(I20, Product!$A$2:$H$501,4,FALSE) -> Lighting | M20: =VLOOKUP(I20, Product!$A$2:$H$501,5,FALSE) -> Harrell LLC | N20: =VLOOKUP(I20, Product!$A$2:$I$501,8,FALSE) -> 218.86 | O20: =VLOOKUP(I20, Product!$A$2:$I$501,9,FALSE) -> 170 | P20: STORE17 | Q20: =VLOOKUP(P20,Store_Dim!$A$2:$E$21,2,FALSE) -> Holloway Ltd | R20: =VLOOKUP(P20,Store_Dim!$A$2:$E$21,3,FALSE) -> North | S20: =VLOOKUP(P20,Store_Dim!$A$2:$E$21,4,FALSE) -> Bensonhaven | T20: =VLOOKUP(P20,Store_Dim!$A$2:$E$21,5,FALSE) -> Flagship | U20: SALE1013 | V20: =VLOOKUP(Table1[[#This Row],[Sales_ID]],Sales!$A$2:$O$2001,2,FALSE) -> 45459 | W20: =VLOOKUP(Table1[[#This Row],[Sales_ID]],Sales!$A$2:$O$2001,12,FALSE) -> 4 | X20: =TEXT(VLOOKUP(Table1[[#This Row],[Sales_ID]],Sales!$A$2:$O$2001,13,FALSE),"₹#,##0") -> ₹929 | Y20: =VLOOKUP(Table1[[#This Row],[Sales_ID]],Sales!$A$2:$O$2001,14,FALSE) -> 0.23 | Z20: =VLOOKUP(Table1[[#This Row],[Sales_ID]],Sales!$A$2:$O$2001,10,FALSE) -> PayPal | AA20: =VLOOKUP(Table1[[#This Row],[Sales_ID]],Sales!$A$2:$O$2001,15,FALSE) -> 2862.1208
A21: CUST1309 | B21: =PROPER(VLOOKUP(A21,Customer!$A$2:$J$501,9,FALSE)) -> Stacy Collins | C21: =PROPER(VLOOKUP(A21,Customer!$A$2:$H$501,3,FALSE)) -> 41 | D21: =PROPER(VLOOKUP(A21,Customer!$A$2:$H$501,4,FALSE)) -> Female | E21: =PROPER(VLOOKUP(A21,Customer!$A$2:$H$501,5,FALSE)) -> Randychester | F21: =PROPER(VLOOKUP(A21,Customer!$A$2:$H$501,6,FALSE)) -> California | G21: =VLOOKUP(A21,Customer!$A$2:$H$501,7,FALSE) -> USA | H21: =PROPER(VLOOKUP(A21,Customer!$A$1:$J$501,10,FALSE)) -> Bronze | I21: PROD60 | J21: =VLOOKUP(I21, Product!$A$2:$H$501, 2,FALSE) -> Luxury Perfume Spray | K21: =VLOOKUP(I21,Product!$A$2:$H$501,3,FALSE) -> Beauty | L21: =VLOOKUP(I21, Product!$A$2:$H$501,4,FALSE) -> Fragrance | M21: =VLOOKUP(I21, Product!$A$2:$H$501,5,FALSE) -> Gibson, Green and Lopez | N21: =VLOOKUP(I21, Product!$A$2:$I$501,8,FALSE) -> 482.75 | O21: =VLOOKUP(I21, Product!$A$2:$I$501,9,FALSE) -> 444 | P21: STORE13 | Q21: =VLOOKUP(P21,Store_Dim!$A$2:$E$21,2,FALSE) -> Gardner, Humphrey and Contreras | R21: =VLOOKUP(P21,Store_Dim!$A$2:$E$21,3,FALSE) -> East | S21: =VLOOKUP(P21,Store_Dim!$A$2:$E$21,4,FALSE) -> Johnsonville | T21: =VLOOKUP(P21,Store_Dim!$A$2:$E$21,5,FALSE) -> Flagship | U21: SALE1014 | V21: =VLOOKUP(Table1[[#This Row],[Sales_ID]],Sales!$A$2:$O$2001,2,FALSE) -> 45681 | W21: =VLOOKUP(Table1[[#This Row],[Sales_ID]],Sales!$A$2:$O$2001,12,FALSE) -> 2 | X21: =TEXT(VLOOKUP(Table1[[#This Row],[Sales_ID]],Sales!$A$2:$O$2001,13,FALSE),"₹#,##0") -> ₹93 | Y21: =VLOOKUP(Table1[[#This Row],[Sales_ID]],Sales!$A$2:$O$2001,14,FALSE) -> 0.14 | Z21: =VLOOKUP(Table1[[#This Row],[Sales_ID]],Sales!$A$2:$O$2001,10,FALSE) -> COD | AA21: =VLOOKUP(Table1[[#This Row],[Sales_ID]],Sales!$A$2:$O$2001,15,FALSE) -> 159.3408
A22: CUST1248 | B22: =PROPER(VLOOKUP(A22,Customer!$A$2:$J$501,9,FALSE)) -> Nicholas Webb | C22: =PROPER(VLOOKUP(A22,Customer!$A$2:$H$501,3,FALSE)) -> 19 | D22: =PROPER(VLOOKUP(A22,Customer!$A$2:$H$501,4,FALSE)) -> Male | E22: =PROPER(VLOOKUP(A22,Customer!$A$2:$H$501,5,FALSE)) -> Lake Timothy | F22: =PROPER(VLOOKUP(A22,Customer!$A$2:$H$501,6,FALSE)) -> Nevada | G22: =VLOOKUP(A22,Customer!$A$2:$H$501,7,FALSE) -> USA | H22: =PROPER(VLOOKUP(A22,Customer!$A$1:$J$501,10,FALSE)) -> Gold | I22: PROD62 | J22: =VLOOKUP(I22, Product!$A$2:$H$501, 2,FALSE) -> Laptop Cooling Pad | K22: =VLOOKUP(I22,Product!$A$2:$H$501,3,FALSE) -> Electronics | L22: =VLOOKUP(I22, Product!$A$2:$H$501,4,FALSE) -> Computer | M22: =VLOOKUP(I22, Product!$A$2:$H$501,5,FALSE) -> Murray, Gould and Ware | N22: =VLOOKUP(I22, Product!$A$2:$I$501,8,FALSE) -> 86.42 | O22: =VLOOKUP(I22, Product!$A$2:$I$501,9,FALSE) -> 222 | P22: STORE4 | Q22: =VLOOKUP(P22,Store_Dim!$A$2:$E$21,2,FALSE) -> Alexander Group | R22: =VLOOKUP(P22,Store_Dim!$A$2:$E$21,3,FALSE) -> South | S22: =VLOOKUP(P22,Store_Dim!$A$2:$E$21,4,FALSE) -> Port Sharon | T22: =VLOOKUP(P22,Store_Dim!$A$2:$E$21,5,FALSE) -> Online | U22: SALE1015 | V22: =VLOOKUP(Table1[[#This Row],[Sales_ID]],Sales!$A$2:$O$2001,2,FALSE) -> 45725 | W22: =VLOOKUP(Table1[[#This Row],[Sales_ID]],Sales!$A$2:$O$2001,12,FALSE) -> 4 | X22: =TEXT(VLOOKUP(Table1[[#This Row],[Sales_ID]],Sales!$A$2:$O$2001,13,FALSE),"₹#,##0") -> ₹139 | Y22: =VLOOKUP(Table1[[#This Row],[Sales_ID]],Sales!$A$2:$O$2001,14,FALSE) -> 0.29 | Z22: =VLOOKUP(Table1[[#This Row],[Sales_ID]],Sales!$A$2:$O$2001,10,FALSE) -> COD | AA22: =VLOOKUP(Table1[[#This Row],[Sales_ID]],Sales!$A$2:$O$2001,15,FALSE) -> 394.902
A23: CUST1140 | B23: =PROPER(VLOOKUP(A23,Customer!$A$2:$J$501,9,FALSE)) -> Patty Francis | C23: =PROPER(VLOOKUP(A23,Customer!$A$2:$H$501,3,FALSE)) -> 63 | D23: =PROPER(VLOOKUP(A23,Customer!$A$2:$H$501,4,FALSE)) -> Female | E23: =PROPER(VLOOKUP(A23,Customer!$A$2:$H$501,5,FALSE)) -> South Brooke | F23: =PROPER(VLOOKUP(A23,Customer!$A$2:$H$501,6,FALSE)) -> Pennsylvania | G23: =VLOOKUP(A23,Customer!$A$2:$H$501,7,FALSE) -> USA | H23: =PROPER(VLOOKUP(A23,Customer!$A$1:$J$501,10,FALSE)) -> Gold | I23: PROD53 | J23: =VLOOKUP(I23, Product!$A$2:$H$501, 2,FALSE) -> Men's Track Pants | K23: =VLOOKUP(I23,Product!$A$2:$H$501,3,FALSE) -> Clothing | L23: =VLOOKUP(I23, Product!$A$2:$H$501,4,FALSE) -> Bottoms | M23: =VLOOKUP(I23, Product!$A$2:$H$501,5,FALSE) -> Hamilton, Woods and Walker | N23: =VLOOKUP(I23, Product!$A$2:$I$501,8,FALSE) -> 386.56 | O23: =VLOOKUP(I23, Product!$A$2:$I$501,9,FALSE) -> 125 | P23: STORE4 | Q23: =VLOOKUP(P23,Store_Dim!$A$2:$E$21,2,FALSE) -> Alexander Group | R23: =VLOOKUP(P23,Store_Dim!$A$2:$E$21,3,FALSE) -> South | S23: =VLOOKUP(P23,Store_Dim!$A$2:$E$21,4,FALSE) -> Port Sharon | T23: =VLOOKUP(P23,Store_Dim!$A$2:$E$21,5,FALSE) -> Online | U23: SALE1016 | V23: =VLOOKUP(Table1[[#This Row],[Sales_ID]],Sales!$A$2:$O$2001,2,FALSE) -> 45461 | W23: =VLOOKUP(Table1[[#This Row],[Sales_ID]],Sales!$A$2:$O$2001,12,FALSE) -> 3 | X23: =TEXT(VLOOKUP(Table1[[#This Row],[Sales_ID]],Sales!$A$2:$O$2001,13,FALSE),"₹#,##0") -> ₹156 | Y23: =VLOOKUP(Table1[[#This Row],[Sales_ID]],Sales!$A$2:$O$2001,14,FALSE) -> 0.03 | Z23: =VLOOKUP(Table1[[#This Row],[Sales_ID]],Sales!$A$2:$O$2001,10,FALSE) -> COD | AA23: =VLOOKUP(Table1[[#This Row],[Sales_ID]],Sales!$A$2:$O$2001,15,FALSE) -> 453.5817
A24: CUST1442 | B24: =PROPER(VLOOKUP(A24,Customer!$A$2:$J$501,9,FALSE)) -> Kelli Smith | C24: =PROPER(VLOOKUP(A24,Customer!$A$2:$H$501,3,FALSE)) -> 42 | D24: =PROPER(VLOOKUP(A24,Customer!$A$2:$H$501,4,FALSE)) -> Female | E24: =PROPER(VLOOKUP(A24,Customer!$A$2:$H$501,5,FALSE)) -> North Maryfort | F24: =PROPER(VLOOKUP(A24,Customer!$A$2:$H$501,6,FALSE)) -> Oregon | G24: =VLOOKUP(A24,Customer!$A$2:$H$501,7,FALSE) -> USA | H24: =PROPER(VLOOKUP(A24,Customer!$A$1:$J$501,10,FALSE)) -> Bronze | I24: PROD34 | J24: =VLOOKUP(I24, Product!$A$2:$H$501, 2,FALSE) -> Gaming Mechanical Keyboard | K24: =VLOOKUP(I24,Product!$A$2:$H$501,3,FALSE) -> Electronics | L24: =VLOOKUP(I24, Product!$A$2:$H$501,4,FALSE) -> Computer | M24: =VLOOKUP(I24, Product!$A$2:$H$501,5,FALSE) -> Lucero LLC | N24: =VLOOKUP(I24, Product!$A$2:$I$501,8,FALSE) -> 419.28 | O24: =VLOOKUP(I24, Product!$A$2:$I$501,9,FALSE) -> 86 | P24: STORE16 | Q24: =VLOOKUP(P24,Store_Dim!$A$2:$E$21,2,FALSE) -> Frederick-Wright | R24: =VLOOKUP(P24,Store_Dim!$A$2:$E$21,3,FALSE) -> West | S24: =VLOOKUP(P24,Store_Dim!$A$2:$E$21,4,FALSE) -> New Jimmymouth | T24: =VLOOKUP(P24,Store_Dim!$A$2:$E$21,5,FALSE) -> Flagship | U24: SALE1017 | V24: =VLOOKUP(Table1[[#This Row],[Sales_ID]],Sales!$A$2:$O$2001,2,FALSE) -> 45837 | W24: =VLOOKUP(Table1[[#This Row],[Sales_ID]],Sales!$A$2:$O$2001,12,FALSE) -> 4 | X24: =TEXT(VLOOKUP(Table1[[#This Row],[Sales_ID]],Sales!$A$2:$O$2001,13,FALSE),"₹#,##0") -> ₹115 | Y24: =VLOOKUP(Table1[[#This Row],[Sales_ID]],Sales!$A$2:$O$2001,14,FALSE) -> 0.03 | Z24: =VLOOKUP(Table1[[#This Row],[Sales_ID]],Sales!$A$2:$O$2001,10,FALSE) -> COD | AA24: =VLOOKUP(Table1[[#This Row],[Sales_ID]],Sales!$A$2:$O$2001,15,FALSE) -> 447.8296
A25: CUST1122 | B25: =PROPER(VLOOKUP(A25,Customer!$A$2:$J$501,9,FALSE)) -> Michael Chang | C25: =PROPER(VLOOKUP(A25,Customer!$A$2:$H$501,3,FALSE)) -> 50 | D25: =PROPER(VLOOKUP(A25,Customer!$A$2:$H$501,4,FALSE)) -> Male | E25: =PROPER(VLOOKUP(A25,Customer!$A$2:$H$501,5,FALSE)) -> Kathrynport | F25: =PROPER(VLOOKUP(A25,Customer!$A$2:$H$501,6,FALSE)) -> North Carolina | G25: =VLOOKUP(A25,Customer!$A$2:$H$501,7,FALSE) -> USA | H25: =PROPER(VLOOKUP(A25,Customer!$A$1:$J$501,10,FALSE)) -> Platinum | I25: PROD52 | J25: =VLOOKUP(I25, Product!$A$2:$H$501, 2,FALSE) -> Rugby Ball | K25: =VLOOKUP(I25,Product!$A$2:$H$501,3,FALSE) -> Sports | L25: =VLOOKUP(I25, Product!$A$2:$H$501,4,FALSE) -> Team Sports | M25: =VLOOKUP(I25, Product!$A$2:$H$501,5,FALSE) -> Harris Inc | N25: =VLOOKUP(I25, Product!$A$2:$I$501,8,FALSE) -> 212.26 | O25: =VLOOKUP(I25, Product!$A$2:$I$501,9,FALSE) -> 82 | P25: STORE6 | Q25: =VLOOKUP(P25,Store_Dim!$A$2:$E$21,2,FALSE) -> Benson-Elliott | R25: =VLOOKUP(P25,Store_Dim!$A$2:$E$21,3,FALSE) -> East | S25: =VLOOKUP(P25,Store_Dim!$A$2:$E$21,4,FALSE) -> Port Josephberg | T25: =VLOOKUP(P25,Store_Dim!$A$2:$E$21,5,FALSE) -> Online | U25: SALE1018 | V25: =VLOOKUP(Table1[[#This Row],[Sales_ID]],Sales!$A$2:$O$2001,2,FALSE) -> 45823 | W25: =VLOOKUP(Table1[[#This Row],[Sales_ID]],Sales!$A$2:$O$2001,12,FALSE) -> 3 | X25: =TEXT(VLOOKUP(Table1[[#This Row],[Sales_ID]],Sales!$A$2:$O$2001,13,FALSE),"₹#,##0") -> ₹594 | Y25: =VLOOKUP(Table1[[#This Row],[Sales_ID]],Sales!$A$2:$O$2001,14,FALSE) -> 0.08 | Z25: =VLOOKUP(Table1[[#This Row],[Sales_ID]],Sales!$A$2:$O$2001,10,FALSE) -> Credit Card | AA25: =VLOOKUP(Table1[[#This Row],[Sales_ID]],Sales!$A$2:$O$2001,15,FALSE) -> 1638.3912
A26: CUST1353 | B26: =PROPER(VLOOKUP(A26,Customer!$A$2:$J$501,9,FALSE)) -> Laura Green | C26: =PROPER(VLOOKUP(A26,Customer!$A$2:$H$501,3,FALSE)) -> 56 | D26: =PROPER(VLOOKUP(A26,Customer!$A$2:$H$501,4,FALSE)) -> Female | E26: =PROPER(VLOOKUP(A26,Customer!$A$2:$H$501,5,FALSE)) -> Westbury | F26: =PROPER(VLOOKUP(A26,Customer!$A$2:$H$501,6,FALSE)) -> Oregon | G26: =VLOOKUP(A26,Customer!$A$2:$H$501,7,FALSE) -> USA | H26: =PROPER(VLOOKUP(A26,Customer!$A$1:$J$501,10,FALSE)) -> Platinum | I26: PROD45 | J26: =VLOOKUP(I26, Product!$A$2:$H$501, 2,FALSE) -> High-Grip Football | K26: =VLOOKUP(I26,Product!$A$2:$H$501,3,FALSE) -> Sports | L26: =VLOOKUP(I26, Product!$A$2:$H$501,4,FALSE) -> Team Sports | M26: =VLOOKUP(I26, Product!$A$2:$H$501,5,FALSE) -> Bridges, Banks and Cummings | N26: =VLOOKUP(I26, Product!$A$2:$I$501,8,FALSE) -> 318.91 | O26: =VLOOKUP(I26, Product!$A$2:$I$501,9,FALSE) -> 114 | P26: STORE4 | Q26: =VLOOKUP(P26,Store_Dim!$A$2:$E$21,2,FALSE) -> Alexander Group | R26: =VLOOKUP(P26,Store_Dim!$A$2:$E$21,3,FALSE) -> South | S26: =VLOOKUP(P26,Store_Dim!$A$2:$E$21,4,FALSE) -> Port Sharon | T26: =VLOOKUP(P26,Store_Dim!$A$2:$E$21,5,FALSE) -> Online | U26: SALE1019 | V26: =VLOOKUP(Table1[[#This Row],[Sales_ID]],Sales!$A$2:$O$2001,2,FALSE) -> 45733 | W26: =VLOOKUP(Table1[[#This Row],[Sales_ID]],Sales!$A$2:$O$2001,12,FALSE) -> 2 | X26: =TEXT(VLOOKUP(Table1[[#This Row],[Sales_ID]],Sales!$A$2:$O$2001,13,FALSE),"₹#,##0") -> ₹825 | Y26: =VLOOKUP(Table1[[#This Row],[Sales_ID]],Sales!$A$2:$O$2001,14,FALSE) -> 0.2 | Z26: =VLOOKUP(Table1[[#This Row],[Sales_ID]],Sales!$A$2:$O$2001,10,FALSE) -> Credit Card | AA26: =VLOOKUP(Table1[[#This Row],[Sales_ID]],Sales!$A$2:$O$2001,15,FALSE) -> 1320.064
A27: CUST1097 | B27: =PROPER(VLOOKUP(A27,Customer!$A$2:$J$501,9,FALSE)) -> David Cobb | C27: =PROPER(VLOOKUP(A27,Customer!$A$2:$H$501,3,FALSE)) -> 36 | D27: =PROPER(VLOOKUP(A27,Customer!$A$2:$H$501,4,FALSE)) -> Male | E27: =PROPER(VLOOKUP(A27,Customer!$A$2:$H$501,5,FALSE)) -> Lake Thomas | F27: =PROPER(VLOOKUP(A27,Customer!$A$2:$H$501,6,FALSE)) -> South Dakota | G27: =VLOOKUP(A27,Customer!$A$2:$H$501,7,FALSE) -> USA | H27: =PROPER(VLOOKUP(A27,Customer!$A$1:$J$501,10,FALSE)) -> Silver | I27: PROD80 | J27: =VLOOKUP(I27, Product!$A$2:$H$501, 2,FALSE) -> Wall-Mounted Spice Rack | K27: =VLOOKUP(I27,Product!$A$2:$H$501,3,FALSE) -> Home | L27: =VLOOKUP(I27, Product!$A$2:$H$501,4,FALSE) -> Kitchen | M27: =VLOOKUP(I27, Product!$A$2:$H$501,5,FALSE) -> Allison Ltd | N27: =VLOOKUP(I27, Product!$A$2:$I$501,8,FALSE) -> 143.43 | O27: =VLOOKUP(I27, Product!$A$2:$I$501,9,FALSE) -> 58 | P27: STORE12 | Q27: =VLOOKUP(P27,Store_Dim!$A$2:$E$21,2,FALSE) -> Thomas, Bridges and Harris | R27: =VLOOKUP(P27,Store_Dim!$A$2:$E$21,3,FALSE) -> North | S27: =VLOOKUP(P27,Store_Dim!$A$2:$E$21,4,FALSE) -> Sabrinatown | T27: =VLOOKUP(P27,Store_Dim!$A$2:$E$21,5,FALSE) -> Online | U27: SALE102 | V27: =VLOOKUP(Table1[[#This Row],[Sales_ID]],Sales!$A$2:$O$2001,2,FALSE) -> 45552 | W27: =VLOOKUP(Table1[[#This Row],[Sales_ID]],Sales!$A$2:$O$2001,12,FALSE) -> 2 | X27: =TEXT(VLOOKUP(Table1[[#This Row],[Sales_ID]],Sales!$A$2:$O$2001,13,FALSE),"₹#,##0") -> ₹472 | Y27: =VLOOKUP(Table1[[#This Row],[Sales_ID]],Sales!$A$2:$O$2001,14,FALSE) -> 0.24 | Z27: =VLOOKUP(Table1[[#This Row],[Sales_ID]],Sales!$A$2:$O$2001,10,FALSE) -> PayPal | AA27: =VLOOKUP(Table1[[#This Row],[Sales_ID]],Sales!$A$2:$O$2001,15,FALSE) -> 717.2576
A28: CUST1464 | B28: =PROPER(VLOOKUP(A28,Customer!$A$2:$J$501,9,FALSE)) -> David Pierce | C28: =PROPER(VLOOKUP(A28,Customer!$A$2:$H$501,3,FALSE)) -> 45 | D28: =PROPER(VLOOKUP(A28,Customer!$A$2:$H$501,4,FALSE)) -> Female | E28: =PROPER(VLOOKUP(A28,Customer!$A$2:$H$501,5,FALSE)) -> Grayland | F28: =PROPER(VLOOKUP(A28,Customer!$A$2:$H$501,6,FALSE)) -> Washington | G28: =VLOOKUP(A28,Customer!$A$2:$H$501,7,FALSE) -> USA | H28: =PROPER(VLOOKUP(A28,Customer!$A$1:$J$501,10,FALSE)) -> Platinum | I28: PROD25 | J28: =VLOOKUP(I28, Product!$A$2:$H$501, 2,FALSE) -> Women's Scarf Set | K28: =VLOOKUP(I28,Product!$A$2:$H$501,3,FALSE) -> Clothing | L28: =VLOOKUP(I28, Product!$A$2:$H$501,4,FALSE) -> Accessories | M28: =VLOOKUP(I28, Product!$A$2:$H$501,5,FALSE) -> Brown and Sons | N28: =VLOOKUP(I28, Product!$A$2:$I$501,8,FALSE) -> 174.02 | O28: =VLOOKUP(I28, Product!$A$2:$I$501,9,FALSE) -> 268 | P28: STORE13 | Q28: =VLOOKUP(P28,Store_Dim!$A$2:$E$21,2,FALSE) -> Gardner, Humphrey and Contreras | R28: =VLOOKUP(P28,Store_Dim!$A$2:$E$21,3,FALSE) -> East | S28: =VLOOKUP(P28,Store_Dim!$A$2:$E$21,4,FALSE) -> Johnsonville | T28: =VLOOKUP(P28,Store_Dim!$A$2:$E$21,5,FALSE) -> Flagship | U28: SALE1020 | V28: =VLOOKUP(Table1[[#This Row],[Sales_ID]],Sales!$A$2:$O$2001,2,FALSE) -> 45322 | W28: =VLOOKUP(Table1[[#This Row],[Sales_ID]],Sales!$A$2:$O$2001,12,FALSE) -> 1 | X28: =TEXT(VLOOKUP(Table1[[#This Row],[Sales_ID]],Sales!$A$2:$O$2001,13,FALSE),"₹#,##0") -> ₹964 | Y28: =VLOOKUP(Table1[[#This Row],[Sales_ID]],Sales!$A$2:$O$2001,14,FALSE) -> 0.14 | Z28: =VLOOKUP(Table1[[#This Row],[Sales_ID]],Sales!$A$2:$O$2001,10,FALSE) -> PayPal | AA28: =VLOOKUP(Table1[[#This Row],[Sales_ID]],Sales!$A$2:$O$2001,15,FALSE) -> 828.8336
A29: CUST1292 | B29: =PROPER(VLOOKUP(A29,Customer!$A$2:$J$501,9,FALSE)) -> Ricardo Jones | C29: =PROPER(VLOOKUP(A29,Customer!$A$2:$H$501,3,FALSE)) -> 30 | D29: =PROPER(VLOOKUP(A29,Customer!$A$2:$H$501,4,FALSE)) -> Male | E29: =PROPER(VLOOKUP(A29,Customer!$A$2:$H$501,5,FALSE)) -> Danielland | F29: =PROPER(VLOOKUP(A29,Customer!$A$2:$H$501,6,FALSE)) -> Minnesota | G29: =VLOOKUP(A29,Customer!$A$2:$H$501,7,FALSE) -> USA | H29: =PROPER(VLOOKUP(A29,Customer!$A$1:$J$501,10,FALSE)) -> Silver | I29: PROD55 | J29: =VLOOKUP(I29, Product!$A$2:$H$501, 2,FALSE) -> Ceramic Plant Pot | K29: =VLOOKUP(I29,Product!$A$2:$H$501,3,FALSE) -> Home | L29: =VLOOKUP(I29, Product!$A$2:$H$501,4,FALSE) -> Decor | M29: =VLOOKUP(I29, Product!$A$2:$H$501,5,FALSE) -> Hatfield, Baird and Torres | N29: =VLOOKUP(I29, Product!$A$2:$I$501,8,FALSE) -> 81.75 | O29: =VLOOKUP(I29, Product!$A$2:$I$501,9,FALSE) -> 226.05 | P29: STORE6 | Q29: =VLOOKUP(P29,Store_Dim!$A$2:$E$21,2,FALSE) -> Benson-Elliott | R29: =VLOOKUP(P29,Store_Dim!$A$2:$E$21,3,FALSE) -> East | S29: =VLOOKUP(P29,Store_Dim!$A$2:$E$21,4,FALSE) -> Port Josephberg | T29: =VLOOKUP(P29,Store_Dim!$A$2:$E$21,5,FALSE) -> Online | U29: SALE1021 | V29: =VLOOKUP(Table1[[#This Row],[Sales_ID]],Sales!$A$2:$O$2001,2,FALSE) -> 45415 | W29: =VLOOKUP(Table1[[#This Row],[Sales_ID]],Sales!$A$2:$O$2001,12,FALSE) -> 1 | X29: =TEXT(VLOOKUP(Table1[[#This Row],[Sales_ID]],Sales!$A$2:$O$2001,13,FALSE),"₹#,##0") -> ₹238 | Y29: =VLOOKUP(Table1[[#This Row],[Sales_ID]],Sales!$A$2:$O$2001,14,FALSE) -> 0.12 | Z29: =VLOOKUP(Table1[[#This Row],[Sales_ID]],Sales!$A$2:$O$2001,10,FALSE) -> PayPal | AA29: =VLOOKUP(Table1[[#This Row],[Sales_ID]],Sales!$A$2:$O$2001,15,FALSE) -> 209.6512
A30: CUST1457 | B30: =PROPER(VLOOKUP(A30,Customer!$A$2:$J$501,9,FALSE)) -> Christina Robertson | C30: =PROPER(VLOOKUP(A30,Customer!$A$2:$H$501,3,FALSE)) -> 59 | D30: =PROPER(VLOOKUP(A30,Customer!$A$2:$H$501,4,FALSE)) -> Male | E30: =PROPER(VLOOKUP(A30,Customer!$A$2:$H$501,5,FALSE)) -> Hubbardborough | F30: =PROPER(VLOOKUP(A30,Customer!$A$2:$H$501,6,FALSE)) -> Kentucky | G30: =VLOOKUP(A30,Customer!$A$2:$H$501,7,FALSE) -> USA | H30: =PROPER(VLOOKUP(A30,Customer!$A$1:$J$501,10,FALSE)) -> Platinum | I30: PROD82 | J30: =VLOOKUP(I30, Product!$A$2:$H$501, 2,FALSE) -> Fitness Resistance Bands | K30: =VLOOKUP(I30,Product!$A$2:$H$501,3,FALSE) -> Sports | L30: =VLOOKUP(I30, Product!$A$2:$H$501, 4,FALSE) -> Fitness | M30: =VLOOKUP(I30, Product!$A$2:$H$501,5,FALSE) -> Reese-Watson | N30: =VLOOKUP(I30, Product!$A$2:$I$501,8,FALSE) -> 152.92 | O30: =VLOOKUP(I30, Product!$A$2:$I$501,9,FALSE) -> 281 | P30: STORE16 | Q30: =VLOOKUP(P30,Store_Dim!$A$2:$E$21,2,FALSE) -> Frederick-Wright | R30: =VLOOKUP(P30,Store_Dim!$A$2:$E$21,3,FALSE) -> West | S30: =VLOOKUP(P30,Store_Dim!$A$2:$E$21,4,FALSE) -> New Jimmymouth | T30: =VLOOKUP(P30,Store_Dim!$A$2:$E$21,5,FALSE) -> Flagship | U30: SALE1022 | V30: =VLOOKUP(Table1[[#This Row],[Sales_ID]],Sales!$A$2:$O$2001,2,FALSE) -> 45644 | W30: =VLOOKUP(Table1[[#This Row],[Sales_ID]],Sales!$A$2:$O$2001,12,FALSE) -> 1 | X30: =TEXT(VLOOKUP(Table1[[#This Row],[Sales_ID]],Sales!$A$2:$O$2001,13,FALSE),"₹#,##0") -> ₹757 | Y30: =VLOOKUP(Table1[[#This Row],[Sales_ID]],Sales!$A$2:$O$2001,14,FALSE) -> 0.04 | Z30: =VLOOKUP(Table1[[#This Row],[Sales_ID]],Sales!$A$2:$O$2001,10,FALSE) -> PayPal | AA30: =VLOOKUP(Table1[[#This Row],[Sales_ID]],Sales!$A$2:$O$2001,15,FALSE) -> 726.3648
A31: CUST1019 | B31: =PROPER(VLOOKUP(A31,Customer!$A$2:$J$501,9,FALSE)) -> Michael Torres | C31: =PROPER(VLOOKUP(A31,Customer!$A$2:$H$501,3,FALSE)) -> 46 | D31: =PROPER(VLOOKUP(A31,Customer!$A$2:$H$501,4,FALSE)) -> Female | E31: =PROPER(VLOOKUP(A31,Customer!$A$2:$H$501,5,FALSE)) -> Gonzalezfort | F31: =PROPER(VLOOKUP(A31,Customer!$A$2:$H$501,6,FALSE)) -> New Jersey | G31: =VLOOKUP(A31,Customer!$A$2:$H$501,7,FALSE) -> USA | H31: =PROPER(VLOOKUP(A31,Customer!$A$1:$J$501,10,FALSE)) -> Platinum | I31: PROD93 | J31: =VLOOKUP(I31, Product!$A$2:$H$501, 2,FALSE) -> USB-C Laptop Charger | K31: =VLOOKUP(I31,Product!$A$2:$H$501,3,FALSE) -> Electronics | L31: =VLOOKUP(I31, Product!$A$2:$H$501, 4,FALSE) -> Computer | M31: =VLOOKUP(I31, Product!$A$2:$H$501,5,FALSE) -> Martin LLC | N31: =VLOOKUP(I31, Product!$A$2:$I$501,8,FALSE) -> 377.52 | O31: =VLOOKUP(I31, Product!$A$2:$I$501,9,FALSE) -> 485 | P31: STORE7 | Q31: =VLOOKUP(P31,Store_Dim!$A$2:$E$21,2,FALSE) -> Martinez-Mullins | R31: =VLOOKUP(P31,Store_Dim!$A$2:$E$21,3,FALSE) -> South | S31: =VLOOKUP(P31,Store_Dim!$A$2:$E$21,4,FALSE) -> Williamsfurt | T31: =VLOOKUP(P31,Store_Dim!$A$2:$E$21,5,FALSE) -> Online | U31: SALE1023 | V31: =VLOOKUP(Table1[[#This Row],[Sales_ID]],Sales!$A$2:$O$2001,2,FALSE) -> 45845 | W31: =VLOOKUP(Table1[[#This Row],[Sales_ID]],Sales!$A$2:$O$2001,12,FALSE) -> 3 | X31: =TEXT(VLOOKUP(Table1[[#This Row],[Sales_ID]],Sales!$A$2:$O$2001,13,FALSE),"₹#,##0") -> ₹160 | Y31: =VLOOKUP(Table1[[#This Row],[Sales_ID]],Sales!$A$2:$O$2001,14,FALSE) -> 0.22 | Z31: =VLOOKUP(Table1[[#This Row],[Sales_ID]],Sales!$A$2:$O$2001,10,FALSE) -> Credit Card | AA31: =VLOOKUP(Table1[[#This Row],[Sales_ID]],Sales!$A$2:$O$2001,15,FALSE) -> 373.8384
A32: CUST1368 | B32: =PROPER(VLOOKUP(A32,Customer!$A$2:$J$501,9,FALSE)) -> Miranda King | C32: =PROPER(VLOOKUP(A32,Customer!$A$2:$H$501,3,FALSE)) -> 34 | D32: =PROPER(VLOOKUP(A32,Customer!$A$2:$H$501,4,FALSE)) -> Female | E32: =PROPER(VLOOKUP(A32,Customer!$A$2:$H$501,5,FALSE)) -> West Mathew | F32: =PROPER(VLOOKUP(A32,Customer!$A$2:$H$501,6,FALSE)) -> New York | G32: =VLOOKUP(A32,Customer!$A$2:$H$501,7,FALSE) -> USA | H32: =PROPER(VLOOKUP(A32,Customer!$A$1:$J$501,10,FALSE)) -> Platinum | I32: PROD95 | J32: =VLOOKUP(I32, Product!$A$2:$H$501, 2,FALSE) -> Sports Stopwatch Basic | K32: =VLOOKUP(I32,Product!$A$2:$H$501,3,FALSE) -> Sports | L32: =VLOOKUP(I32, Product!$A$2:$H$501, 4,FALSE) -> Accessories | M32: =VLOOKUP(I32, Product!$A$2:$H$501,5,FALSE) -> Wilson Group | N32: =VLOOKUP(I32, Product!$A$2:$I$501,8,FALSE) -> 60.65 | O32: =VLOOKUP(I32, Product!$A$2:$I$501,9,FALSE) -> 75 | P32: STORE8 | Q32: =VLOOKUP(P32,Store_Dim!$A$2:$E$21,2,FALSE) -> Bean, Jones and Park | R32: =VLOOKUP(P32,Store_Dim!$A$2:$E$21,3,FALSE) -> West | S32: =VLOOKUP(P32,Store_Dim!$A$2:$E$21,4,FALSE) -> Thompsonborough | T32: =VLOOKUP(P32,Store_Dim!$A$2:$E$21,5,FALSE) -> Online | U32: SALE1024 | V32: =VLOOKUP(Table1[[#This Row],[Sales_ID]],Sales!$A$2:$O$2001,2,FALSE) -> 45354 | W32: =VLOOKUP(Table1[[#This Row],[Sales_ID]],Sales!$A$2:$O$2001,12,FALSE) -> 1 | X32: =TEXT(VLOOKUP(Table1[[#This Row],[Sales_ID]],Sales!$A$2:$O$2001,13,FALSE),"₹#,##0") -> ₹330 | Y32: =VLOOKUP(Table1[[#This Row],[Sales_ID]],Sales!$A$2:$O$2001,14,FALSE) -> 0.14 | Z32: =VLOOKUP(Table1[[#This Row],[Sales_ID]],Sales!$A$2:$O$2001,10,FALSE) -> COD | AA32: =VLOOKUP(Table1[[#This Row],[Sales_ID]],Sales!$A$2:$O$2001,15,FALSE) -> 283.7484
A33: CUST1060 | B33: =PROPER(VLOOKUP(A33,Customer!$A$2:$J$501,9,FALSE)) -> Dr. David Smith | C33: =PROPER(VLOOKUP(A33,Customer!$A$2:$H$501,3,FALSE)) -> 22 | D33: =PROPER(VLOOKUP(A33,Customer!$A$2:$H$501,4,FALSE)) -> Female | E33: =PROPER(VLOOKUP(A33,Customer!$A$2:$H$501,5,FALSE)) -> Schmidtchester | F33: =PROPER(VLOOKUP(A33,Customer!$A$2:$H$501,6,FALSE)) -> Alaska | G33: =VLOOKUP(A33,Customer!$A$2:$H$501,7,FALSE) -> USA | H33: =PROPER(VLOOKUP(A33,Customer!$A$1:$J$501,10,FALSE)) -> Silver | I33: PROD17 | J33: =VLOOKUP(I33, Product!$A$2:$H$501, 2,FALSE) -> Soccer Training Cone Set | K33: =VLOOKUP(I33,Product!$A$2:$H$501,3,FALSE) -> Sports | L33: =VLOOKUP(I33, Product!$A$2:$H$501, 4,FALSE) -> Accessories | M33: =VLOOKUP(I33, Product!$A$2:$H$501,5,FALSE) -> Ford, Murphy and Wilson | N33: =VLOOKUP(I33, Product!$A$2:$I$501,8,FALSE) -> 144.53 | O33: =VLOOKUP(I33, Product!$A$2:$I$501,9,FALSE) -> 367 | P33: STORE8 | Q33: =VLOOKUP(P33,Store_Dim!$A$2:$E$21,2,FALSE) -> Bean, Jones and Park | R33: =VLOOKUP(P33,Store_Dim!$A$2:$E$21,3,FALSE) -> West | S33: =VLOOKUP(P33,Store_Dim!$A$2:$E$21,4,FALSE) -> Thompsonborough | T33: =VLOOKUP(P33,Store_Dim!$A$2:$E$21,5,FALSE) -> Online | U33: SALE1025 | V33: =VLOOKUP(Table1[[#This Row],[Sales_ID]],Sales!$A$2:$O$2001,2,FALSE) -> 45720 | W33: =VLOOKUP(Table1[[#This Row],[Sales_ID]],Sales!$A$2:$O$2001,12,FALSE) -> 1 | X33: =TEXT(VLOOKUP(Table1[[#This Row],[Sales_ID]],Sales!$A$2:$O$2001,13,FALSE),"₹#,##0") -> ₹234 | Y33: =VLOOKUP(Table1[[#This Row],[Sales_ID]],Sales!$A$2:$O$2001,14,FALSE) -> 0.11 | Z33: =VLOOKUP(Table1[[#This Row],[Sales_ID]],Sales!$A$2:$O$2001,10,FALSE) -> PayPal | AA33: =VLOOKUP(Table1[[#This Row],[Sales_ID]],Sales!$A$2:$O$2001,15,FALSE) -> 208.3134
A34: CUST1317 | B34: =PROPER(VLOOKUP(A34,Customer!$A$2:$J$501,9,FALSE)) -> Tiffany Williams | C34: =PROPER(VLOOKUP(A34,Customer!$A$2:$H$501,3,FALSE)) -> 64 | D34: =PROPER(VLOOKUP(A34,Customer!$A$2:$H$501,4,FALSE)) -> Female | E34: =PROPER(VLOOKUP(A34,Customer!$A$2:$H$501,5,FALSE)) -> Richardsport | F34: =PROPER(VLOOKUP(A34,Customer!$A$2:$H$501,6,FALSE)) -> New Hampshire | G34: =VLOOKUP(A34,Customer!$A$2:$H$501,7,FALSE) -> USA | H34: =PROPER(VLOOKUP(A34,Customer!$A$1:$J$501,10,FALSE)) -> Gold | I34: PROD81 | J34: =VLOOKUP(I34, Product!$A$2:$H$501, 2,FALSE) -> Badminton Racket Set | K34: =VLOOKUP(I34,Product!$A$2:$H$501,3,FALSE) -> Sports | L34: =VLOOKUP(I34, Product!$A$2:$H$501, 4,FALSE) -> Equipment | M34: =VLOOKUP(I34, Product!$A$2:$H$501,5,FALSE) -> Robinson-Brown | N34: =VLOOKUP(I34, Product!$A$2:$I$501,8,FALSE) -> 285.54 | O34: =VLOOKUP(I34, Product!$A$2:$I$501,9,FALSE) -> 358 | P34: STORE0 | Q34: =VLOOKUP(P34,Store_Dim!$A$2:$E$21,2,FALSE) -> Rivera-Warner | R34: =VLOOKUP(P34,Store_Dim!$A$2:$E$21,3,FALSE) -> East | S34: =VLOOKUP(P34,Store_Dim!$A$2:$E$21,4,FALSE) -> Washingtonfurt | T34: =VLOOKUP(P34,Store_Dim!$A$2:$E$21,5,FALSE) -> Flagship | U34: SALE1026 | V34: =VLOOKUP(Table1[[#This Row],[Sales_ID]],Sales!$A$2:$O$2001,2,FALSE) -> 45278 | W34: =VLOOKUP(Table1[[#This Row],[Sales_ID]],Sales!$A$2:$O$2001,12,FALSE) -> 2 | X34: =TEXT(VLOOKUP(Table1[[#This Row],[Sales_ID]],Sales!$A$2:$O$2001,13,FALSE),"₹#,##0") -> ₹774 | Y34: =VLOOKUP(Table1[[#This Row],[Sales_ID]],Sales!$A$2:$O$2001,14,FALSE) -> 0.16 | Z34: =VLOOKUP(Table1[[#This Row],[Sales_ID]],Sales!$A$2:$O$2001,10,FALSE) -> PayPal | AA34: =VLOOKUP(Table1[[#This Row],[Sales_ID]],Sales!$A$2:$O$2001,15,FALSE) -> 1299.9
A35: CUST1436 | B35: =PROPER(VLOOKUP(A35,Customer!$A$2:$J$501,9,FALSE)) -> Sharon Simpson | C35: =PROPER(VLOOKUP(A35,Customer!$A$2:$H$501,3,FALSE)) -> 61 | D35: =PROPER(VLOOKUP(A35,Customer!$A$2:$H$501,4,FALSE)) -> Male | E35: =PROPER(VLOOKUP(A35,Customer!$A$2:$H$501,5,FALSE)) -> South Michellebury | F35: =PROPER(VLOOKUP(A35,Customer!$A$2:$H$501,6,FALSE)) -> South Dakota | G35: =VLOOKUP(A35,Customer!$A$2:$H$501,7,FALSE) -> USA | H35: =PROPER(VLOOKUP(A35,Customer!$A$1:$J$501,10,FALSE)) -> Gold | I35: PROD52 | J35: =VLOOKUP(I35, Product!$A$2:$H$501, 2,FALSE) -> Rugby Ball | K35: =VLOOKUP(I35,Product!$A$2:$H$501,3,FALSE) -> Sports | L35: =VLOOKUP(I35, Product!$A$2:$H$501, 4,FALSE) -> Team Sports | M35: =VLOOKUP(I35, Product!$A$2:$H$501,5,FALSE) -> Harris Inc | N35: =VLOOKUP(I35, Product!$A$2:$I$501,8,FALSE) -> 212.26 | O35: =VLOOKUP(I35, Product!$A$2:$I$501,9,FALSE) -> 82 | P35: STORE18 | Q35: =VLOOKUP(P35,Store_Dim!$A$2:$E$21,2,FALSE) -> Guerrero-Schmitt | R35: =VLOOKUP(P35,Store_Dim!$A$2:$E$21,3,FALSE) -> East | S35: =VLOOKUP(P35,Store_Dim!$A$2:$E$21,4,FALSE) -> East Stevechester | T35: =VLOOKUP(P35,Store_Dim!$A$2:$E$21,5,FALSE) -> Flagship | U35: SALE1027 | V35: =VLOOKUP(Table1[[#This Row],[Sales_ID]],Sales!$A$2:$O$2001,2,FALSE) -> 45422 | W35: =VLOOKUP(Table1[[#This Row],[Sales_ID]],Sales!$A$2:$O$2001,12,FALSE) -> 1 | X35: =TEXT(VLOOKUP(Table1[[#This Row],[Sales_ID]],Sales!$A$2:$O$2001,13,FALSE),"₹#,##0") -> ₹74 | Y35: =VLOOKUP(Table1[[#This Row],[Sales_ID]],Sales!$A$2:$O$2001,14,FALSE) -> 0.04 | Z35: =VLOOKUP(Table1[[#This Row],[Sales_ID]],Sales!$A$2:$O$2001,10,FALSE) -> Credit Card | AA35: =VLOOKUP(Table1[[#This Row],[Sales_ID]],Sales!$A$2:$O$2001,15,FALSE) -> 70.9248
A36: CUST1005 | B36: =PROPER(VLOOKUP(A36,Customer!$A$2:$J$501,9,FALSE)) -> Christine Vaughn | C36: =PROPER(VLOOKUP(A36,Customer!$A$2:$H$501,3,FALSE)) -> 24 | D36: =PROPER(VLOOKUP(A36,Customer!$A$2:$H$501,4,FALSE)) -> Male | E36: =PROPER(VLOOKUP(A36,Customer!$A$2:$H$501,5,FALSE)) -> East Amandamouth | F36: =PROPER(VLOOKUP(A36,Customer!$A$2:$H$501,6,FALSE)) -> Oregon | G36: =VLOOKUP(A36,Customer!$A$2:$H$501,7,FALSE) -> USA | H36: =PROPER(VLOOKUP(A36,Customer!$A$1:$J$501,10,FALSE)) -> Bronze | I36: PROD86 | J36: =VLOOKUP(I36, Product!$A$2:$H$501, 2,FALSE) -> Kitchen Cutting Board | K36: =VLOOKUP(I36,Product!$A$2:$H$501,3,FALSE) -> Home | L36: =VLOOKUP(I36, Product!$A$2:$H$501, 4,FALSE) -> Kitchen | M36: =VLOOKUP(I36, Product!$A$2:$H$501,5,FALSE) -> Taylor, Dodson and Johnston | N36: =VLOOKUP(I36, Product!$A$2:$I$501,8,FALSE) -> 176.07 | O36: =VLOOKUP(I36, Product!$A$2:$I$501,9,FALSE) -> 82 | P36: STORE18 | Q36: =VLOOKUP(P36,Store_Dim!$A$2:$E$21,2,FALSE) -> Guerrero-Schmitt | R36: =VLOOKUP(P36,Store_Dim!$A$2:$E$21,3,FALSE) -> East | S36: =VLOOKUP(P36,Store_Dim!$A$2:$E$21,4,FALSE) -> East Stevechester | T36: =VLOOKUP(P36,Store_Dim!$A$2:$E$21,5,FALSE) -> Flagship | U36: SALE1028 | V36: =VLOOKUP(Table1[[#This Row],[Sales_ID]],Sales!$A$2:$O$2001,2,FALSE) -> 45337 | W36: =VLOOKUP(Table1[[#This Row],[Sales_ID]],Sales!$A$2:$O$2001,12,FALSE) -> 1 | X36: =TEXT(VLOOKUP(Table1[[#This Row],[Sales_ID]],Sales!$A$2:$O$2001,13,FALSE),"₹#,##0") -> ₹859 | Y36: =VLOOKUP(Table1[[#This Row],[Sales_ID]],Sales!$A$2:$O$2001,14,FALSE) -> 0.16 | Z36: =VLOOKUP(Table1[[#This Row],[Sales_ID]],Sales!$A$2:$O$2001,10,FALSE) -> PayPal | AA36: =VLOOKUP(Table1[[#This Row],[Sales_ID]],Sales!$A$2:$O$2001,15,FALSE) -> 721.812
A37: CUST1129 | B37: =PROPER(VLOOKUP(A37,Customer!$A$2:$J$501,9,FALSE)) -> Jessica Mitchell | C37: =PROPER(VLOOKUP(A37,Customer!$A$2:$H$501,3,FALSE)) -> 43 | D37: =PROPER(VLOOKUP(A37,Customer!$A$2:$H$501,4,FALSE)) -> Female | E37: =PROPER(VLOOKUP(A37,Customer!$A$2:$H$501,5,FALSE)) -> Matthewbury | F37: =PROPER(VLOOKUP(A37,Customer!$A$2:$H$501,6,FALSE)) -> South Dakota | G37: =VLOOKUP(A37,Customer!$A$2:$H$501,7,FALSE) -> USA | H37: =PROPER(VLOOKUP(A37,Customer!$A$1:$J$501,10,FALSE)) -> Silver | I37: PROD81 | J37: =VLOOKUP(I37, Product!$A$2:$H$501, 2,FALSE) -> Badminton Racket Set | K37: =VLOOKUP(I37,Product!$A$2:$H$501,3,FALSE) -> Sports | L37: =VLOOKUP(I37, Product!$A$2:$H$501, 4,FALSE) -> Equipment | M37: =VLOOKUP(I37, Product!$A$2:$H$501,5,FALSE) -> Robinson-Brown | N37: =VLOOKUP(I37, Product!$A$2:$I$501,8,FALSE) -> 285.54 | O37: =VLOOKUP(I37, Product!$A$2:$I$501,9,FALSE) -> 358 | P37: STORE6 | Q37: =VLOOKUP(P37,Store_Dim!$A$2:$E$21,2,FALSE) -> Benson-Elliott | R37: =VLOOKUP(P37,Store_Dim!$A$2:$E$21,3,FALSE) -> East | S37: =VLOOKUP(P37,Store_Dim!$A$2:$E$21,4,FALSE) -> Port Josephberg | T37: =VLOOKUP(P37,Store_Dim!$A$2:$E$21,5,FALSE) -> Online | U37: SALE1029 | V37: =VLOOKUP(Table1[[#This Row],[Sales_ID]],Sales!$A$2:$O$2001,2,FALSE) -> 45564 | W37: =VLOOKUP(Table1[[#This Row],[Sales_ID]],Sales!$A$2:$O$2001,12,FALSE) -> 4 | X37: =TEXT(VLOOKUP(Table1[[#This Row],[Sales_ID]],Sales!$A$2:$O$2001,13,FALSE),"₹#,##0") -> ₹762 | Y37: =VLOOKUP(Table1[[#This Row],[Sales_ID]],Sales!$A$2:$O$2001,14,FALSE) -> 0.05 | Z37: =VLOOKUP(Table1[[#This Row],[Sales_ID]],Sales!$A$2:$O$2001,10,FALSE) -> Credit Card | AA37: =VLOOKUP(Table1[[#This Row],[Sales_ID]],Sales!$A$2:$O$2001,15,FALSE) -> 2897.234
A38: CUST1182 | B38: =PROPER(VLOOKUP(A38,Customer!$A$2:$J$501,9,FALSE)) -> Melissa Hamilton | C38: =PROPER(VLOOKUP(A38,Customer!$A$2:$H$501,3,FALSE)) -> 23 | D38: =PROPER(VLOOKUP(A38,Customer!$A$2:$H$501,4,FALSE)) -> Female | E38: =PROPER(VLOOKUP(A38,Customer!$A$2:$H$501,5,FALSE)) -> Hutchinsonville | F38: =PROPER(VLOOKUP(A38,Customer!$A$2:$H$501,6,FALSE)) -> Oklahoma | G38: =VLOOKUP(A38,Customer!$A$2:$H$501,7,FALSE) -> USA | H38: =PROPER(VLOOKUP(A38,Customer!$A$1:$J$501,10,FALSE)) -> Silver | I38: PROD34 | J38: =VLOOKUP(I38, Product!$A$2:$H$501, 2,FALSE) -> Gaming Mechanical Keyboard | K38: =VLOOKUP(I38,Product!$A$2:$H$501,3,FALSE) -> Electronics | L38: =VLOOKUP(I38, Product!$A$2:$H$501, 4,FALSE) -> Computer | M38: =VLOOKUP(I38, Product!$A$2:$H$501,5,FALSE) -> Lucero LLC | N38: =VLOOKUP(I38, Product!$A$2:$I$501,8,FALSE) -> 419.28 | O38: =VLOOKUP(I38, Product!$A$2:$I$501,9,FALSE) -> 86 | P38: STORE4 | Q38: =VLOOKUP(P38,Store_Dim!$A$2:$E$21,2,FALSE) -> Alexander Group | R38: =VLOOKUP(P38,Store_Dim!$A$2:$E$21,3,FALSE) -> South | S38: =VLOOKUP(P38,Store_Dim!$A$2:$E$21,4,FALSE) -> Port Sharon | T38: =VLOOKUP(P38,Store_Dim!$A$2:$E$21,5,FALSE) -> Online | U38: SALE103 | V38: =VLOOKUP(Table1[[#This Row],[Sales_ID]],Sales!$A$2:$O$2001,2,FALSE) -> 45907 | W38: =VLOOKUP(Table1[[#This Row],[Sales_ID]],Sales!$A$2:$O$2001,12,FALSE) -> 4 | X38: =TEXT(VLOOKUP(Table1[[#This Row],[Sales_ID]],Sales!$A$2:$O$2001,13,FALSE),"₹#,##0") -> ₹925 | Y38: =VLOOKUP(Table1[[#This Row],[Sales_ID]],Sales!$A$2:$O$2001,14,FALSE) -> 0.19 | Z38: =VLOOKUP(Table1[[#This Row],[Sales_ID]],Sales!$A$2:$O$2001,10,FALSE) -> PayPal | AA38: =VLOOKUP(Table1[[#This Row],[Sales_ID]],Sales!$A$2:$O$2001,15,FALSE) -> 2997.6156
A39: CUST1124 | B39: =PROPER(VLOOKUP(A39,Customer!$A$2:$J$501,9,FALSE)) -> Donald Lee | C39: =PROPER(VLOOKUP(A39,Customer!$A$2:$H$501,3,FALSE)) -> 26 | D39: =PROPER(VLOOKUP(A39,Customer!$A$2:$H$501,4,FALSE)) -> Male | E39: =PROPER(VLOOKUP(A39,Customer!$A$2:$H$501,5,FALSE)) -> Wongberg | F39: =PROPER(VLOOKUP(A39,Customer!$A$2:$H$501,6,FALSE)) -> Illinois | G39: =VLOOKUP(A39,Customer!$A$2:$H$501,7,FALSE) -> USA | H39: =PROPER(VLOOKUP(A39,Customer!$A$1:$J$501,10,FALSE)) -> Bronze | I39: PROD73 | J39: =VLOOKUP(I39, Product!$A$2:$H$501, 2,FALSE) -> Shin Guards – Adult | K39: =VLOOKUP(I39,Product!$A$2:$H$501,3,FALSE) -> Sports | L39: =VLOOKUP(I39, Product!$A$2:$H$501, 4,FALSE) -> Team Sports | M39: =VLOOKUP(I39, Product!$A$2:$H$501,5,FALSE) -> French Ltd | N39: =VLOOKUP(I39, Product!$A$2:$I$501,8,FALSE) -> 107.06 | O39: =VLOOKUP(I39, Product!$A$2:$I$501,9,FALSE) -> 359 | P39: STORE0 | Q39: =VLOOKUP(P39,Store_Dim!$A$2:$E$21,2,FALSE) -> Rivera-Warner | R39: =VLOOKUP(P39,Store_Dim!$A$2:$E$21,3,FALSE) -> East | S39: =VLOOKUP(P39,Store_Dim!$A$2:$E$21,4,FALSE) -> Washingtonfurt | T39: =VLOOKUP(P39,Store_Dim!$A$2:$E$21,5,FALSE) -> Flagship | U39: SALE1030 | V39: =VLOOKUP(Table1[[#This Row],[Sales_ID]],Sales!$A$2:$O$2001,2,FALSE) -> 45424 | W39: =VLOOKUP(Table1[[#This Row],[Sales_ID]],Sales!$A$2:$O$2001,12,FALSE) -> 1 | X39: =TEXT(VLOOKUP(Table1[[#This Row],[Sales_ID]],Sales!$A$2:$O$2001,13,FALSE),"₹#,##0") -> ₹329 | Y39: =VLOOKUP(Table1[[#This Row],[Sales_ID]],Sales!$A$2:$O$2001,14,FALSE) -> 0.2 | Z39: =VLOOKUP(Table1[[#This Row],[Sales_ID]],Sales!$A$2:$O$2001,10,FALSE) -> COD | AA39: =VLOOKUP(Table1[[#This Row],[Sales_ID]],Sales!$A$2:$O$2001,15,FALSE) -> 262.808
A40: CUST1274 | B40: =PROPER(VLOOKUP(A40,Customer!$A$2:$J$501,9,FALSE)) -> Sarah Lane | C40: =PROPER(VLOOKUP(A40,Customer!$A$2:$H$501,3,FALSE)) -> 38 | D40: =PROPER(VLOOKUP(A40,Customer!$A$2:$H$501,4,FALSE)) -> Male | E40: =PROPER(VLOOKUP(A40,Customer!$A$2:$H$501,5,FALSE)) -> Edwardborough | F40: =PROPER(VLOOKUP(A40,Customer!$A$2:$H$501,6,FALSE)) -> Vermont | G40: =VLOOKUP(A40,Customer!$A$2:$H$501,7,FALSE) -> USA | H40: =PROPER(VLOOKUP(A40,Customer!$A$1:$J$501,10,FALSE)) -> Silver | I40: PROD44 | J40: =VLOOKUP(I40, Product!$A$2:$H$501, 2,FALSE) -> Adjustable Jump Rope | K40: =VLOOKUP(I40,Product!$A$2:$H$501,3,FALSE) -> Sports | L40: =VLOOKUP(I40, Product!$A$2:$H$501, 4,FALSE) -> Fitness | M40: =VLOOKUP(I40, Product!$A$2:$H$501,5,FALSE) -> Cox Inc | N40: =VLOOKUP(I40, Product!$A$2:$I$501,8,FALSE) -> 167.12 | O40: =VLOOKUP(I40, Product!$A$2:$I$501,9,FALSE) -> 316 | P40: STORE4 | Q40: =VLOOKUP(P40,Store_Dim!$A$2:$E$21,2,FALSE) -> Alexander Group | R40: =VLOOKUP(P40,Store_Dim!$A$2:$E$21,3,FALSE) -> South | S40: =VLOOKUP(P40,Store_Dim!$A$2:$E$21,4,FALSE) -> Port Sharon | T40: =VLOOKUP(P40,Store_Dim!$A$2:$E$21,5,FALSE) -> Online | U40: SALE1031 | V40: =VLOOKUP(Table1[[#This Row],[Sales_ID]],Sales!$A$2:$O$2001,2,FALSE) -> 45719 | W40: =VLOOKUP(Table1[[#This Row],[Sales_ID]],Sales!$A$2:$O$2001,12,FALSE) -> 1 | X40: =TEXT(VLOOKUP(Table1[[#This Row],[Sales_ID]],Sales!$A$2:$O$2001,13,FALSE),"₹#,##0") -> ₹35 | Y40: =VLOOKUP(Table1[[#This Row],[Sales_ID]],Sales!$A$2:$O$2001,14,FALSE) -> 0.04 | Z40: =VLOOKUP(Table1[[#This Row],[Sales_ID]],Sales!$A$2:$O$2001,10,FALSE) -> COD | AA40: =VLOOKUP(Table1[[#This Row],[Sales_ID]],Sales!$A$2:$O$2001,15,FALSE) -> 33.1296
A41: CUST1105 | B41: =PROPER(VLOOKUP(A41,Customer!$A$2:$J$501,9,FALSE)) -> Lance Baker | C41: =PROPER(VLOOKUP(A41,Customer!$A$2:$H$501,3,FALSE)) -> 50 | D41: =PROPER(VLOOKUP(A41,Customer!$A$2:$H$501,4,FALSE)) -> Female | E41: =PROPER(VLOOKUP(A41,Customer!$A$2:$H$501,5,FALSE)) -> Port Victoria | F41: =PROPER(VLOOKUP(A41,Customer!$A$2:$H$501,6,FALSE)) -> Florida | G41: =VLOOKUP(A41,Customer!$A$2:$H$501,7,FALSE) -> USA | H41: =PROPER(VLOOKUP(A41,Customer!$A$1:$J$501,10,FALSE)) -> Gold | I41: PROD19 | J41: =VLOOKUP(I41, Product!$A$2:$H$501, 2,FALSE) -> Knee Support Brace | K41: =VLOOKUP(I41,Product!$A$2:$H$501,3,FALSE) -> Sports | L41: =VLOOKUP(I41, Product!$A$2:$H$501, 4,FALSE) -> Equipment | M41: =VLOOKUP(I41, Product!$A$2:$H$501,5,FALSE) -> May-Reese | N41: =VLOOKUP(I41, Product!$A$2:$I$501,8,FALSE) -> 21.34 | O41: =VLOOKUP(I41, Product!$A$2:$I$501,9,FALSE) -> 65 | P41: STORE11 | Q41: =VLOOKUP(P41,Store_Dim!$A$2:$E$21,2,FALSE) -> Aguirre-Keller | R41: =VLOOKUP(P41,Store_Dim!$A$2:$E$21,3,FALSE) -> South | S41: =VLOOKUP(P41,Store_Dim!$A$2:$E$21,4,FALSE) -> Lake Michael | T41: =VLOOKUP(P41,Store_Dim!$A$2:$E$21,5,FALSE) -> Online | U41: SALE1032 | V41: =VLOOKUP(Table1[[#This Row],[Sales_ID]],Sales!$A$2:$O$2001,2,FALSE) -> 45250 | W41: =VLOOKUP(Table1[[#This Row],[Sales_ID]],Sales!$A$2:$O$2001,12,FALSE) -> 3 | X41: =TEXT(VLOOKUP(Table1[[#This Row],[Sales_ID]],Sales!$A$2:$O$2001,13,FALSE),"₹#,##0") -> ₹664 | Y41: =VLOOKUP(Table1[[#This Row],[Sales_ID]],Sales!$A$2:$O$2001,14,FALSE) -> 0.06 | Z41: =VLOOKUP(Table1[[#This Row],[Sales_ID]],Sales!$A$2:$O$2001,10,FALSE) -> COD | AA41: =VLOOKUP(Table1[[#This Row],[Sales_ID]],Sales!$A$2:$O$2001,15,FALSE) -> 1871.7186
... A2001: CUST1421 | B2001: =PROPER(VLOOKUP(A2001,Customer!$A$2:$J$501,9,FALSE)) -> Holly Robinson | C2001: =PROPER(VLOOKUP(A2001,Customer!$A$2:$H$501,3,FALSE)) -> 45 | D2001: =PROPER(VLOOKUP(A2001,Customer!$A$2:$H$501,4,FALSE)) -> Female | E2001: =PROPER(VLOOKUP(A2001,Customer!$A$2:$H$501,5,FALSE)) -> East Amy | F2001: =PROPER(VLOOKUP(A2001,Customer!$A$2:$H$501,6,FALSE)) -> Washington | G2001: =VLOOKUP(A2001,Customer!$A$2:$H$501,7,FALSE) -> USA | H2001: =PROPER(VLOOKUP(A2001,Customer!$A$1:$J$501,10,FALSE)) -> Platinum | I2001: PROD81 | J2001: =VLOOKUP(I2001, Product!$A$2:$H$501, 2,FALSE) -> Badminton Racket Set | K2001: =VLOOKUP(I2001,Product!$A$2:$H$501,3,FALSE) -> Sports | L2001: =VLOOKUP(I2001, Product!$A$2:$H$501, 4,FALSE) -> Equipment | M2001: =VLOOKUP(I2001, Product!$A$2:$H$501,5,FALSE) -> Robinson-Brown | N2001: =VLOOKUP(I2001, Product!$A$2:$I$501,8,FALSE) -> 285.54 | O2001: =VLOOKUP(I2001, Product!$A$2:$I$501,9,FALSE) -> 358 | P2001: STORE8 | Q2001: =VLOOKUP(P2001,Store_Dim!$A$2:$E$21,2,FALSE) -> Bean, Jones and Park | R2001: =VLOOKUP(P2001,Store_Dim!$A$2:$E$21,3,FALSE) -> West | S2001: =VLOOKUP(P2001,Store_Dim!$A$2:$E$21,4,FALSE) -> Thompsonborough | T2001: =VLOOKUP(P2001,Store_Dim!$A$2:$E$21,5,FALSE) -> Online | U2001: SALE999 | V2001: =VLOOKUP(Table1[[#This Row],[Sales_ID]],Sales!$A$2:$O$2001,2,FALSE) -> 45304 | W2001: =VLOOKUP(Table1[[#This Row],[Sales_ID]],Sales!$A$2:$O$2001,12,FALSE) -> 4 | X2001: =TEXT(VLOOKUP(Table1[[#This Row],[Sales_ID]],Sales!$A$2:$O$2001,13,FALSE),"₹#,##0") -> ₹23 | Y2001: =VLOOKUP(Table1[[#This Row],[Sales_ID]],Sales!$A$2:$O$2001,14,FALSE) -> 0.27 | Z2001: =VLOOKUP(Table1[[#This Row],[Sales_ID]],Sales!$A$2:$O$2001,10,FALSE) -> PayPal | AA2001: =VLOOKUP(Table1[[#This Row],[Sales_ID]],Sales!$A$2:$O$2001,15,FALSE) -> 65.7292

Sheet Cal
B3: Total number Of Sales in Online | E3: =SUMIF('Cleaned Table'!T89:T2001,"Online",'Cleaned Table'!AA2:AA2001) -> 826134.31
B4: Total number Of Sales in Outlet | E4: =SUMIF('Cleaned Table'!T89:T2001,"Outlet",'Cleaned Table'!AA2:AA2001) -> 392520.32
B5: Total number Of Sales in Flagship | E5: =SUMIF('Cleaned Table'!T89:T2001,"Flagship",'Cleaned Table'!AA2:AA2001) -> 849226.23
B6: Number of Purchase by Male customer | E6: =COUNTIF('Cleaned Table'!D2:D2001,"Male") -> 904
B7: Number of Purchase by Female customer | E7: =COUNTIF('Cleaned Table'!D2:D2001,"Female") -> 1096
B8: Number of Customer From North Region | E8: =COUNTIF('Cleaned Table'!R2:R2001,"North") -> 596
B9: Average No of Sales in Store 1 | E9: =AVERAGEIF(Table1[[#All],[Store_ID]],"STORE1",Table1[[#All],[Total_Amount]]) -> 1075.1129
B10: Mean of quantity | E10: =AVERAGE('Cleaned Table'!W2:W2001) -> 2.4801238
B11: Mode of Quantity | E11: =MODE('Cleaned Table'!W2:W2001) -> 2

Sheet Pivot Table
A2: Gender wise Total Number of Sales | D2: Payment Method Wise Average Of Discount | H2: State wise Loyaly Level
A3: Row Labels | B3: Sum of Total_Amount | D3: Row Labels | E3: Average of Discount | H3: Row Labels | I3: Count of Loyalty_Level
A4: Female | B4: 1231444.2 | D4: COD | E4: 0.1485303 | H4: Alabama | I4: 46
A5: Male | B5: 943206.94 | D5: Credit Card | E5: 0.15047439 | H5: Alaska | I5: 41 | Z5: Summary
A6: Grand Total | B6: 2174651.2 | D6: PayPal | E6: 0.14556919 | H6: Arizona | I6: 41 | Z6: I created pivot table and created charts for
D7: Grand Total | E7: 0.14812829 | H7: Arkansas | I7: 26 | Z7: gender wise sales, payment method wise sales,
H8: California | I8: 53 | Z8: Date wise sales, state wise loyalty, region wise sales, store wise sales
H9: Colorado | I9: 8
A10: Region Wise Total Percentage of Sales | D10: Date wise Total Number Of Sales | H10: Connecticut | I10: 55
A11: Row Labels | B11: Sum of Total_Amount | D11: Row Labels | E11: Sum of Total_Amount | H11: Delaware | I11: 32
A12: East | B12: 622009.12 | D12: Jan | E12: 174449.14 | H12: Florida | I12: 52
A13: North | B13: 646752.54 | D13: 2024 | E13: 82463.042 | H13: Georgia | I13: 50
A14: South | B14: 635213.1 | D14: 2025 | E14: 91986.098 | H14: Hawaii | I14: 32
A15: West | B15: 270676.41 | D15: Feb | E15: 155073.94 | H15: Idaho | I15: 11
A16: Grand Total | B16: 2174651.2 | D16: 2024 | E16: 83018.279 | H16: Illinois | I16: 30
D17: 2025 | E17: 72055.66 | H17: Indiana | I17: 39
D18: Mar | E18: 210704.52 | H18: Iowa | I18: 47
A19: Store wise Average Number of Sales | D19: 2024 | E19: 103115.66 | H19: Kansas | I19: 47
A20: Row Labels | B20: Average of Total_Amount | D20: 2025 | E20: 107588.86 | H20: Kentucky | I20: 25
A21: Aguirre-Keller | B21: 1057.3652 | D21: Apr | E21: 192864.04 | H21: Louisiana | I21: 39
A22: Alexander Group | B22: 1164.8443 | D22: 2024 | E22: 90470.731 | H22: Maine | I22: 36
A23: Bean, Jones and Park | B23: 1251.7438 | D23: 2025 | E23: 102393.3 | H23: Maryland | I23: 28
A24: Benson-Elliott | B24: 1080.5075 | D24: May | E24: 146511.96 | H24: Massachusetts | I24: 21
A25: Black-Horn | B25: 1075.661 | D25: 2024 | E25: 57825.221 | H25: Michigan | I25: 45
A26: Frederick-Wright | B26: 1053.8202 | D26: 2025 | E26: 88686.742 | H26: Minnesota | I26: 40
A27: Gardner, Humphrey and Contreras | B27: 1204.226 | D27: Jun | E27: 162640.02 | H27: Mississippi | I27: 23
A28: Gray Ltd | B28: 987.19574 | D28: 2024 | E28: 97004.005 | H28: Missouri | I28: 34
A29: Guerrero-Schmitt | B29: 993.45766 | D29: 2025 | E29: 65636.012 | H29: Montana | I29: 37
A30: Hill, Wagner and Ballard | B30: 1128.2979 | D30: Jul | E30: 195305.47 | H30: Nebraska | I30: 22
A31: Holloway Ltd | B31: 1111.2232 | D31: 2024 | E31: 93582.269 | H31: Nevada | I31: 55
A32: Johnson-Wright | B32: 1096.595 | D32: 2025 | E32: 101723.2 | H32: New Hampshire | I32: 57
... A41: Grand Total | B41: 1087.3256 | D41: 2024 | E41: 102567.65 | H41: Pennsylvania | I41: 46
D42: 2025 | E42: 38467.816 | H42: Rhode Island | I42: 29
D43: Nov | E43: 187386.17 | H43: South Carolina | I43: 34
D44: 2023 | E44: 84402.869 | H44: South Dakota | I44: 40
D45: 2024 | E45: 102983.3 | H45: Tennessee | I45: 51
D46: Dec | E46: 183212.99 | H46: Texas | I46: 22
D47: 2023 | E47: 94335.117 | H47: Utah | I47: 38
D48: 2024 | E48: 88877.871 | H48: Vermont | I48: 60
D49: Grand Total | E49: 2174651.2 | H49: Virginia | I49: 47
H50: Washington | I50: 43
H51: West Virginia | I51: 51
H52: Wisconsin | I52: 39
H53: Wyoming | I53: 23
H54: Grand Total | I54: 2000

Sheet Dashboard
I2: E-Commerce Sales Insights And Analysis

Sheet Summary
A1: Summary
A2: 1)I use trim and proper formula to correct the name
A3: 2)I use if, index, match formula to take mode for loyalty level
A4: 3) C-1486, C-1491, C-1496,… are corrected by using find and replace
A5: 4)Cost and Stock finded by if formula
A6: 5)P3,P16 change to PROD3, PROD16 by find and replace
A7: 6)use if, iferror, averageif to find quantity, unit price,
A8: discount, total amount of missing values
A9: 7) used text formula to makes rupees in unit price
A10: 8) I find summary statistics using analysis toolpak
A11: 9)use vlookup to bring
A12: columns from the other sheet
... A16: Date wise sales, state wise loyalty, region wise sales, store wise sales
